Workbook

Sheet Readme
B1: # INTRODUCTION
C2: The Management Spreadsheet (MSS) is a Software built in LibreOffice and saved as Excel xlsx file.
C3: It is considered a Tool and integral part of the *Management Framework* as discused in the note MGT: Legend.
C4: This software can be used on a standalone basis but its strength is in use with the MGT: xxx notes.
C5: The software can be found wihtin the management file structure in the following location: ~/mgt/mgt.xlsx
C7: MSS is the same for perso and work context, and the master of the functionality is maintained in the perso context.
C8: As per the license, see below, the software can be used freely, but it is stressed here that that free distribution only pertains to concepts and functionality.
C9: In other words, data collected in the spreadsheet is confidential for the context used, and even specific to the Venture.
C11: In order to use this file efficiently the key concepts of the Management Framework need to be understood.
C12: These concepts are discussed in the note MGT: Legend. The implementation of the concepts through Tools is discussed in note MGT: 99.Tools.
C14: All sheets in MSS are functionally the same in perso and work context with one exception (see further below).
C15: This in turn means they seek to collect the same data types and to calculate the same values.
C17: Sheets have tab colors that indicate the type of sheet they are, they are explained below in [# SHEETS].
... C26: Details are provided below under [# COLUMNS]
B29: # LICENSE
C30: The license of this software is as per [MGT: Legend # LICENSE]. It is repeated here.
C31: MSS is a Tool for the implementation of the Management Framework based on [MGT: Legend # PROFILE] and [MGT: 99.Tools ## MSS].
C33: Copyright (c) 2022 Sander Elzinga, sander.elzinga@gmail.com
C35: This program is free software: you can redistribute it and/or modify
C36: it under the terms of the GNU General Public License as published by
C37: the Free Software Foundation, either version 3 of the License, or
C38: (at your option) any later version.
C40: This program is distributed in the hope that it will be useful,
C41: but WITHOUT ANY WARRANTY; without even the implied warranty of
C42: MERCHANTABILITY or FITNESS FOR A PARTICULAR PURPOSE. See the
C43: GNU General Public License for more details.
C45: You should have received a copy of the GNU General Public License
... C50: *) Data is the data entered in addition to the formulas, static data, headers, and in addition of the data already provided in the master file.
B53: # SHEETS
B54: ## Overview
C55: Sheets are aligned to specific parts of the [MGT: 99.Tools ## RPT] and have therefore specific tab colours.
C56: The list of sheets are provided below with an explanation.
C57: Most sheets have a first Row that explains for each column in the Row what the undelrying data is.
C58: This makes each sheet self explanatory because it suffices to read the details in the first row.
C60: Readme | E60: This sheet. It explains what the MSS file does.
C61: PT_xxx | E61: Sheet names starting with PT_ is a Pivot Table report for a specific purpose, there can be many sheets.
C62: M0 | E62: Mangerial 7 nr 0: Management
C63: M1 | E63: Mangerial 7 nr 1: Revenue
C64: M2 | E64: Mangerial 7 nr 2: Cost
C65: M3 | E65: Mangerial 7 nr 3: Risk
C66: M4 | E66: Mangerial 7 nr 4: Run
C67: M5 | E67: Mangerial 7 nr 5: Change
C68: M6 | E68: Mangerial 7 nr 6: Intel
C69: 5.Staff | E69: RPT Component with details from Resource =Staff
C70: 6.Assets | E70: RPT Component with details from Resource = Assets
C71: 7.Supplier | E71: RPT Component with details from Resource = Suppliers
... C76: Static | E76: Contains static data used on other sheets
B78: ## Using Sheets
C80: M0 – M6
C81: Refer to [MGT: 99.Tools ## Mxx
C83: 11.Staff
C84: Data in Sheet = 5.Staff represents details of each Staff used within the Venture. They can be internal and external.
C86: Note that all Resources (Suppliers, Assets, Stafff) have a column called Parent which permits defining a hierarchy within each Resource.
C88: 12.Assets
C89: Data in Sheet = 6.Assets represents details of each Asset used within the Venture. They can be internal and external.
C90: This excludes data that is maintained by the Staff that responsbilities have been delegated to.
C92: 13.Supplier
C93: Data in Sheet = 7.Supplier represents details of each Supplier used within the Venture. They can be internal and external.
C94: This excludes data that is maintained by the Staff that responsbilities have been delegated to.
C97: Static
C98: Static data contains items used to select content of a Cell using “Validity”/ “Data Validation” of LibreOffice/Excel within other Sheets
B101: # COLUMNS
C102: There is a specific color coding format logic to Column Headers as per below:
C104: Grey witih white Text | E104: Default format of all column headers that are part of the License (see above) and that should be available in perso and work context.
C105: Blue with white text | E105: This column contains data that is specific to the Venture and that does not need to be available in both perso and work context.
B108: # VERSIONING
C109: 0.0.0 | D109: 20211007 | E109: Initital creation of the file
C110: 0.0.1 | D110: =D109 -> 20211007 | E110: Added Sheet=’Plan’ and Sheet=’Static’ and first stab at ‘Plan” logic based on [MGT: Tools ## Gantt Chart].
C111: 1.0.0 | D111: 20211014 | E111: Replaced ‘Plan’ with ‘Tactica‘ and added the full Gantt Chart logic. Tested in production environment at work.
E112: - Columns with final values and columns with T_ values (grouped together so as to hide in production)
E113: - Columns with conditional formatting based on T_ columns
E114: NB: Borders do not work well when saving as an xlsx file !
C115: 1.0.1 | D115: 20211015 | E115: Added ‘# LICENSE’ in this sheet
C116: 1.0.2 | D116: 20211015 | E116: Added Column ‘Status’ in Planning
C117: 1.0.3 | D117: 20211015 | E117: Added T_Ettor logic and a column ‘!’ to reflect a red ‘!’ if T_Error != none.
C118: 1.0.4 | D118: 20211015 | E118: Added current month indicator
C119: 1.0.5 | D119: 20211016 | E119: Updated formatting of Gantt Colors and changed Bold to Normal for Column headers
C120: 1.0.6 | D120: 20211016 | E120: Changed ‘chg’ to ‘Change’ so that it correctly reflects the [MGT: Legend] notion of Run and Change. All formulas updated too.
C121: 1.0.7 | D121: 20211016 | E121: First stab at Sheet = Operational
C122: 1.1.0 | D122: 20211017 | E122: Finalised Sheet=Operational
C123: 1.2.0 | D123: 20211018 | E123: Various improvements to Sheet = Tactical and bug-fiex. Notably: account for ‘*’ in input data *which resolves against the first occurence of a lookup table! Also, default Owener is ‘SE’.
C124: 1.2.1 | D124: 20211019 | E124: Updated T_NetStatus to be simpler (only possible status = “Overdue” or the Value from “T_Status).
E125: Updated SortM to sort such that within a Goal it sorts on Owner first.
E126: Updated SortA to reflect 0,1, 4 or empty. So that by sorting them, all Cells in Column A with some data are all below Total / Change / Run and below eachother: easier to delete all data.
E127: Updated T_Color to become ‘Amber’ if T_NetStatus = Started + also Pending or Urgent
E128: Added a Color Legend
E129: Added Stats per ‘Who’ in hidden columns
E130: Updated Sheet = Operational to use only one single Month (Jan) using a INDIRECT formula.
C131: 1.2.2 | D131: 20211020 | E131: Corrected bug fix (circular reference) in Sheet = Operational. Updated col OO in Sheet = Tactical to also flag as ‘&’ if Ptype = Routine
C132: 1.2.3 | D132: 20211022 | E132: Sheet=Tactical: Update Col T_EffortEstimated to 0 if Col Lvl >3.
E133: Sheet=Tactical: Update Col Who to TRIM output, same for Col Freq
E134: Sheet=Tactical: Add more useful stats in hidden rows/cols section including breakdown %Routine.
E135: Sheet=Operational: updated formatting for Private Holidays to be white text for AM and PM (was black). Updated Procedures to Copy paste formats after inserting rows!!!
C136: 1.2.4 | D136: 20211029 | E136: Sheet=Tactical: Update Col Description to use TRIM(SUBSTITUTE(M37,IF(E37="",""," "&E37),"") i/o TRIM(SUBSTITUTE(M37,E37,"")) to avoid that “COO” would be substited with “” if the T_OO col = OO
C137: 1.2.5 | D137: 20211105 | E137: Sheet=Tactical. Update Col=SOrtM and replace the reference to Col=Who (Hxx) with Col=Start (Aixx)
E138: Sheet=Tactical bugfix Col=Start : IF T_Start > T_End then T_End else T_Start,. This is to avoid cases where completed tasks seem to start after the end date if there is only one date in (...)
E139: Sheet=Tactical: bugfix Col = End: IF T_Complete = “none” T_End else T_Complete. This is to assure that a Project that is completed gets as End date the completion date.
C140: 1.2.6 | D140: 20211117 | E140: Sheet=Tactical move ‘!’ column before column LvL. Group all collums from Value to Lvl so they don’t appear in Reports
C141: 2.0.0 | D141: 20220110 | E141: Complete overhaul to have the entire MGT: xxx strcture embedded in an excel file.
E142: Creation of new Sheets: Planning (Goals &Objectives – Routines, Projects-), Organising (Activities & Groups), Suppliers, Assets
...

Sheet PT_templ
A1: Sort | B1: - all -
A2: Item Type | B2: - all -
A3: Lvl | B3: - all -
A5: Self | B5: Hold Date | C5: Self+1 Pty | D5: Key | E5: Sum - Effort
A6: (empty) | B6: (empty) | C6: 0 | D6: (empty) | E6: 0
A7: VNT | B7: (empty) | C7: 0 | D7: VNT | E7: 1
A8: Action Some Action for the Study | B8: (empty) | C8: 45658 | D8: Action Some Action for the Study | E8: 0
A9: Chg GoalDMM | B9: (empty) | C9: 0 | D9: Chg GoalDMM | E9: 0
A10: Chg GoalEMM | B10: (empty) | C10: 0 | D10: Chg GoalEMM | E10: 0
A11: ProjectSome Study Project for sub-cat 1 | B11: (empty) | C11: 0 | D11: ProjectSome Study Project for sub-cat 1 | E11: 0
A12: ProjectSome Study Project for sub-cat 2 | B12: (empty) | C12: 0 | D12: ProjectSome Study Project for sub-cat 2 | E12: 0
A13: Stream Some Stream of the project | B13: (empty) | C13: 45658 | D13: Stream Some Stream of the project | E13: 0
A14: Total Result | E14: 1

Sheet Tracker
BW1: x
BW2: x
BW3: x
A4: =A3 -> 0 | B4: =B3 -> 0 | C4: =C3 -> 0 | D4: =D3 -> 0 | E4: =E3 -> 0 | F4: =F3 -> 0 | G4: =G3 -> 0 | H4: =H3 -> 0 | ... R4: =R3 -> 0 | Z4: =Z3 -> 0 | AB4: =AB3 -> 0 | AC4: =AC3 -> 0 | AD4: =AD3 -> 0 | AE4: =AE3 -> 0 | AF4: =AF3 -> 0 | AG4: =AG3 -> 0 | AH4: =AH3 -> 0 | AI4: =AI3 -> 0 | ... AK4: =AK3 -> 0 | BW4: =BW3 -> x
BW5: x
BW6: x
BW7: x
BW15: x
BW16: x
BW17: x
BW18: x
BW19: x
BW20: x
A21: =TODAY() -> 46321 | B21: Calculated. First Note of Column = Notes. | C21: Calculated. Last Note -f Column = Notes. | D21: Calculated. Date of First NoTe from Column = First Note. | E21: Calculated. Date of Last Note from Column = Last Note. | F21: Calculated. Date of the Last Note or epoch based on Col = Notes. | G21: Calcualted. Time between Last Date and Start Date. | H21: Calculated. Nr Tasks in Status indicated by name of this Column. The IF() is to account for the fact that typing anything at the start of a cell is not preceded the <ENTER> Character CHAR(10). | I21: Calculated. Nr Tasks in Status indicated by name of this Column. The IF() is to account for the fact that typing anything at the start of a cell is not preceded the <ENTER> Character CHAR(10). | J21: Calculated. Nr Tasks in Status indicated by name of this Column. The IF() is to account for the fact that typing anything at the start of a cell is not preceded the <ENTER> Character CHAR(10). | K21: Calculated. Nr Tasks in Status indicated by name of this Column. The IF() is to account for the fact that typing anything at the start of a cell is not preceded the <ENTER> Character CHAR(10). | L21: Calculated. Nr Tasks in Status indicated by name of this Column. The IF() is to account for the fact that typing anything at the start of a cell is not preceded the <ENTER> Character CHAR(10). | M21: Calaculated. Sum of all Tasks in Tasks. | N21: Calcualted. Whether the Last Date was within X weeks of the Monday of the week of the date in cell $D$2. | O21: Calculated. Assures Tracking Type = Management is at the top, then Routines, then Projects that are Roadmap items, then Projects and then the rest of the entries. | P21: Calculated. Whether the Jounral entry is reportable based on whether the Last Date is newer than the monday X weeks ago, with X determined in Cell $D$2. | Q21: Optional. Can force the reporting of a Journal Entry if the defaulting rules would (not) report an entry. | R21: Optional. Tag the entry for specific filtering. The value can be freely chosen. It is possible to have multiple comma-separated values. This column is an incredibly powerful feature of the entire sheet. | S21: Whom For Level 1. Mandatory. The Beneficiery. The Activity for which this is performed. The Default = the entire Venture VNT. | X21: Optional: This column has a drop-down which is based on the value in the column to the left i.e. Sub-Goal depends on Goal. | Z21: Mandatory. In theory several options possible, but choose only “Routine”. | AB21: Mandatory. 6W = What: part 1 of Name. Name is preferably unique within the Tracking Type and should start with a Verb. Verbs are an indication of targeted Result, see [MGT: 99. Tools ## Objective Definition]: - Assist: somebody in execution of their Process - Attend: prepare and attend a meeting - Build: something new from scratch - Complete: something started elsewhere/prior - Create: same as Build - Define: a Target/expected Result, next Build/Create - Deploy: as new something existing elsewhere - Expand: something existing by adding to it - Improve: something existing by automation etc. - Increase: something existing by a numeric value - Learn: something that may become important later on - Maintain: something existing at current level - Meet: someone on regular or ad-hoc basis - Perform: one or more specific Processes - Prepare: a deliverable for completion elsewhere - Process: take in a request and deliver Result - React to: a situation with specific measures - Report to: Staff, Manager, Committee via mail - Resolve: Problems - Review: Result vs Target + assess if change needed - Rewrite: an existing document | AC21: Optional. 6W = How: Details of how the Routine is achieved. | AD21: Mandatory. Notes drive two columns: Start Date and Last Date. Format for each line: dd-mm-yy: xxx in which dd, mm and yy are day, month and year and xxx is free text. | AE21: Optional. Tasks with individual Status. Multiple entries are possible. In combination with Column = Updated this column helps in Reporting. Items follow the Objective Notation as per [MGT: 99.Tools ## Objective Notation] i.e. Status Description (start:end:complete) {who} [ref] NB: Goal end Effort are not relevant for this Column. Used in Formulas. | AF21: Calculated. Nr non-completed Tasks. | AG21: Calculated. Nr Tasks non-completed Tasks over total nr Tasks as %. | AH21: Mandatory. The frequency type of the Routine, based on a drop-down list maintained in Sheet=Static. | AI21: Mandatory. The number of times the Routine is done throughout a year. This is partially linked to Period (label): Day -> 260 (without holidays), 220 (with holidays) Week -> 52 (without holidays), 48 (with full week holidays) Month -> 12 Quarterly -> 4 Semi-annually -> 2 Annually -> 1 Ad-hoc -> this is determined by the user depending on expetations based on past or current information | AJ21: Mandatory. THe amount of hours worked on each time the Routine is performed. | AK21: Calculated. Total nr of 8-hour days the ROutine takes. | AL21: When | AM21: When | AN21: When | AO21: When | AP21: When | AQ21: Custom Field 1 | AR21: Custom Field 2 | AS21: Custom Field 3 | AT21: Custom Field 4 | AU21: Custom Field 5 | AV21: Custom Field 6 | AW21: Custom Field 7 | AX21: Custom Field 8 | AY21: Custom Field 9 | AZ21: Custom Field 10 | BA21: Custom Field 11 | BB21: Custom Field 12 | BC21: Custom Field 13 | BD21: Custom Field 14 | BE21: Custom Field 15 | BF21: Custom Field 16 | BG21: Custom Field 17 | BH21: Custom Field 18 | BI21: Custom Field 19 | BJ21: Custom Field 20 | BW21: Last Column. Contains value = “X”.
F22: 1 | AG22: ## This indicates that Today is in the Month below → | BK22: =IF(AND($A$21>BK23,$A$21<(DATE(YEAR(BK23),MONTH(BK23),DAY(EOMONTH(DATE(YEAR(BK23),MONTH(BK23),1),0))))),1,0) -> 0 | BL22: =IF(AND($A$21>BL23,$A$21<(DATE(YEAR(BL23),MONTH(BL23),DAY(EOMONTH(DATE(YEAR(BL23),MONTH(BL23),1),0))))),1,0) -> 0 | BM22: =IF(AND($A$21>BM23,$A$21<(DATE(YEAR(BM23),MONTH(BM23),DAY(EOMONTH(DATE(YEAR(BM23),MONTH(BM23),1),0))))),1,0) -> 0 | BN22: =IF(AND($A$21>BN23,$A$21<(DATE(YEAR(BN23),MONTH(BN23),DAY(EOMONTH(DATE(YEAR(BN23),MONTH(BN23),1),0))))),1,0) -> 0 | BO22: =IF(AND($A$21>BO23,$A$21<(DATE(YEAR(BO23),MONTH(BO23),DAY(EOMONTH(DATE(YEAR(BO23),MONTH(BO23),1),0))))),1,0) -> 0 | BP22: =IF(AND($A$21>BP23,$A$21<(DATE(YEAR(BP23),MONTH(BP23),DAY(EOMONTH(DATE(YEAR(BP23),MONTH(BP23),1),0))))),1,0) -> 0 | BQ22: =IF(AND($A$21>BQ23,$A$21<(DATE(YEAR(BQ23),MONTH(BQ23),DAY(EOMONTH(DATE(YEAR(BQ23),MONTH(BQ23),1),0))))),1,0) -> 0 | BR22: =IF(AND($A$21>BR23,$A$21<(DATE(YEAR(BR23),MONTH(BR23),DAY(EOMONTH(DATE(YEAR(BR23),MONTH(BR23),1),0))))),1,0) -> 0 | ... BV22: =IF(AND($A$21>BV23,$A$21<(DATE(YEAR(BV23),MONTH(BV23),DAY(EOMONTH(DATE(YEAR(BV23),MONTH(BV23),1),0))))),1,0) -> 0
A23: A | B23: First Note | C23: Last Note | D23: First Note Date | E23: Last Note Date | F23: Last Date | G23: Duration | H23: Tasks Open | I23: Tasks Started | J23: Tasks Pending | K23: Tasks Urgent | L23: Tasks Done | M23: Tasks Total | N23: Last wk? | O23: Sort | P23: Rep ? | Q23: Force Rep? | R23: Tag | S23: Whom for lvl1 | T23: Whom for lvl2 | U23: Whom By Lvl1 | V23: Whom By Lvl2 | W23: Goal | X23: Sub-Goal | Y23: Initiative | Z23: Planning Type | AA23: Status | AB23: Name | AC23: Details: | AD23: Notes | AE23: Tasks | AF23: Tasks Left | AG23: Task Progress | AH23: Period (label) | AI23: Period (count) | AJ23: Effort / count (hr) | AK23: Effort / yr (days) | AL23: Start Date | AM23: End Date | AN23: Hold Date | AO23: Complete Date | AP23: Effort / project (days) | AQ23: Custom Field 1 | AR23: Custom Field 2 | AS23: Custom Field 3 | AT23: Custom Field 4 | AU23: Custom Field 5 | AV23: Custom Field 6 | AW23: Custom Field 7 | AX23: Custom Field 8 | AY23: Custom Field 9 | AZ23: Custom Field 10 | BA23: Custom Field 11 | BB23: Custom Field 12 | BC23: Custom Field 13 | BD23: Custom Field 14 | BE23: Custom Field 15 | BF23: Custom Field 16 | BG23: Custom Field 17 | BH23: Custom Field 18 | BI23: Custom Field 19 | BJ23: Custom Field 20 | BK23: 45658 | BL23: 45689 | BM23: 45717 | BN23: 45748 | BO23: 45778 | BP23: 45809 | BQ23: 45839 | BR23: 45870 | BS23: 45901 | BT23: 45931 | BU23: 45962 | BV23: 45992 | BW23: Z
A24: =A23 -> A | B24: =B23 -> First Note | C24: =C23 -> Last Note | D24: =D23 -> First Note Date | E24: =E23 -> Last Note Date | F24: =F23 -> Last Date | G24: =G23 -> Duration | H24: =H23 -> Tasks Open | ... Q24: =Q23 -> Force Rep? | S24: =S23 -> Whom for lvl1 | T24: =T23 -> Whom for lvl2 | U24: =U23 -> Whom By Lvl1 | V24: =V23 -> Whom By Lvl2 | W24: =W23 -> Goal | X24: =X23 -> Sub-Goal | Y24: =Y23 -> Initiative | Z24: =Z23 -> Planning Type | ... BK24: =BK23 -> 45658 | BW24: =BW23 -> Z
B25: =IF(AD25="","",IF(ISERROR(FIND(CHAR(10),AD25,1)),AD25,LEFT(AD25,FIND(CHAR(10),AD25,1)))) -> 03-01-22: init | C25: =IF(AD25="","",IFERROR(RIGHT(AD25,LEN(AD25)-FIND("@@@",SUBSTITUTE(AD25,CHAR(10),"@@@",LEN(AD25)-LEN(SUBSTITUTE(AD25,CHAR(10),""))),1)),AD25)) -> 03-01-22: init | D25: =IFERROR(DATE(("20"&MID(B25,7,2))*1,MID(B25,4,2)*1,MID(B25,1,2)*1),"") -> 44564 | E25: =IFERROR(DATE(("20"&MID(C25,7,2))*1,MID(C25,4,2)*1,MID(C25,1,2)*1),"") -> 44564 | F25: =MAX(D25,IF(E25="none",D25,E25)) -> 44564 | G25: =IFERROR(DAYS360(D25,F25),0) -> 0 | H25: =((LEN($AE25)-LEN(SUBSTITUTE($AE25,CHAR(10)&". ","")))/3)+IF(LEFT(TRIM($AE25),2)=". ",1,0) -> 0 | I25: =((LEN($AE25)-LEN(SUBSTITUTE($AE25,CHAR(10)&"/ ","")))/3)+IF(LEFT(TRIM($AE25),2)="/ ",1,0) -> 0 | J25: =((LEN($AE25)-LEN(SUBSTITUTE($AE25,CHAR(10)&"~ ","")))/3)+IF(LEFT(TRIM($AE25),2)="~ ",1,0) -> 0 | K25: =((LEN($AE25)-LEN(SUBSTITUTE($AE25,CHAR(10)&"! ","")))/3)+IF(LEFT(TRIM($AE25),2)="! ",1,0) -> 0 | L25: =((LEN($AE25)-LEN(SUBSTITUTE($AE25,CHAR(10)&"x ","")))/3)+IF(LEFT(TRIM($AE25),2)="x ",1,0) -> 0 | M25: =SUM(H25:L25) -> 0 | N25: =IF(F25>(($A$21-WEEKDAY($A$21,2))-7*$F$22),"Y","N") -> N | O25: =IF(AB25=""," - ZZZ"," - "&X25&Y25&AB25) -> - 00.managementGeneral Management00.Maintain Management | P25: =IF(AB25="","",(IF(OR(Q25="Y",Q25="N"),Q25,IF(N25="Y","Y","N")))) -> N | Q25: N | S25: VNT | T25: _all | U25: n/a | V25: Sander | W25: mgt | X25: 00.management | Y25: General Management | Z25: Routine | AA25: Started | AB25: 00.Maintain Management | AC25: Details: # INTRODUCTION Details of this management item are in the Management Framework. | AD25: 03-01-22: init | AE25: ## Generic Routines & Maintain MSS [this file] & Maintain Management Framework [the local implementation of the public domain version of the Management Framework] & Maintain Management Approach [## Management Approach] ________________________________________ ## Management Approach ## _END | AF25: =IF(AB25="","",SUM(H25:K25)) -> 0 | AG25: =IF(AB25="","",IF(M25<>0,(I25*0.5+L25)/M25,1)) -> 1 | AH25: Ad-hoc | AK25: =IF(AB25="","",AI25*AJ25/8) -> 0 | BW25: z
B26: =IF(AD26="","",IF(ISERROR(FIND(CHAR(10),AD26,1)),AD26,LEFT(AD26,FIND(CHAR(10),AD26,1)))) -> 03-01-22: init | C26: =IF(AD26="","",IFERROR(RIGHT(AD26,LEN(AD26)-FIND("@@@",SUBSTITUTE(AD26,CHAR(10),"@@@",LEN(AD26)-LEN(SUBSTITUTE(AD26,CHAR(10),""))),1)),AD26)) -> 03-01-22: init | D26: =IFERROR(DATE(("20"&MID(B26,7,2))*1,MID(B26,4,2)*1,MID(B26,1,2)*1),"") -> 44564 | E26: =IFERROR(DATE(("20"&MID(C26,7,2))*1,MID(C26,4,2)*1,MID(C26,1,2)*1),"") -> 44564 | F26: =MAX(D26,IF(E26="none",D26,E26)) -> 44564 | G26: =IFERROR(DAYS360(D26,F26),0) -> 0 | H26: =((LEN($AE26)-LEN(SUBSTITUTE($AE26,CHAR(10)&". ","")))/3)+IF(LEFT(TRIM($AE26),2)=". ",1,0) -> 0 | I26: =((LEN($AE26)-LEN(SUBSTITUTE($AE26,CHAR(10)&"/ ","")))/3)+IF(LEFT(TRIM($AE26),2)="/ ",1,0) -> 0 | J26: =((LEN($AE26)-LEN(SUBSTITUTE($AE26,CHAR(10)&"~ ","")))/3)+IF(LEFT(TRIM($AE26),2)="~ ",1,0) -> 0 | K26: =((LEN($AE26)-LEN(SUBSTITUTE($AE26,CHAR(10)&"! ","")))/3)+IF(LEFT(TRIM($AE26),2)="! ",1,0) -> 0 | L26: =((LEN($AE26)-LEN(SUBSTITUTE($AE26,CHAR(10)&"x ","")))/3)+IF(LEFT(TRIM($AE26),2)="x ",1,0) -> 0 | M26: =SUM(H26:L26) -> 0 | N26: =IF(F26>(($A$21-WEEKDAY($A$21,2))-7*$F$22),"Y","N") -> N | O26: =IF(AB26=""," - ZZZ"," - "&X26&Y26&AB26) -> - 01.planningGeneral Management00.Maintain Planning | P26: =IF(AB26="","",(IF(OR(Q26="Y",Q26="N"),Q26,IF(N26="Y","Y","N")))) -> N | Q26: N | S26: VNT | T26: _all | U26: n/a | V26: Sander | W26: mgt | X26: 01.planning | Y26: General Management | Z26: Routine | AA26: Started | AB26: 00.Maintain Planning | AC26: Details: # INTRODUCTION Details of this management item are in the Management Framework. | AD26: 03-01-22: init | AE26: ## Generic Routines & 01.Maintain Business Model [## Business Model] & 02.Maintain Purpose [## Purpose] & 03.Maintan Vision [## Vision] & 04.Maintain Mission [## Mission] & 05.Maintain Values [## Values] & 06.Maintain Bylaws [## Bylaws] & 07.Maintain SWOT [## SWOT] & 08.Maintain Goals [## Goals] & 09.Maintain Objectives [## Objectives] & 10.Maintain Tasks [## Tasks] & 11.Maintain Benchmarks [## Benchmarks] & 12.Maintain Strategic Plan [## Strategic Plan] & 13.Maintain Tactical Plan [## Tactical Plan] & 14. Maintain Operational Plan [## Operational Plan] & 15.Maintain Intel [## Intel] ________________________________________ ## Business Model ________________________________________ ## Purpose ________________________________________ ## Vision ________________________________________ ## Mission ________________________________________ ## Values ________________________________________ ## Bylaws ________________________________________ ## SWOT ________________________________________ ## Goals ________________________________________ ## Objectives ________________________________________ ## Tasks ________________________________________ ## Benchmarks ________________________________________ ## Strategic Plan ________________________________________ ## Tactical Plan ________________________________________ ## Operational Plan ________________________________________ ## Intel ## _END | AF26: =IF(AB26="","",SUM(H26:K26)) -> 0 | AG26: =IF(AB26="","",IF(M26<>0,(I26*0.5+L26)/M26,1)) -> 1 | AH26: Ad-hoc | AK26: =IF(AB26="","",AI26*AJ26/8) -> 0 | BW26: z
B27: =IF(AD27="","",IF(ISERROR(FIND(CHAR(10),AD27,1)),AD27,LEFT(AD27,FIND(CHAR(10),AD27,1)))) -> 03-01-22: init | C27: =IF(AD27="","",IFERROR(RIGHT(AD27,LEN(AD27)-FIND("@@@",SUBSTITUTE(AD27,CHAR(10),"@@@",LEN(AD27)-LEN(SUBSTITUTE(AD27,CHAR(10),""))),1)),AD27)) -> 03-01-22: init | D27: =IFERROR(DATE(("20"&MID(B27,7,2))*1,MID(B27,4,2)*1,MID(B27,1,2)*1),"") -> 44564 | E27: =IFERROR(DATE(("20"&MID(C27,7,2))*1,MID(C27,4,2)*1,MID(C27,1,2)*1),"") -> 44564 | F27: =MAX(D27,IF(E27="none",D27,E27)) -> 44564 | G27: =IFERROR(DAYS360(D27,F27),0) -> 0 | H27: =((LEN($AE27)-LEN(SUBSTITUTE($AE27,CHAR(10)&". ","")))/3)+IF(LEFT(TRIM($AE27),2)=". ",1,0) -> 0 | I27: =((LEN($AE27)-LEN(SUBSTITUTE($AE27,CHAR(10)&"/ ","")))/3)+IF(LEFT(TRIM($AE27),2)="/ ",1,0) -> 0 | J27: =((LEN($AE27)-LEN(SUBSTITUTE($AE27,CHAR(10)&"~ ","")))/3)+IF(LEFT(TRIM($AE27),2)="~ ",1,0) -> 0 | K27: =((LEN($AE27)-LEN(SUBSTITUTE($AE27,CHAR(10)&"! ","")))/3)+IF(LEFT(TRIM($AE27),2)="! ",1,0) -> 0 | L27: =((LEN($AE27)-LEN(SUBSTITUTE($AE27,CHAR(10)&"x ","")))/3)+IF(LEFT(TRIM($AE27),2)="x ",1,0) -> 0 | M27: =SUM(H27:L27) -> 0 | N27: =IF(F27>(($A$21-WEEKDAY($A$21,2))-7*$F$22),"Y","N") -> N | O27: =IF(AB27=""," - ZZZ"," - "&X27&Y27&AB27) -> - 02.organisingGeneral Management00.Maintain Organising | P27: =IF(AB27="","",(IF(OR(Q27="Y",Q27="N"),Q27,IF(N27="Y","Y","N")))) -> N | Q27: N | S27: VNT | T27: _all | U27: n/a | V27: Sander | W27: mgt | X27: 02.organising | Y27: General Management | Z27: Routine | AA27: Started | AB27: 00.Maintain Organising | AC27: Details: # INTRODUCTION Details of this management item are in the Management Framework. | AD27: 03-01-22: init | AE27: ## Generic Routines & 01.Maintain Activities [## Activities] & 02.Maintain Groups [## Groups] & 03.Maintain Delegating [## Delegating] & 04.Maintain R&R [## R&R] & 05.Maintain Casting [## Casting] & 06.Maintain Funding [## Funding] ________________________________________ ## Activities ________________________________________ ## Groups ________________________________________ ## R&R ________________________________________ ## Casting ________________________________________ ## Funding ## _END | AF27: =IF(AB27="","",SUM(H27:K27)) -> 0 | AG27: =IF(AB27="","",IF(M27<>0,(I27*0.5+L27)/M27,1)) -> 1 | AH27: Ad-hoc | AK27: =IF(AB27="","",AI27*AJ27/8) -> 0 | BW27: z
B28: =IF(AD28="","",IF(ISERROR(FIND(CHAR(10),AD28,1)),AD28,LEFT(AD28,FIND(CHAR(10),AD28,1)))) -> 03-01-22: init | C28: =IF(AD28="","",IFERROR(RIGHT(AD28,LEN(AD28)-FIND("@@@",SUBSTITUTE(AD28,CHAR(10),"@@@",LEN(AD28)-LEN(SUBSTITUTE(AD28,CHAR(10),""))),1)),AD28)) -> 03-01-22: init | D28: =IFERROR(DATE(("20"&MID(B28,7,2))*1,MID(B28,4,2)*1,MID(B28,1,2)*1),"") -> 44564 | E28: =IFERROR(DATE(("20"&MID(C28,7,2))*1,MID(C28,4,2)*1,MID(C28,1,2)*1),"") -> 44564 | F28: =MAX(D28,IF(E28="none",D28,E28)) -> 44564 | G28: =IFERROR(DAYS360(D28,F28),0) -> 0 | H28: =((LEN($AE28)-LEN(SUBSTITUTE($AE28,CHAR(10)&". ","")))/3)+IF(LEFT(TRIM($AE28),2)=". ",1,0) -> 0 | I28: =((LEN($AE28)-LEN(SUBSTITUTE($AE28,CHAR(10)&"/ ","")))/3)+IF(LEFT(TRIM($AE28),2)="/ ",1,0) -> 0 | J28: =((LEN($AE28)-LEN(SUBSTITUTE($AE28,CHAR(10)&"~ ","")))/3)+IF(LEFT(TRIM($AE28),2)="~ ",1,0) -> 0 | K28: =((LEN($AE28)-LEN(SUBSTITUTE($AE28,CHAR(10)&"! ","")))/3)+IF(LEFT(TRIM($AE28),2)="! ",1,0) -> 0 | L28: =((LEN($AE28)-LEN(SUBSTITUTE($AE28,CHAR(10)&"x ","")))/3)+IF(LEFT(TRIM($AE28),2)="x ",1,0) -> 0 | M28: =SUM(H28:L28) -> 0 | N28: =IF(F28>(($A$21-WEEKDAY($A$21,2))-7*$F$22),"Y","N") -> N | O28: =IF(AB28=""," - ZZZ"," - "&X28&Y28&AB28) -> - 03.leadingGeneral Management00.Maintain Leading | P28: =IF(AB28="","",(IF(OR(Q28="Y",Q28="N"),Q28,IF(N28="Y","Y","N")))) -> N | Q28: N | S28: VNT | T28: _all | U28: n/a | V28: Sander | W28: mgt | X28: 03.leading | Y28: General Management | Z28: Routine | AA28: Started | AB28: 00.Maintain Leading | AC28: Details: # INTRODUCTION Details of this management item are in the Management Framework. | AD28: 03-01-22: init | AE28: ## Generic Routines & 01.Maintain Safe Space [## Safe Space] & 02.Maintain Direction [## Direction] & 03.Maintain Collaboration [## Collaboration] & 04.Maintain Motivation [## Motivation] & 05.Maintain Inspiration [## Inspiration] & 06.Maintain Learning [## Learning] & 07.Maintain Networking [## Networking] & 08.Maintain Leaders [## Leaders] & 09.Maintain Management Improvement [## Management Improvement] & 10.Maintain Culture [## Culture] ________________________________________ ## Safe Space ________________________________________ ## Direction ________________________________________ ## Collaboration ________________________________________ ## Motivation ________________________________________ ## Inspiration ________________________________________ ## Learning ________________________________________ ## Networking ________________________________________ ## Leaders ________________________________________ ## Management Improvement ________________________________________ ## Culture ## _END | AF28: =IF(AB28="","",SUM(H28:K28)) -> 0 | AG28: =IF(AB28="","",IF(M28<>0,(I28*0.5+L28)/M28,1)) -> 1 | AH28: Ad-hoc | AK28: =IF(AB28="","",AI28*AJ28/8) -> 0 | BW28: z
B29: =IF(AD29="","",IF(ISERROR(FIND(CHAR(10),AD29,1)),AD29,LEFT(AD29,FIND(CHAR(10),AD29,1)))) -> 03-01-22: init | C29: =IF(AD29="","",IFERROR(RIGHT(AD29,LEN(AD29)-FIND("@@@",SUBSTITUTE(AD29,CHAR(10),"@@@",LEN(AD29)-LEN(SUBSTITUTE(AD29,CHAR(10),""))),1)),AD29)) -> 03-01-22: init | D29: =IFERROR(DATE(("20"&MID(B29,7,2))*1,MID(B29,4,2)*1,MID(B29,1,2)*1),"") -> 44564 | E29: =IFERROR(DATE(("20"&MID(C29,7,2))*1,MID(C29,4,2)*1,MID(C29,1,2)*1),"") -> 44564 | F29: =MAX(D29,IF(E29="none",D29,E29)) -> 44564 | G29: =IFERROR(DAYS360(D29,F29),0) -> 0 | H29: =((LEN($AE29)-LEN(SUBSTITUTE($AE29,CHAR(10)&". ","")))/3)+IF(LEFT(TRIM($AE29),2)=". ",1,0) -> 0 | I29: =((LEN($AE29)-LEN(SUBSTITUTE($AE29,CHAR(10)&"/ ","")))/3)+IF(LEFT(TRIM($AE29),2)="/ ",1,0) -> 0 | J29: =((LEN($AE29)-LEN(SUBSTITUTE($AE29,CHAR(10)&"~ ","")))/3)+IF(LEFT(TRIM($AE29),2)="~ ",1,0) -> 0 | K29: =((LEN($AE29)-LEN(SUBSTITUTE($AE29,CHAR(10)&"! ","")))/3)+IF(LEFT(TRIM($AE29),2)="! ",1,0) -> 0 | L29: =((LEN($AE29)-LEN(SUBSTITUTE($AE29,CHAR(10)&"x ","")))/3)+IF(LEFT(TRIM($AE29),2)="x ",1,0) -> 0 | M29: =SUM(H29:L29) -> 0 | N29: =IF(F29>(($A$21-WEEKDAY($A$21,2))-7*$F$22),"Y","N") -> N | O29: =IF(AB29=""," - ZZZ"," - "&X29&Y29&AB29) -> - 04.controllingGeneral Management00.Maintain Controlling | P29: =IF(AB29="","",(IF(OR(Q29="Y",Q29="N"),Q29,IF(N29="Y","Y","N")))) -> N | Q29: N | S29: VNT | T29: _all | U29: n/a | V29: Sander | W29: mgt | X29: 04.controlling | Y29: General Management | Z29: Routine | AA29: Started | AB29: 00.Maintain Controlling | AC29: Details: # INTRODUCTION Details of this management item are in the Management Framework. | AD29: 03-01-22: init | AE29: ## Generic Routines & 01.Maintain Jounal [## Jounal] & 02.Maintain Supervision [## Supervision] & 03.Maintain Reports [## Reports] & 04.Maintain Monitoring [## Monitoring] ________________________________________ ## Jounal ________________________________________ ## Supervision ________________________________________ ## Reports ________________________________________ ## Monitoring ## _END | AF29: =IF(AB29="","",SUM(H29:K29)) -> 0 | AG29: =IF(AB29="","",IF(M29<>0,(I29*0.5+L29)/M29,1)) -> 1 | AH29: Ad-hoc | AK29: =IF(AB29="","",AI29*AJ29/8) -> 0 | BW29: z
B30: =IF(AD30="","",IF(ISERROR(FIND(CHAR(10),AD30,1)),AD30,LEFT(AD30,FIND(CHAR(10),AD30,1)))) -> 03-01-22: init | C30: =IF(AD30="","",IFERROR(RIGHT(AD30,LEN(AD30)-FIND("@@@",SUBSTITUTE(AD30,CHAR(10),"@@@",LEN(AD30)-LEN(SUBSTITUTE(AD30,CHAR(10),""))),1)),AD30)) -> 03-01-22: init | D30: =IFERROR(DATE(("20"&MID(B30,7,2))*1,MID(B30,4,2)*1,MID(B30,1,2)*1),"") -> 44564 | E30: =IFERROR(DATE(("20"&MID(C30,7,2))*1,MID(C30,4,2)*1,MID(C30,1,2)*1),"") -> 44564 | F30: =MAX(D30,IF(E30="none",D30,E30)) -> 44564 | G30: =IFERROR(DAYS360(D30,F30),0) -> 0 | H30: =((LEN($AE30)-LEN(SUBSTITUTE($AE30,CHAR(10)&". ","")))/3)+IF(LEFT(TRIM($AE30),2)=". ",1,0) -> 0 | I30: =((LEN($AE30)-LEN(SUBSTITUTE($AE30,CHAR(10)&"/ ","")))/3)+IF(LEFT(TRIM($AE30),2)="/ ",1,0) -> 0 | J30: =((LEN($AE30)-LEN(SUBSTITUTE($AE30,CHAR(10)&"~ ","")))/3)+IF(LEFT(TRIM($AE30),2)="~ ",1,0) -> 0 | K30: =((LEN($AE30)-LEN(SUBSTITUTE($AE30,CHAR(10)&"! ","")))/3)+IF(LEFT(TRIM($AE30),2)="! ",1,0) -> 0 | L30: =((LEN($AE30)-LEN(SUBSTITUTE($AE30,CHAR(10)&"x ","")))/3)+IF(LEFT(TRIM($AE30),2)="x ",1,0) -> 0 | M30: =SUM(H30:L30) -> 0 | N30: =IF(F30>(($A$21-WEEKDAY($A$21,2))-7*$F$22),"Y","N") -> N | O30: =IF(AB30=""," - ZZZ"," - "&X30&Y30&AB30) -> - 05.00.business functionsGeneral Management00.Maintain Business Functions | P30: =IF(AB30="","",(IF(OR(Q30="Y",Q30="N"),Q30,IF(N30="Y","Y","N")))) -> N | Q30: N | S30: VNT | T30: _all | U30: n/a | V30: Sander | W30: mgt | X30: 05.00.business functions | Y30: General Management | Z30: Routine | AA30: Started | AB30: 00.Maintain Business Functions | AC30: Details: # INTRODUCTION Details of this management item are in the Management Framework. | AD30: 03-01-22: init | AE30: ## Generic Routines ## _END | AF30: =IF(AB30="","",SUM(H30:K30)) -> 0 | AG30: =IF(AB30="","",IF(M30<>0,(I30*0.5+L30)/M30,1)) -> 1 | AH30: Ad-hoc | AK30: =IF(AB30="","",AI30*AJ30/8) -> 0 | BW30: z
B31: =IF(AD31="","",IF(ISERROR(FIND(CHAR(10),AD31,1)),AD31,LEFT(AD31,FIND(CHAR(10),AD31,1)))) -> 03-01-22: init | C31: =IF(AD31="","",IFERROR(RIGHT(AD31,LEN(AD31)-FIND("@@@",SUBSTITUTE(AD31,CHAR(10),"@@@",LEN(AD31)-LEN(SUBSTITUTE(AD31,CHAR(10),""))),1)),AD31)) -> 03-01-22: init | D31: =IFERROR(DATE(("20"&MID(B31,7,2))*1,MID(B31,4,2)*1,MID(B31,1,2)*1),"") -> 44564 | E31: =IFERROR(DATE(("20"&MID(C31,7,2))*1,MID(C31,4,2)*1,MID(C31,1,2)*1),"") -> 44564 | F31: =MAX(D31,IF(E31="none",D31,E31)) -> 44564 | G31: =IFERROR(DAYS360(D31,F31),0) -> 0 | H31: =((LEN($AE31)-LEN(SUBSTITUTE($AE31,CHAR(10)&". ","")))/3)+IF(LEFT(TRIM($AE31),2)=". ",1,0) -> 0 | I31: =((LEN($AE31)-LEN(SUBSTITUTE($AE31,CHAR(10)&"/ ","")))/3)+IF(LEFT(TRIM($AE31),2)="/ ",1,0) -> 0 | J31: =((LEN($AE31)-LEN(SUBSTITUTE($AE31,CHAR(10)&"~ ","")))/3)+IF(LEFT(TRIM($AE31),2)="~ ",1,0) -> 0 | K31: =((LEN($AE31)-LEN(SUBSTITUTE($AE31,CHAR(10)&"! ","")))/3)+IF(LEFT(TRIM($AE31),2)="! ",1,0) -> 0 | L31: =((LEN($AE31)-LEN(SUBSTITUTE($AE31,CHAR(10)&"x ","")))/3)+IF(LEFT(TRIM($AE31),2)="x ",1,0) -> 0 | M31: =SUM(H31:L31) -> 0 | N31: =IF(F31>(($A$21-WEEKDAY($A$21,2))-7*$F$22),"Y","N") -> N | O31: =IF(AB31=""," - ZZZ"," - "&X31&Y31&AB31) -> - 05.01.financeGeneral Management00.Maintain Finance | P31: =IF(AB31="","",(IF(OR(Q31="Y",Q31="N"),Q31,IF(N31="Y","Y","N")))) -> N | Q31: N | S31: VNT | T31: _all | U31: n/a | V31: Sander | W31: mgt | X31: 05.01.finance | Y31: General Management | Z31: Routine | AA31: Started | AB31: 00.Maintain Finance | AC31: Details: # INTRODUCTION Details of this management item are in the Management Framework. | AD31: 03-01-22: init | AE31: ## Generic Routines & 01.Maintain Accounting [## Accounting] & 02.Maintain Financing [## Financing] ________________________________________ ## Accounting ________________________________________ ## Financing ## _END | AF31: =IF(AB31="","",SUM(H31:K31)) -> 0 | AG31: =IF(AB31="","",IF(M31<>0,(I31*0.5+L31)/M31,1)) -> 1 | AH31: Ad-hoc | AK31: =IF(AB31="","",AI31*AJ31/8) -> 0 | BW31: z
B32: =IF(AD32="","",IF(ISERROR(FIND(CHAR(10),AD32,1)),AD32,LEFT(AD32,FIND(CHAR(10),AD32,1)))) -> 03-01-22: init | C32: =IF(AD32="","",IFERROR(RIGHT(AD32,LEN(AD32)-FIND("@@@",SUBSTITUTE(AD32,CHAR(10),"@@@",LEN(AD32)-LEN(SUBSTITUTE(AD32,CHAR(10),""))),1)),AD32)) -> 03-01-22: init | D32: =IFERROR(DATE(("20"&MID(B32,7,2))*1,MID(B32,4,2)*1,MID(B32,1,2)*1),"") -> 44564 | E32: =IFERROR(DATE(("20"&MID(C32,7,2))*1,MID(C32,4,2)*1,MID(C32,1,2)*1),"") -> 44564 | F32: =MAX(D32,IF(E32="none",D32,E32)) -> 44564 | G32: =IFERROR(DAYS360(D32,F32),0) -> 0 | H32: =((LEN($AE32)-LEN(SUBSTITUTE($AE32,CHAR(10)&". ","")))/3)+IF(LEFT(TRIM($AE32),2)=". ",1,0) -> 0 | I32: =((LEN($AE32)-LEN(SUBSTITUTE($AE32,CHAR(10)&"/ ","")))/3)+IF(LEFT(TRIM($AE32),2)="/ ",1,0) -> 0 | J32: =((LEN($AE32)-LEN(SUBSTITUTE($AE32,CHAR(10)&"~ ","")))/3)+IF(LEFT(TRIM($AE32),2)="~ ",1,0) -> 0 | K32: =((LEN($AE32)-LEN(SUBSTITUTE($AE32,CHAR(10)&"! ","")))/3)+IF(LEFT(TRIM($AE32),2)="! ",1,0) -> 0 | L32: =((LEN($AE32)-LEN(SUBSTITUTE($AE32,CHAR(10)&"x ","")))/3)+IF(LEFT(TRIM($AE32),2)="x ",1,0) -> 0 | M32: =SUM(H32:L32) -> 0 | N32: =IF(F32>(($A$21-WEEKDAY($A$21,2))-7*$F$22),"Y","N") -> N | O32: =IF(AB32=""," - ZZZ"," - "&X32&Y32&AB32) -> - 05.02.HRGeneral Management00.Maintain HR | P32: =IF(AB32="","",(IF(OR(Q32="Y",Q32="N"),Q32,IF(N32="Y","Y","N")))) -> N | Q32: N | S32: VNT | T32: _all | U32: n/a | V32: Sander | W32: mgt | X32: 05.02.HR | Y32: General Management | Z32: Routine | AA32: Started | AB32: 00.Maintain HR | AC32: Details: # INTRODUCTION Details of this management item are in the Management Framework. | AD32: 03-01-22: init | AE32: ## Generic Routines & 01.Maintain Recruitment [## Recruitment] & 02.Maintain Skills & Knowledge [## Skills & Knowledge] & 03.Maintain Training [## Training] & 04.Maintain Performance [## Performance] & 05.Maintain Remuneration [## Remuneration] & 06.Maintain Job Satifactions [## Learning] & 07.Maintain Employee Relations [## Employee Relations] & 08.Maintain Employment Law [## Employment Law] ________________________________________ ## Recruitment ________________________________________ ## Skills & Knowledge ________________________________________ ## Training ________________________________________ ## Performance ________________________________________ ## Remuneration ________________________________________ ## Job Satisfacton ________________________________________ ## Employee Relations ________________________________________ ## Employment Law ## _END | AF32: =IF(AB32="","",SUM(H32:K32)) -> 0 | AG32: =IF(AB32="","",IF(M32<>0,(I32*0.5+L32)/M32,1)) -> 1 | AH32: Ad-hoc | AK32: =IF(AB32="","",AI32*AJ32/8) -> 0 | BW32: z
B33: =IF(AD33="","",IF(ISERROR(FIND(CHAR(10),AD33,1)),AD33,LEFT(AD33,FIND(CHAR(10),AD33,1)))) -> 03-01-22: init | C33: =IF(AD33="","",IFERROR(RIGHT(AD33,LEN(AD33)-FIND("@@@",SUBSTITUTE(AD33,CHAR(10),"@@@",LEN(AD33)-LEN(SUBSTITUTE(AD33,CHAR(10),""))),1)),AD33)) -> 03-01-22: init | D33: =IFERROR(DATE(("20"&MID(B33,7,2))*1,MID(B33,4,2)*1,MID(B33,1,2)*1),"") -> 44564 | E33: =IFERROR(DATE(("20"&MID(C33,7,2))*1,MID(C33,4,2)*1,MID(C33,1,2)*1),"") -> 44564 | F33: =MAX(D33,IF(E33="none",D33,E33)) -> 44564 | G33: =IFERROR(DAYS360(D33,F33),0) -> 0 | H33: =((LEN($AE33)-LEN(SUBSTITUTE($AE33,CHAR(10)&". ","")))/3)+IF(LEFT(TRIM($AE33),2)=". ",1,0) -> 0 | I33: =((LEN($AE33)-LEN(SUBSTITUTE($AE33,CHAR(10)&"/ ","")))/3)+IF(LEFT(TRIM($AE33),2)="/ ",1,0) -> 0 | J33: =((LEN($AE33)-LEN(SUBSTITUTE($AE33,CHAR(10)&"~ ","")))/3)+IF(LEFT(TRIM($AE33),2)="~ ",1,0) -> 0 | K33: =((LEN($AE33)-LEN(SUBSTITUTE($AE33,CHAR(10)&"! ","")))/3)+IF(LEFT(TRIM($AE33),2)="! ",1,0) -> 0 | L33: =((LEN($AE33)-LEN(SUBSTITUTE($AE33,CHAR(10)&"x ","")))/3)+IF(LEFT(TRIM($AE33),2)="x ",1,0) -> 0 | M33: =SUM(H33:L33) -> 0 | N33: =IF(F33>(($A$21-WEEKDAY($A$21,2))-7*$F$22),"Y","N") -> N | O33: =IF(AB33=""," - ZZZ"," - "&X33&Y33&AB33) -> - 05.03.ITGeneral Management00.Maintain IT | P33: =IF(AB33="","",(IF(OR(Q33="Y",Q33="N"),Q33,IF(N33="Y","Y","N")))) -> N | Q33: N | S33: VNT | T33: _all | U33: n/a | V33: Sander | W33: mgt | X33: 05.03.IT | Y33: General Management | Z33: Routine | AA33: Started | AB33: 00.Maintain IT | AC33: Details: # INTRODUCTION Details of this management item are in the Management Framework. | AD33: 03-01-22: init | AE33: ## Generic Routines & 01.Maintain Infra [## Infra] & 02.Maintain Applications [## Applications] ________________________________________ ## Infra ________________________________________ ## Applications ## _END | AF33: =IF(AB33="","",SUM(H33:K33)) -> 0 | AG33: =IF(AB33="","",IF(M33<>0,(I33*0.5+L33)/M33,1)) -> 1 | AH33: Ad-hoc | AK33: =IF(AB33="","",AI33*AJ33/8) -> 0 | BW33: z
B34: =IF(AD34="","",IF(ISERROR(FIND(CHAR(10),AD34,1)),AD34,LEFT(AD34,FIND(CHAR(10),AD34,1)))) -> 03-01-22: init | C34: =IF(AD34="","",IFERROR(RIGHT(AD34,LEN(AD34)-FIND("@@@",SUBSTITUTE(AD34,CHAR(10),"@@@",LEN(AD34)-LEN(SUBSTITUTE(AD34,CHAR(10),""))),1)),AD34)) -> 03-01-22: init | D34: =IFERROR(DATE(("20"&MID(B34,7,2))*1,MID(B34,4,2)*1,MID(B34,1,2)*1),"") -> 44564 | E34: =IFERROR(DATE(("20"&MID(C34,7,2))*1,MID(C34,4,2)*1,MID(C34,1,2)*1),"") -> 44564 | F34: =MAX(D34,IF(E34="none",D34,E34)) -> 44564 | G34: =IFERROR(DAYS360(D34,F34),0) -> 0 | H34: =((LEN($AE34)-LEN(SUBSTITUTE($AE34,CHAR(10)&". ","")))/3)+IF(LEFT(TRIM($AE34),2)=". ",1,0) -> 0 | I34: =((LEN($AE34)-LEN(SUBSTITUTE($AE34,CHAR(10)&"/ ","")))/3)+IF(LEFT(TRIM($AE34),2)="/ ",1,0) -> 0 | J34: =((LEN($AE34)-LEN(SUBSTITUTE($AE34,CHAR(10)&"~ ","")))/3)+IF(LEFT(TRIM($AE34),2)="~ ",1,0) -> 0 | K34: =((LEN($AE34)-LEN(SUBSTITUTE($AE34,CHAR(10)&"! ","")))/3)+IF(LEFT(TRIM($AE34),2)="! ",1,0) -> 0 | L34: =((LEN($AE34)-LEN(SUBSTITUTE($AE34,CHAR(10)&"x ","")))/3)+IF(LEFT(TRIM($AE34),2)="x ",1,0) -> 0 | M34: =SUM(H34:L34) -> 0 | N34: =IF(F34>(($A$21-WEEKDAY($A$21,2))-7*$F$22),"Y","N") -> N | O34: =IF(AB34=""," - ZZZ"," - "&X34&Y34&AB34) -> - 05.04.riskGeneral Management00.Maintain Risk | P34: =IF(AB34="","",(IF(OR(Q34="Y",Q34="N"),Q34,IF(N34="Y","Y","N")))) -> N | Q34: N | S34: VNT | T34: _all | U34: n/a | V34: Sander | W34: mgt | X34: 05.04.risk | Y34: General Management | Z34: Routine | AA34: Started | AB34: 00.Maintain Risk | AC34: Details: # INTRODUCTION Details of this management item are in the Management Framework. | AD34: 03-01-22: init | AE34: ## Generic Routines ________________________________________ ## _END | AF34: =IF(AB34="","",SUM(H34:K34)) -> 0 | AG34: =IF(AB34="","",IF(M34<>0,(I34*0.5+L34)/M34,1)) -> 1 | AH34: Ad-hoc | AK34: =IF(AB34="","",AI34*AJ34/8) -> 0 | BW34: z
B35: =IF(AD35="","",IF(ISERROR(FIND(CHAR(10),AD35,1)),AD35,LEFT(AD35,FIND(CHAR(10),AD35,1)))) -> 03-01-22: init | C35: =IF(AD35="","",IFERROR(RIGHT(AD35,LEN(AD35)-FIND("@@@",SUBSTITUTE(AD35,CHAR(10),"@@@",LEN(AD35)-LEN(SUBSTITUTE(AD35,CHAR(10),""))),1)),AD35)) -> 03-01-22: init | D35: =IFERROR(DATE(("20"&MID(B35,7,2))*1,MID(B35,4,2)*1,MID(B35,1,2)*1),"") -> 44564 | E35: =IFERROR(DATE(("20"&MID(C35,7,2))*1,MID(C35,4,2)*1,MID(C35,1,2)*1),"") -> 44564 | F35: =MAX(D35,IF(E35="none",D35,E35)) -> 44564 | G35: =IFERROR(DAYS360(D35,F35),0) -> 0 | H35: =((LEN($AE35)-LEN(SUBSTITUTE($AE35,CHAR(10)&". ","")))/3)+IF(LEFT(TRIM($AE35),2)=". ",1,0) -> 0 | I35: =((LEN($AE35)-LEN(SUBSTITUTE($AE35,CHAR(10)&"/ ","")))/3)+IF(LEFT(TRIM($AE35),2)="/ ",1,0) -> 0 | J35: =((LEN($AE35)-LEN(SUBSTITUTE($AE35,CHAR(10)&"~ ","")))/3)+IF(LEFT(TRIM($AE35),2)="~ ",1,0) -> 0 | K35: =((LEN($AE35)-LEN(SUBSTITUTE($AE35,CHAR(10)&"! ","")))/3)+IF(LEFT(TRIM($AE35),2)="! ",1,0) -> 0 | L35: =((LEN($AE35)-LEN(SUBSTITUTE($AE35,CHAR(10)&"x ","")))/3)+IF(LEFT(TRIM($AE35),2)="x ",1,0) -> 0 | M35: =SUM(H35:L35) -> 0 | N35: =IF(F35>(($A$21-WEEKDAY($A$21,2))-7*$F$22),"Y","N") -> N | O35: =IF(AB35=""," - ZZZ"," - "&X35&Y35&AB35) -> - 05.05.complianceGeneral Management00.Maintain Compliance | P35: =IF(AB35="","",(IF(OR(Q35="Y",Q35="N"),Q35,IF(N35="Y","Y","N")))) -> N | Q35: N | S35: VNT | T35: _all | U35: n/a | V35: Sander | W35: mgt | X35: 05.05.compliance | Y35: General Management | Z35: Routine | AA35: Started | AB35: 00.Maintain Compliance | AC35: Details: # INTRODUCTION Details of this management item are in the Management Framework. | AD35: 03-01-22: init | AE35: ## Generic Routines ________________________________________ ## _END | AF35: =IF(AB35="","",SUM(H35:K35)) -> 0 | AG35: =IF(AB35="","",IF(M35<>0,(I35*0.5+L35)/M35,1)) -> 1 | AH35: Ad-hoc | AK35: =IF(AB35="","",AI35*AJ35/8) -> 0 | BW35: z
B36: =IF(AD36="","",IF(ISERROR(FIND(CHAR(10),AD36,1)),AD36,LEFT(AD36,FIND(CHAR(10),AD36,1)))) -> 03-01-22: init | C36: =IF(AD36="","",IFERROR(RIGHT(AD36,LEN(AD36)-FIND("@@@",SUBSTITUTE(AD36,CHAR(10),"@@@",LEN(AD36)-LEN(SUBSTITUTE(AD36,CHAR(10),""))),1)),AD36)) -> 03-01-22: init | D36: =IFERROR(DATE(("20"&MID(B36,7,2))*1,MID(B36,4,2)*1,MID(B36,1,2)*1),"") -> 44564 | E36: =IFERROR(DATE(("20"&MID(C36,7,2))*1,MID(C36,4,2)*1,MID(C36,1,2)*1),"") -> 44564 | F36: =MAX(D36,IF(E36="none",D36,E36)) -> 44564 | G36: =IFERROR(DAYS360(D36,F36),0) -> 0 | H36: =((LEN($AE36)-LEN(SUBSTITUTE($AE36,CHAR(10)&". ","")))/3)+IF(LEFT(TRIM($AE36),2)=". ",1,0) -> 0 | I36: =((LEN($AE36)-LEN(SUBSTITUTE($AE36,CHAR(10)&"/ ","")))/3)+IF(LEFT(TRIM($AE36),2)="/ ",1,0) -> 0 | J36: =((LEN($AE36)-LEN(SUBSTITUTE($AE36,CHAR(10)&"~ ","")))/3)+IF(LEFT(TRIM($AE36),2)="~ ",1,0) -> 0 | K36: =((LEN($AE36)-LEN(SUBSTITUTE($AE36,CHAR(10)&"! ","")))/3)+IF(LEFT(TRIM($AE36),2)="! ",1,0) -> 0 | L36: =((LEN($AE36)-LEN(SUBSTITUTE($AE36,CHAR(10)&"x ","")))/3)+IF(LEFT(TRIM($AE36),2)="x ",1,0) -> 0 | M36: =SUM(H36:L36) -> 0 | N36: =IF(F36>(($A$21-WEEKDAY($A$21,2))-7*$F$22),"Y","N") -> N | O36: =IF(AB36=""," - ZZZ"," - "&X36&Y36&AB36) -> - 05.06.legalGeneral Management00.Maintain Legal | P36: =IF(AB36="","",(IF(OR(Q36="Y",Q36="N"),Q36,IF(N36="Y","Y","N")))) -> N | Q36: N | S36: VNT | T36: _all | U36: n/a | V36: Sander | W36: mgt | X36: 05.06.legal | Y36: General Management | Z36: Routine | AA36: Started | AB36: 00.Maintain Legal | AC36: Details: # INTRODUCTION Details of this management item are in the Management Framework. | AD36: 03-01-22: init | AE36: ## Generic Routines & 01.Maintain Legal Opinions [## Legal Opinions] & 02.Maintain Litigation [## Financing] & 03.Maintain Entty Structure [## Entity Structure] ________________________________________ ## Legal Opinions ________________________________________ ## Litigation ________________________________________ ## Entity Structure ## _END | AF36: =IF(AB36="","",SUM(H36:K36)) -> 0 | AG36: =IF(AB36="","",IF(M36<>0,(I36*0.5+L36)/M36,1)) -> 1 | AH36: Ad-hoc | AK36: =IF(AB36="","",AI36*AJ36/8) -> 0 | BW36: z
... B43: =IF(AD43="","",IF(ISERROR(FIND(CHAR(10),AD43,1)),AD43,LEFT(AD43,FIND(CHAR(10),AD43,1)))) -> 03-01-22: init | C43: =IF(AD43="","",IFERROR(RIGHT(AD43,LEN(AD43)-FIND("@@@",SUBSTITUTE(AD43,CHAR(10),"@@@",LEN(AD43)-LEN(SUBSTITUTE(AD43,CHAR(10),""))),1)),AD43)) -> 03-01-22: init | D43: =IFERROR(DATE(("20"&MID(B43,7,2))*1,MID(B43,4,2)*1,MID(B43,1,2)*1),"") -> 44564 | E43: =IFERROR(DATE(("20"&MID(C43,7,2))*1,MID(C43,4,2)*1,MID(C43,1,2)*1),"") -> 44564 | F43: =MAX(D43,IF(E43="none",D43,E43)) -> 44564 | G43: =IFERROR(DAYS360(D43,F43),0) -> 0 | H43: =((LEN($AE43)-LEN(SUBSTITUTE($AE43,CHAR(10)&". ","")))/3)+IF(LEFT(TRIM($AE43),2)=". ",1,0) -> 0 | I43: =((LEN($AE43)-LEN(SUBSTITUTE($AE43,CHAR(10)&"/ ","")))/3)+IF(LEFT(TRIM($AE43),2)="/ ",1,0) -> 0 | J43: =((LEN($AE43)-LEN(SUBSTITUTE($AE43,CHAR(10)&"~ ","")))/3)+IF(LEFT(TRIM($AE43),2)="~ ",1,0) -> 0 | K43: =((LEN($AE43)-LEN(SUBSTITUTE($AE43,CHAR(10)&"! ","")))/3)+IF(LEFT(TRIM($AE43),2)="! ",1,0) -> 0 | L43: =((LEN($AE43)-LEN(SUBSTITUTE($AE43,CHAR(10)&"x ","")))/3)+IF(LEFT(TRIM($AE43),2)="x ",1,0) -> 0 | M43: =SUM(H43:L43) -> 0 | N43: =IF(F43>(($A$21-WEEKDAY($A$21,2))-7*$F$22),"Y","N") -> N | O43: =IF(AB43=""," - ZZZ"," - "&X43&Y43&AB43) -> - 06.toolsGeneral Management00.Maintain Tools | P43: =IF(AB43="","",(IF(OR(Q43="Y",Q43="N"),Q43,IF(N43="Y","Y","N")))) -> N | Q43: N | S43: VNT | T43: _all | U43: n/a | V43: Sander | W43: mgt | X43: 06.tools | Y43: General Management | Z43: Routine | AA43: Started | AB43: 00.Maintain Tools | AC43: Details: # INTRODUCTION Details of this management item are in the Management Framework. | AD43: 03-01-22: init | AE43: ## Generic Routines ________________________________________ ## _END | AF43: =IF(AB43="","",SUM(H43:K43)) -> 0 | AG43: =IF(AB43="","",IF(M43<>0,(I43*0.5+L43)/M43,1)) -> 1 | AH43: Ad-hoc | AK43: =IF(AB43="","",AI43*AJ43/8) -> 0 | BW43: z
B44: =IF(AD44="","",IF(ISERROR(FIND(CHAR(10),AD44,1)),AD44,LEFT(AD44,FIND(CHAR(10),AD44,1)))) -> 03-01-22: init | C44: =IF(AD44="","",IFERROR(RIGHT(AD44,LEN(AD44)-FIND("@@@",SUBSTITUTE(AD44,CHAR(10),"@@@",LEN(AD44)-LEN(SUBSTITUTE(AD44,CHAR(10),""))),1)),AD44)) -> 03-01-22: init | D44: =IFERROR(DATE(("20"&MID(B44,7,2))*1,MID(B44,4,2)*1,MID(B44,1,2)*1),"") -> 44564 | E44: =IFERROR(DATE(("20"&MID(C44,7,2))*1,MID(C44,4,2)*1,MID(C44,1,2)*1),"") -> 44564 | F44: =MAX(D44,IF(E44="none",D44,E44)) -> 44564 | G44: =IFERROR(DAYS360(D44,F44),0) -> 0 | H44: =((LEN($AE44)-LEN(SUBSTITUTE($AE44,CHAR(10)&". ","")))/3)+IF(LEFT(TRIM($AE44),2)=". ",1,0) -> 0 | I44: =((LEN($AE44)-LEN(SUBSTITUTE($AE44,CHAR(10)&"/ ","")))/3)+IF(LEFT(TRIM($AE44),2)="/ ",1,0) -> 0 | J44: =((LEN($AE44)-LEN(SUBSTITUTE($AE44,CHAR(10)&"~ ","")))/3)+IF(LEFT(TRIM($AE44),2)="~ ",1,0) -> 0 | K44: =((LEN($AE44)-LEN(SUBSTITUTE($AE44,CHAR(10)&"! ","")))/3)+IF(LEFT(TRIM($AE44),2)="! ",1,0) -> 0 | L44: =((LEN($AE44)-LEN(SUBSTITUTE($AE44,CHAR(10)&"x ","")))/3)+IF(LEFT(TRIM($AE44),2)="x ",1,0) -> 0 | M44: =SUM(H44:L44) -> 0 | N44: =IF(F44>(($A$21-WEEKDAY($A$21,2))-7*$F$22),"Y","N") -> N | O44: =IF(AB44=""," - ZZZ"," - "&X44&Y44&AB44) -> - 07.management cycleGeneral Management00.Maintain Management Cycle | P44: =IF(AB44="","",(IF(OR(Q44="Y",Q44="N"),Q44,IF(N44="Y","Y","N")))) -> N | Q44: N | S44: VNT | T44: _all | U44: n/a | V44: Sander | W44: mgt | X44: 07.management cycle | Y44: General Management | Z44: Routine | AA44: Started | AB44: 00.Maintain Management Cycle | AC44: Details: # INTRODUCTION Details of this management item are in the Management Framework. | AD44: 03-01-22: init | AE44: ## Generic Routines ________________________________________ ## _END | AF44: =IF(AB44="","",SUM(H44:K44)) -> 0 | AG44: =IF(AB44="","",IF(M44<>0,(I44*0.5+L44)/M44,1)) -> 1 | AK44: =IF(AB44="","",AI44*AJ44/8) -> 0 | BW44: z
B45: =IF(AD45="","",IF(ISERROR(FIND(CHAR(10),AD45,1)),AD45,LEFT(AD45,FIND(CHAR(10),AD45,1)))) | C45: =IF(AD45="","",IFERROR(RIGHT(AD45,LEN(AD45)-FIND("@@@",SUBSTITUTE(AD45,CHAR(10),"@@@",LEN(AD45)-LEN(SUBSTITUTE(AD45,CHAR(10),""))),1)),AD45)) | D45: =IFERROR(DATE(("20"&MID(B45,7,2))*1,MID(B45,4,2)*1,MID(B45,1,2)*1),"") | E45: =IFERROR(DATE(("20"&MID(C45,7,2))*1,MID(C45,4,2)*1,MID(C45,1,2)*1),"") | F45: =MAX(D45,IF(E45="none",D45,E45)) -> 0 | G45: =IFERROR(DAYS360(D45,F45),0) -> 0 | H45: =((LEN($AE45)-LEN(SUBSTITUTE($AE45,CHAR(10)&". ","")))/3)+IF(LEFT(TRIM($AE45),2)=". ",1,0) -> 0 | I45: =((LEN($AE45)-LEN(SUBSTITUTE($AE45,CHAR(10)&"/ ","")))/3)+IF(LEFT(TRIM($AE45),2)="/ ",1,0) -> 0 | J45: =((LEN($AE45)-LEN(SUBSTITUTE($AE45,CHAR(10)&"~ ","")))/3)+IF(LEFT(TRIM($AE45),2)="~ ",1,0) -> 0 | K45: =((LEN($AE45)-LEN(SUBSTITUTE($AE45,CHAR(10)&"! ","")))/3)+IF(LEFT(TRIM($AE45),2)="! ",1,0) -> 0 | L45: =((LEN($AE45)-LEN(SUBSTITUTE($AE45,CHAR(10)&"x ","")))/3)+IF(LEFT(TRIM($AE45),2)="x ",1,0) -> 0 | M45: =SUM(H45:L45) -> 0 | N45: =IF(F45>(($A$21-WEEKDAY($A$21,2))-7*$F$22),"Y","N") -> N | O45: =IF(AB45=""," - ZZZ"," - "&X45&Y45&AB45) -> - ZZZ | P45: =IF(AB45="","",(IF(OR(Q45="Y",Q45="N"),Q45,IF(N45="Y","Y","N")))) | AF45: =IF(AB45="","",SUM(H45:K45)) | AG45: =IF(AB45="","",IF(M45<>0,(I45*0.5+L45)/M45,1)) | AK45: =IF(AB45="","",AI45*AJ45/8) | BW45: z
B46: =IF(AD46="","",IF(ISERROR(FIND(CHAR(10),AD46,1)),AD46,LEFT(AD46,FIND(CHAR(10),AD46,1)))) | C46: =IF(AD46="","",IFERROR(RIGHT(AD46,LEN(AD46)-FIND("@@@",SUBSTITUTE(AD46,CHAR(10),"@@@",LEN(AD46)-LEN(SUBSTITUTE(AD46,CHAR(10),""))),1)),AD46)) | D46: =IFERROR(DATE(("20"&MID(B46,7,2))*1,MID(B46,4,2)*1,MID(B46,1,2)*1),"") | E46: =IFERROR(DATE(("20"&MID(C46,7,2))*1,MID(C46,4,2)*1,MID(C46,1,2)*1),"") | F46: =MAX(D46,IF(E46="none",D46,E46)) -> 0 | G46: =IFERROR(DAYS360(D46,F46),0) -> 0 | H46: =((LEN($AE46)-LEN(SUBSTITUTE($AE46,CHAR(10)&". ","")))/3)+IF(LEFT(TRIM($AE46),2)=". ",1,0) -> 0 | I46: =((LEN($AE46)-LEN(SUBSTITUTE($AE46,CHAR(10)&"/ ","")))/3)+IF(LEFT(TRIM($AE46),2)="/ ",1,0) -> 0 | J46: =((LEN($AE46)-LEN(SUBSTITUTE($AE46,CHAR(10)&"~ ","")))/3)+IF(LEFT(TRIM($AE46),2)="~ ",1,0) -> 0 | K46: =((LEN($AE46)-LEN(SUBSTITUTE($AE46,CHAR(10)&"! ","")))/3)+IF(LEFT(TRIM($AE46),2)="! ",1,0) -> 0 | L46: =((LEN($AE46)-LEN(SUBSTITUTE($AE46,CHAR(10)&"x ","")))/3)+IF(LEFT(TRIM($AE46),2)="x ",1,0) -> 0 | M46: =SUM(H46:L46) -> 0 | N46: =IF(F46>(($A$21-WEEKDAY($A$21,2))-7*$F$22),"Y","N") -> N | O46: =IF(AB46=""," - ZZZ"," - "&X46&Y46&AB46) -> - ZZZ | P46: =IF(AB46="","",(IF(OR(Q46="Y",Q46="N"),Q46,IF(N46="Y","Y","N")))) | AF46: =IF(AB46="","",SUM(H46:K46)) | AG46: =IF(AB46="","",IF(M46<>0,(I46*0.5+L46)/M46,1)) | AK46: =IF(AB46="","",AI46*AJ46/8) | BW46: z
B47: =IF(AD47="","",IF(ISERROR(FIND(CHAR(10),AD47,1)),AD47,LEFT(AD47,FIND(CHAR(10),AD47,1)))) | C47: =IF(AD47="","",IFERROR(RIGHT(AD47,LEN(AD47)-FIND("@@@",SUBSTITUTE(AD47,CHAR(10),"@@@",LEN(AD47)-LEN(SUBSTITUTE(AD47,CHAR(10),""))),1)),AD47)) | D47: =IFERROR(DATE(("20"&MID(B47,7,2))*1,MID(B47,4,2)*1,MID(B47,1,2)*1),"") | E47: =IFERROR(DATE(("20"&MID(C47,7,2))*1,MID(C47,4,2)*1,MID(C47,1,2)*1),"") | F47: =MAX(D47,IF(E47="none",D47,E47)) -> 0 | G47: =IFERROR(DAYS360(D47,F47),0) -> 0 | H47: =((LEN($AE47)-LEN(SUBSTITUTE($AE47,CHAR(10)&". ","")))/3)+IF(LEFT(TRIM($AE47),2)=". ",1,0) -> 0 | I47: =((LEN($AE47)-LEN(SUBSTITUTE($AE47,CHAR(10)&"/ ","")))/3)+IF(LEFT(TRIM($AE47),2)="/ ",1,0) -> 0 | J47: =((LEN($AE47)-LEN(SUBSTITUTE($AE47,CHAR(10)&"~ ","")))/3)+IF(LEFT(TRIM($AE47),2)="~ ",1,0) -> 0 | K47: =((LEN($AE47)-LEN(SUBSTITUTE($AE47,CHAR(10)&"! ","")))/3)+IF(LEFT(TRIM($AE47),2)="! ",1,0) -> 0 | L47: =((LEN($AE47)-LEN(SUBSTITUTE($AE47,CHAR(10)&"x ","")))/3)+IF(LEFT(TRIM($AE47),2)="x ",1,0) -> 0 | M47: =SUM(H47:L47) -> 0 | N47: =IF(F47>(($A$21-WEEKDAY($A$21,2))-7*$F$22),"Y","N") -> N | O47: =IF(AB47=""," - ZZZ"," - "&X47&Y47&AB47) -> - ZZZ | P47: =IF(AB47="","",(IF(OR(Q47="Y",Q47="N"),Q47,IF(N47="Y","Y","N")))) | AF47: =IF(AB47="","",SUM(H47:K47)) | AG47: =IF(AB47="","",IF(M47<>0,(I47*0.5+L47)/M47,1)) | AK47: =IF(AB47="","",AI47*AJ47/8) | BW47: z
B48: =IF(AD48="","",IF(ISERROR(FIND(CHAR(10),AD48,1)),AD48,LEFT(AD48,FIND(CHAR(10),AD48,1)))) | C48: =IF(AD48="","",IFERROR(RIGHT(AD48,LEN(AD48)-FIND("@@@",SUBSTITUTE(AD48,CHAR(10),"@@@",LEN(AD48)-LEN(SUBSTITUTE(AD48,CHAR(10),""))),1)),AD48)) | D48: =IFERROR(DATE(("20"&MID(B48,7,2))*1,MID(B48,4,2)*1,MID(B48,1,2)*1),"") | E48: =IFERROR(DATE(("20"&MID(C48,7,2))*1,MID(C48,4,2)*1,MID(C48,1,2)*1),"") | F48: =MAX(D48,IF(E48="none",D48,E48)) -> 0 | G48: =IFERROR(DAYS360(D48,F48),0) -> 0 | H48: =((LEN($AE48)-LEN(SUBSTITUTE($AE48,CHAR(10)&". ","")))/3)+IF(LEFT(TRIM($AE48),2)=". ",1,0) -> 0 | I48: =((LEN($AE48)-LEN(SUBSTITUTE($AE48,CHAR(10)&"/ ","")))/3)+IF(LEFT(TRIM($AE48),2)="/ ",1,0) -> 0 | J48: =((LEN($AE48)-LEN(SUBSTITUTE($AE48,CHAR(10)&"~ ","")))/3)+IF(LEFT(TRIM($AE48),2)="~ ",1,0) -> 0 | K48: =((LEN($AE48)-LEN(SUBSTITUTE($AE48,CHAR(10)&"! ","")))/3)+IF(LEFT(TRIM($AE48),2)="! ",1,0) -> 0 | L48: =((LEN($AE48)-LEN(SUBSTITUTE($AE48,CHAR(10)&"x ","")))/3)+IF(LEFT(TRIM($AE48),2)="x ",1,0) -> 0 | M48: =SUM(H48:L48) -> 0 | N48: =IF(F48>(($A$21-WEEKDAY($A$21,2))-7*$F$22),"Y","N") -> N | O48: =IF(AB48=""," - ZZZ"," - "&X48&Y48&AB48) -> - ZZZ | P48: =IF(AB48="","",(IF(OR(Q48="Y",Q48="N"),Q48,IF(N48="Y","Y","N")))) | AF48: =IF(AB48="","",SUM(H48:K48)) | AG48: =IF(AB48="","",IF(M48<>0,(I48*0.5+L48)/M48,1)) | AK48: =IF(AB48="","",AI48*AJ48/8) | BW48: z
B49: =IF(AD49="","",IF(ISERROR(FIND(CHAR(10),AD49,1)),AD49,LEFT(AD49,FIND(CHAR(10),AD49,1)))) | C49: =IF(AD49="","",IFERROR(RIGHT(AD49,LEN(AD49)-FIND("@@@",SUBSTITUTE(AD49,CHAR(10),"@@@",LEN(AD49)-LEN(SUBSTITUTE(AD49,CHAR(10),""))),1)),AD49)) | D49: =IFERROR(DATE(("20"&MID(B49,7,2))*1,MID(B49,4,2)*1,MID(B49,1,2)*1),"") | E49: =IFERROR(DATE(("20"&MID(C49,7,2))*1,MID(C49,4,2)*1,MID(C49,1,2)*1),"") | F49: =MAX(D49,IF(E49="none",D49,E49)) -> 0 | G49: =IFERROR(DAYS360(D49,F49),0) -> 0 | H49: =((LEN($AE49)-LEN(SUBSTITUTE($AE49,CHAR(10)&". ","")))/3)+IF(LEFT(TRIM($AE49),2)=". ",1,0) -> 0 | I49: =((LEN($AE49)-LEN(SUBSTITUTE($AE49,CHAR(10)&"/ ","")))/3)+IF(LEFT(TRIM($AE49),2)="/ ",1,0) -> 0 | J49: =((LEN($AE49)-LEN(SUBSTITUTE($AE49,CHAR(10)&"~ ","")))/3)+IF(LEFT(TRIM($AE49),2)="~ ",1,0) -> 0 | K49: =((LEN($AE49)-LEN(SUBSTITUTE($AE49,CHAR(10)&"! ","")))/3)+IF(LEFT(TRIM($AE49),2)="! ",1,0) -> 0 | L49: =((LEN($AE49)-LEN(SUBSTITUTE($AE49,CHAR(10)&"x ","")))/3)+IF(LEFT(TRIM($AE49),2)="x ",1,0) -> 0 | M49: =SUM(H49:L49) -> 0 | N49: =IF(F49>(($A$21-WEEKDAY($A$21,2))-7*$F$22),"Y","N") -> N | O49: =IF(AB49=""," - ZZZ"," - "&X49&Y49&AB49) -> - ZZZ | P49: =IF(AB49="","",(IF(OR(Q49="Y",Q49="N"),Q49,IF(N49="Y","Y","N")))) | AF49: =IF(AB49="","",SUM(H49:K49)) | AG49: =IF(AB49="","",IF(M49<>0,(I49*0.5+L49)/M49,1)) | AK49: =IF(AB49="","",AI49*AJ49/8) | BW49: z
B50: =IF(AD50="","",IF(ISERROR(FIND(CHAR(10),AD50,1)),AD50,LEFT(AD50,FIND(CHAR(10),AD50,1)))) | C50: =IF(AD50="","",IFERROR(RIGHT(AD50,LEN(AD50)-FIND("@@@",SUBSTITUTE(AD50,CHAR(10),"@@@",LEN(AD50)-LEN(SUBSTITUTE(AD50,CHAR(10),""))),1)),AD50)) | D50: =IFERROR(DATE(("20"&MID(B50,7,2))*1,MID(B50,4,2)*1,MID(B50,1,2)*1),"") | E50: =IFERROR(DATE(("20"&MID(C50,7,2))*1,MID(C50,4,2)*1,MID(C50,1,2)*1),"") | F50: =MAX(D50,IF(E50="none",D50,E50)) -> 0 | G50: =IFERROR(DAYS360(D50,F50),0) -> 0 | H50: =((LEN($AE50)-LEN(SUBSTITUTE($AE50,CHAR(10)&". ","")))/3)+IF(LEFT(TRIM($AE50),2)=". ",1,0) -> 0 | I50: =((LEN($AE50)-LEN(SUBSTITUTE($AE50,CHAR(10)&"/ ","")))/3)+IF(LEFT(TRIM($AE50),2)="/ ",1,0) -> 0 | J50: =((LEN($AE50)-LEN(SUBSTITUTE($AE50,CHAR(10)&"~ ","")))/3)+IF(LEFT(TRIM($AE50),2)="~ ",1,0) -> 0 | K50: =((LEN($AE50)-LEN(SUBSTITUTE($AE50,CHAR(10)&"! ","")))/3)+IF(LEFT(TRIM($AE50),2)="! ",1,0) -> 0 | L50: =((LEN($AE50)-LEN(SUBSTITUTE($AE50,CHAR(10)&"x ","")))/3)+IF(LEFT(TRIM($AE50),2)="x ",1,0) -> 0 | M50: =SUM(H50:L50) -> 0 | N50: =IF(F50>(($A$21-WEEKDAY($A$21,2))-7*$F$22),"Y","N") -> N | O50: =IF(AB50=""," - ZZZ"," - "&X50&Y50&AB50) -> - ZZZ | P50: =IF(AB50="","",(IF(OR(Q50="Y",Q50="N"),Q50,IF(N50="Y","Y","N")))) | AF50: =IF(AB50="","",SUM(H50:K50)) | AG50: =IF(AB50="","",IF(M50<>0,(I50*0.5+L50)/M50,1)) | AK50: =IF(AB50="","",AI50*AJ50/8) | BW50: z
B51: =IF(AD51="","",IF(ISERROR(FIND(CHAR(10),AD51,1)),AD51,LEFT(AD51,FIND(CHAR(10),AD51,1)))) | C51: =IF(AD51="","",IFERROR(RIGHT(AD51,LEN(AD51)-FIND("@@@",SUBSTITUTE(AD51,CHAR(10),"@@@",LEN(AD51)-LEN(SUBSTITUTE(AD51,CHAR(10),""))),1)),AD51)) | D51: =IFERROR(DATE(("20"&MID(B51,7,2))*1,MID(B51,4,2)*1,MID(B51,1,2)*1),"") | E51: =IFERROR(DATE(("20"&MID(C51,7,2))*1,MID(C51,4,2)*1,MID(C51,1,2)*1),"") | F51: =MAX(D51,IF(E51="none",D51,E51)) -> 0 | G51: =IFERROR(DAYS360(D51,F51),0) -> 0 | H51: =((LEN($AE51)-LEN(SUBSTITUTE($AE51,CHAR(10)&". ","")))/3)+IF(LEFT(TRIM($AE51),2)=". ",1,0) -> 0 | I51: =((LEN($AE51)-LEN(SUBSTITUTE($AE51,CHAR(10)&"/ ","")))/3)+IF(LEFT(TRIM($AE51),2)="/ ",1,0) -> 0 | J51: =((LEN($AE51)-LEN(SUBSTITUTE($AE51,CHAR(10)&"~ ","")))/3)+IF(LEFT(TRIM($AE51),2)="~ ",1,0) -> 0 | K51: =((LEN($AE51)-LEN(SUBSTITUTE($AE51,CHAR(10)&"! ","")))/3)+IF(LEFT(TRIM($AE51),2)="! ",1,0) -> 0 | L51: =((LEN($AE51)-LEN(SUBSTITUTE($AE51,CHAR(10)&"x ","")))/3)+IF(LEFT(TRIM($AE51),2)="x ",1,0) -> 0 | M51: =SUM(H51:L51) -> 0 | N51: =IF(F51>(($A$21-WEEKDAY($A$21,2))-7*$F$22),"Y","N") -> N | O51: =IF(AB51=""," - ZZZ"," - "&X51&Y51&AB51) -> - ZZZ | P51: =IF(AB51="","",(IF(OR(Q51="Y",Q51="N"),Q51,IF(N51="Y","Y","N")))) | AF51: =IF(AB51="","",SUM(H51:K51)) | AG51: =IF(AB51="","",IF(M51<>0,(I51*0.5+L51)/M51,1)) | AK51: =IF(AB51="","",AI51*AJ51/8) | BW51: z
B52: =IF(AD52="","",IF(ISERROR(FIND(CHAR(10),AD52,1)),AD52,LEFT(AD52,FIND(CHAR(10),AD52,1)))) | C52: =IF(AD52="","",IFERROR(RIGHT(AD52,LEN(AD52)-FIND("@@@",SUBSTITUTE(AD52,CHAR(10),"@@@",LEN(AD52)-LEN(SUBSTITUTE(AD52,CHAR(10),""))),1)),AD52)) | D52: =IFERROR(DATE(("20"&MID(B52,7,2))*1,MID(B52,4,2)*1,MID(B52,1,2)*1),"") | E52: =IFERROR(DATE(("20"&MID(C52,7,2))*1,MID(C52,4,2)*1,MID(C52,1,2)*1),"") | F52: =MAX(D52,IF(E52="none",D52,E52)) -> 0 | G52: =IFERROR(DAYS360(D52,F52),0) -> 0 | H52: =((LEN($AE52)-LEN(SUBSTITUTE($AE52,CHAR(10)&". ","")))/3)+IF(LEFT(TRIM($AE52),2)=". ",1,0) -> 0 | I52: =((LEN($AE52)-LEN(SUBSTITUTE($AE52,CHAR(10)&"/ ","")))/3)+IF(LEFT(TRIM($AE52),2)="/ ",1,0) -> 0 | J52: =((LEN($AE52)-LEN(SUBSTITUTE($AE52,CHAR(10)&"~ ","")))/3)+IF(LEFT(TRIM($AE52),2)="~ ",1,0) -> 0 | K52: =((LEN($AE52)-LEN(SUBSTITUTE($AE52,CHAR(10)&"! ","")))/3)+IF(LEFT(TRIM($AE52),2)="! ",1,0) -> 0 | L52: =((LEN($AE52)-LEN(SUBSTITUTE($AE52,CHAR(10)&"x ","")))/3)+IF(LEFT(TRIM($AE52),2)="x ",1,0) -> 0 | M52: =SUM(H52:L52) -> 0 | N52: =IF(F52>(($A$21-WEEKDAY($A$21,2))-7*$F$22),"Y","N") -> N | O52: =IF(AB52=""," - ZZZ"," - "&X52&Y52&AB52) -> - ZZZ | P52: =IF(AB52="","",(IF(OR(Q52="Y",Q52="N"),Q52,IF(N52="Y","Y","N")))) | AF52: =IF(AB52="","",SUM(H52:K52)) | AG52: =IF(AB52="","",IF(M52<>0,(I52*0.5+L52)/M52,1)) | AK52: =IF(AB52="","",AI52*AJ52/8) | BW52: z
B53: =IF(AD53="","",IF(ISERROR(FIND(CHAR(10),AD53,1)),AD53,LEFT(AD53,FIND(CHAR(10),AD53,1)))) | C53: =IF(AD53="","",IFERROR(RIGHT(AD53,LEN(AD53)-FIND("@@@",SUBSTITUTE(AD53,CHAR(10),"@@@",LEN(AD53)-LEN(SUBSTITUTE(AD53,CHAR(10),""))),1)),AD53)) | D53: =IFERROR(DATE(("20"&MID(B53,7,2))*1,MID(B53,4,2)*1,MID(B53,1,2)*1),"") | E53: =IFERROR(DATE(("20"&MID(C53,7,2))*1,MID(C53,4,2)*1,MID(C53,1,2)*1),"") | F53: =MAX(D53,IF(E53="none",D53,E53)) -> 0 | G53: =IFERROR(DAYS360(D53,F53),0) -> 0 | H53: =((LEN($AE53)-LEN(SUBSTITUTE($AE53,CHAR(10)&". ","")))/3)+IF(LEFT(TRIM($AE53),2)=". ",1,0) -> 0 | I53: =((LEN($AE53)-LEN(SUBSTITUTE($AE53,CHAR(10)&"/ ","")))/3)+IF(LEFT(TRIM($AE53),2)="/ ",1,0) -> 0 | J53: =((LEN($AE53)-LEN(SUBSTITUTE($AE53,CHAR(10)&"~ ","")))/3)+IF(LEFT(TRIM($AE53),2)="~ ",1,0) -> 0 | K53: =((LEN($AE53)-LEN(SUBSTITUTE($AE53,CHAR(10)&"! ","")))/3)+IF(LEFT(TRIM($AE53),2)="! ",1,0) -> 0 | L53: =((LEN($AE53)-LEN(SUBSTITUTE($AE53,CHAR(10)&"x ","")))/3)+IF(LEFT(TRIM($AE53),2)="x ",1,0) -> 0 | M53: =SUM(H53:L53) -> 0 | N53: =IF(F53>(($A$21-WEEKDAY($A$21,2))-7*$F$22),"Y","N") -> N | O53: =IF(AB53=""," - ZZZ"," - "&X53&Y53&AB53) -> - ZZZ | P53: =IF(AB53="","",(IF(OR(Q53="Y",Q53="N"),Q53,IF(N53="Y","Y","N")))) | AF53: =IF(AB53="","",SUM(H53:K53)) | AG53: =IF(AB53="","",IF(M53<>0,(I53*0.5+L53)/M53,1)) | AK53: =IF(AB53="","",AI53*AJ53/8) | BW53: z
B54: =IF(AD54="","",IF(ISERROR(FIND(CHAR(10),AD54,1)),AD54,LEFT(AD54,FIND(CHAR(10),AD54,1)))) | C54: =IF(AD54="","",IFERROR(RIGHT(AD54,LEN(AD54)-FIND("@@@",SUBSTITUTE(AD54,CHAR(10),"@@@",LEN(AD54)-LEN(SUBSTITUTE(AD54,CHAR(10),""))),1)),AD54)) | D54: =IFERROR(DATE(("20"&MID(B54,7,2))*1,MID(B54,4,2)*1,MID(B54,1,2)*1),"") | E54: =IFERROR(DATE(("20"&MID(C54,7,2))*1,MID(C54,4,2)*1,MID(C54,1,2)*1),"") | F54: =MAX(D54,IF(E54="none",D54,E54)) -> 0 | G54: =IFERROR(DAYS360(D54,F54),0) -> 0 | H54: =((LEN($AE54)-LEN(SUBSTITUTE($AE54,CHAR(10)&". ","")))/3)+IF(LEFT(TRIM($AE54),2)=". ",1,0) -> 0 | I54: =((LEN($AE54)-LEN(SUBSTITUTE($AE54,CHAR(10)&"/ ","")))/3)+IF(LEFT(TRIM($AE54),2)="/ ",1,0) -> 0 | J54: =((LEN($AE54)-LEN(SUBSTITUTE($AE54,CHAR(10)&"~ ","")))/3)+IF(LEFT(TRIM($AE54),2)="~ ",1,0) -> 0 | K54: =((LEN($AE54)-LEN(SUBSTITUTE($AE54,CHAR(10)&"! ","")))/3)+IF(LEFT(TRIM($AE54),2)="! ",1,0) -> 0 | L54: =((LEN($AE54)-LEN(SUBSTITUTE($AE54,CHAR(10)&"x ","")))/3)+IF(LEFT(TRIM($AE54),2)="x ",1,0) -> 0 | M54: =SUM(H54:L54) -> 0 | N54: =IF(F54>(($A$21-WEEKDAY($A$21,2))-7*$F$22),"Y","N") -> N | O54: =IF(AB54=""," - ZZZ"," - "&X54&Y54&AB54) -> - ZZZ | P54: =IF(AB54="","",(IF(OR(Q54="Y",Q54="N"),Q54,IF(N54="Y","Y","N")))) | AF54: =IF(AB54="","",SUM(H54:K54)) | AG54: =IF(AB54="","",IF(M54<>0,(I54*0.5+L54)/M54,1)) | AK54: =IF(AB54="","",AI54*AJ54/8) | BW54: z
B55: =IF(AD55="","",IF(ISERROR(FIND(CHAR(10),AD55,1)),AD55,LEFT(AD55,FIND(CHAR(10),AD55,1)))) | C55: =IF(AD55="","",IFERROR(RIGHT(AD55,LEN(AD55)-FIND("@@@",SUBSTITUTE(AD55,CHAR(10),"@@@",LEN(AD55)-LEN(SUBSTITUTE(AD55,CHAR(10),""))),1)),AD55)) | D55: =IFERROR(DATE(("20"&MID(B55,7,2))*1,MID(B55,4,2)*1,MID(B55,1,2)*1),"") | E55: =IFERROR(DATE(("20"&MID(C55,7,2))*1,MID(C55,4,2)*1,MID(C55,1,2)*1),"") | F55: =MAX(D55,IF(E55="none",D55,E55)) -> 0 | G55: =IFERROR(DAYS360(D55,F55),0) -> 0 | H55: =((LEN($AE55)-LEN(SUBSTITUTE($AE55,CHAR(10)&". ","")))/3)+IF(LEFT(TRIM($AE55),2)=". ",1,0) -> 0 | I55: =((LEN($AE55)-LEN(SUBSTITUTE($AE55,CHAR(10)&"/ ","")))/3)+IF(LEFT(TRIM($AE55),2)="/ ",1,0) -> 0 | J55: =((LEN($AE55)-LEN(SUBSTITUTE($AE55,CHAR(10)&"~ ","")))/3)+IF(LEFT(TRIM($AE55),2)="~ ",1,0) -> 0 | K55: =((LEN($AE55)-LEN(SUBSTITUTE($AE55,CHAR(10)&"! ","")))/3)+IF(LEFT(TRIM($AE55),2)="! ",1,0) -> 0 | L55: =((LEN($AE55)-LEN(SUBSTITUTE($AE55,CHAR(10)&"x ","")))/3)+IF(LEFT(TRIM($AE55),2)="x ",1,0) -> 0 | M55: =SUM(H55:L55) -> 0 | N55: =IF(F55>(($A$21-WEEKDAY($A$21,2))-7*$F$22),"Y","N") -> N | O55: =IF(AB55=""," - ZZZ"," - "&X55&Y55&AB55) -> - ZZZ | P55: =IF(AB55="","",(IF(OR(Q55="Y",Q55="N"),Q55,IF(N55="Y","Y","N")))) | AF55: =IF(AB55="","",SUM(H55:K55)) | AG55: =IF(AB55="","",IF(M55<>0,(I55*0.5+L55)/M55,1)) | AK55: =IF(AB55="","",AI55*AJ55/8) | BW55: z
B56: =IF(AD56="","",IF(ISERROR(FIND(CHAR(10),AD56,1)),AD56,LEFT(AD56,FIND(CHAR(10),AD56,1)))) | C56: =IF(AD56="","",IFERROR(RIGHT(AD56,LEN(AD56)-FIND("@@@",SUBSTITUTE(AD56,CHAR(10),"@@@",LEN(AD56)-LEN(SUBSTITUTE(AD56,CHAR(10),""))),1)),AD56)) | D56: =IFERROR(DATE(("20"&MID(B56,7,2))*1,MID(B56,4,2)*1,MID(B56,1,2)*1),"") | E56: =IFERROR(DATE(("20"&MID(C56,7,2))*1,MID(C56,4,2)*1,MID(C56,1,2)*1),"") | F56: =MAX(D56,IF(E56="none",D56,E56)) -> 0 | G56: =IFERROR(DAYS360(D56,F56),0) -> 0 | H56: =((LEN($AE56)-LEN(SUBSTITUTE($AE56,CHAR(10)&". ","")))/3)+IF(LEFT(TRIM($AE56),2)=". ",1,0) -> 0 | I56: =((LEN($AE56)-LEN(SUBSTITUTE($AE56,CHAR(10)&"/ ","")))/3)+IF(LEFT(TRIM($AE56),2)="/ ",1,0) -> 0 | J56: =((LEN($AE56)-LEN(SUBSTITUTE($AE56,CHAR(10)&"~ ","")))/3)+IF(LEFT(TRIM($AE56),2)="~ ",1,0) -> 0 | K56: =((LEN($AE56)-LEN(SUBSTITUTE($AE56,CHAR(10)&"! ","")))/3)+IF(LEFT(TRIM($AE56),2)="! ",1,0) -> 0 | L56: =((LEN($AE56)-LEN(SUBSTITUTE($AE56,CHAR(10)&"x ","")))/3)+IF(LEFT(TRIM($AE56),2)="x ",1,0) -> 0 | M56: =SUM(H56:L56) -> 0 | N56: =IF(F56>(($A$21-WEEKDAY($A$21,2))-7*$F$22),"Y","N") -> N | O56: =IF(AB56=""," - ZZZ"," - "&X56&Y56&AB56) -> - ZZZ | P56: =IF(AB56="","",(IF(OR(Q56="Y",Q56="N"),Q56,IF(N56="Y","Y","N")))) | AF56: =IF(AB56="","",SUM(H56:K56)) | AG56: =IF(AB56="","",IF(M56<>0,(I56*0.5+L56)/M56,1)) | AK56: =IF(AB56="","",AI56*AJ56/8) | BW56: z
... B91: =IF(AD91="","",IF(ISERROR(FIND(CHAR(10),AD91,1)),AD91,LEFT(AD91,FIND(CHAR(10),AD91,1)))) | C91: =IF(AD91="","",IFERROR(RIGHT(AD91,LEN(AD91)-FIND("@@@",SUBSTITUTE(AD91,CHAR(10),"@@@",LEN(AD91)-LEN(SUBSTITUTE(AD91,CHAR(10),""))),1)),AD91)) | D91: =IFERROR(DATE(("20"&MID(B91,7,2))*1,MID(B91,4,2)*1,MID(B91,1,2)*1),"") | E91: =IFERROR(DATE(("20"&MID(C91,7,2))*1,MID(C91,4,2)*1,MID(C91,1,2)*1),"") | F91: =MAX(D91,IF(E91="none",D91,E91)) -> 0 | G91: =IFERROR(DAYS360(D91,F91),0) -> 0 | H91: =((LEN($AE91)-LEN(SUBSTITUTE($AE91,CHAR(10)&". ","")))/3)+IF(LEFT(TRIM($AE91),2)=". ",1,0) -> 0 | I91: =((LEN($AE91)-LEN(SUBSTITUTE($AE91,CHAR(10)&"/ ","")))/3)+IF(LEFT(TRIM($AE91),2)="/ ",1,0) -> 0 | J91: =((LEN($AE91)-LEN(SUBSTITUTE($AE91,CHAR(10)&"~ ","")))/3)+IF(LEFT(TRIM($AE91),2)="~ ",1,0) -> 0 | K91: =((LEN($AE91)-LEN(SUBSTITUTE($AE91,CHAR(10)&"! ","")))/3)+IF(LEFT(TRIM($AE91),2)="! ",1,0) -> 0 | L91: =((LEN($AE91)-LEN(SUBSTITUTE($AE91,CHAR(10)&"x ","")))/3)+IF(LEFT(TRIM($AE91),2)="x ",1,0) -> 0 | M91: =SUM(H91:L91) -> 0 | N91: =IF(F91>(($A$21-WEEKDAY($A$21,2))-7*$F$22),"Y","N") -> N | O91: =IF(AB91=""," - ZZZ"," - "&X91&Y91&AB91) -> - ZZZ | P91: =IF(AB91="","",(IF(OR(Q91="Y",Q91="N"),Q91,IF(N91="Y","Y","N")))) | AF91: =IF(AB91="","",SUM(H91:K91)) | AG91: =IF(AB91="","",IF(M91<>0,(I91*0.5+L91)/M91,1)) | AK91: =IF(AB91="","",AI91*AJ91/8) | BW91: z

Sheet GTD
D1: Select GTD Type from drop-down list. | E1: Type Project Name, Routine Name, Reference Name | F1: Type Task Name (=Name of reportable item for a Reference) | G1: Type “Self” for Taks owned by self. Type name of someone else in all other cases (if someone is Owner) | H1: Expected Date of Completion | I1: Actual Completion Date | J1: Date at which the Reference Item should be Reported. | K1: Provide details. No specific format. | L1: GTD List as per [Management Framework ## GTD] | M1: Additional List in case of Projects, Routines and References. If OneNote is available, each is represented by a Section and in it there is a page with the Project Name, Routine Name and Reference Name as per Collumn “Project / Routine / Reference Name” - Project Details - Project Name 1 - etc - Routine Details - Routine Name 1 - etc - Reference Details - Reference Name 1 - etc | N1: Indication how close the Due Date is: - Overdue - Due in 7 days - Due in 30 days | O1: Whether an item is reportable based on Done Date or Tickle Date | P1: Integrity Checls of each Row | Q1: Last Column. Contains value = “X”.
A2: =TODAY() -> 46321 | B2: 1 | D2: Manual | E2: Manual | F2: Manual | G2: Manual | H2: Manual | I2: Manual | J2: Manual | K2: Manual | L2: Calculated | M2: Calculated | N2: Calculated | O2: Calculated | P2: Calculated
A3: A | C3: Sort | D3: GTD Type | E3: Project / Routine / Reference Name | F3: Task Name | G3: Owner | H3: Due Date | I3: Done Date | J3: Tickle Date | K3: Details | L3: List | M3: Additional List | N3: Overdue / Due 7d / Due 30d | O3: Report | P3: Check | Q3: Z
A4: =A3 -> A | C4: =C3 -> Sort | D4: =D3 -> GTD Type | E4: =E3 -> Project / Routine / Reference Name | F4: =F3 -> Task Name | G4: =G3 -> Owner | H4: =H3 -> Due Date | I4: =I3 -> Done Date | J4: =J3 -> Tickle Date | ... Q4: =Q3 -> Z
C5: =IF( D5=""," - ZZZ", " - "&F5&E5&F5) -> - Project 1 | D5: Project | E5: Project 1 | G5: Self | H5: 44209 | I5: 46288 | K5: Details: | L5: =IF( I5<>"","Delete", IF( AND(G5="Self",H5<>""),"Defer", IF( AND(G5<>"",G5<>"Self",H5<>""),"Delegate", IF( D5="Project","Projects", IF( D5="Routine","Routines", IF( D5="Task","Someday", IF( D5="Reference","Reference", "" ) ) ) ) ) ) ) -> Delete | M5: =IF( D5="Project","Project Details", IF( D5="Routine","Routine Details", IF( D5="Reference","Reference Details", "" ) ) ) -> Project Details | N5: =IF( D5="","", IF( AND(H5<>"",I5="",H5<$A$2),"Overdue", IF( AND(H5<>"",I5="",(7*1+$A$2)>H5),"Due 7d", IF( AND(H5<>"",I5="",(30*1+$A$2)>H5),"Due 30d", "None" ) ) ) ) -> None | O5: =IF( D5="","", IF( I5>($A$2-7*$B$2),"Yes", IF( J5>($A$2-7*$B$2),"Yes", "No" ) ) ) -> No | P5: =IF( D5="","", IF( AND(H5<>"",G5=""),"Error: no Owner for Task with Due Date", "ok" ) ) -> ok | Q5: z
C6: =IF( D6=""," - ZZZ", " - "&F6&E6&F6) -> - Project Task 1Project 1Project Task 1 | D6: Project | E6: Project 1 | F6: Project Task 1 | G6: Self | H6: 46325 | I6: 46318 | L6: =IF( I6<>"","Delete", IF( AND(G6="Self",H6<>""),"Defer", IF( AND(G6<>"",G6<>"Self",H6<>""),"Delegate", IF( D6="Project","Projects", IF( D6="Routine","Routines", IF( D6="Task","Someday", IF( D6="Reference","Reference", "" ) ) ) ) ) ) ) -> Delete | M6: =IF( D6="Project","Project Details", IF( D6="Routine","Routine Details", IF( D6="Reference","Reference Details", "" ) ) ) -> Project Details | N6: =IF( D6="","", IF( AND(H6<>"",I6="",H6<$A$2),"Overdue", IF( AND(H6<>"",I6="",(7*1+$A$2)>H6),"Due 7d", IF( AND(H6<>"",I6="",(30*1+$A$2)>H6),"Due 30d", "None" ) ) ) ) -> None | O6: =IF( D6="","", IF( I6>($A$2-7*$B$2),"Yes", IF( J6>($A$2-7*$B$2),"Yes", "No" ) ) ) -> Yes | P6: =IF( D6="","", IF( AND(H6<>"",G6=""),"Error: no Owner for Task with Due Date", "ok" ) ) -> ok | Q6: z
C7: =IF( D7=""," - ZZZ", " - "&F7&E7&F7) -> - Project Task 2Project 1Project Task 2 | D7: Project | E7: Project 1 | F7: Project Task 2 | G7: Toto | H7: 46349 | L7: =IF( I7<>"","Delete", IF( AND(G7="Self",H7<>""),"Defer", IF( AND(G7<>"",G7<>"Self",H7<>""),"Delegate", IF( D7="Project","Projects", IF( D7="Routine","Routines", IF( D7="Task","Someday", IF( D7="Reference","Reference", "" ) ) ) ) ) ) ) -> Delegate | M7: =IF( D7="Project","Project Details", IF( D7="Routine","Routine Details", IF( D7="Reference","Reference Details", "" ) ) ) -> Project Details | N7: =IF( D7="","", IF( AND(H7<>"",I7="",H7<$A$2),"Overdue", IF( AND(H7<>"",I7="",(7*1+$A$2)>H7),"Due 7d", IF( AND(H7<>"",I7="",(30*1+$A$2)>H7),"Due 30d", "None" ) ) ) ) -> Due 30d | O7: =IF( D7="","", IF( I7>($A$2-7*$B$2),"Yes", IF( J7>($A$2-7*$B$2),"Yes", "No" ) ) ) -> No | P7: =IF( D7="","", IF( AND(H7<>"",G7=""),"Error: no Owner for Task with Due Date", "ok" ) ) -> ok | Q7: z
C8: =IF( D8=""," - ZZZ", " - "&F8&E8&F8) -> - Routine task 1Routine 1Routine task 1 | D8: Routine | E8: Routine 1 | F8: Routine task 1 | G8: Self | H8: 46354 | L8: =IF( I8<>"","Delete", IF( AND(G8="Self",H8<>""),"Defer", IF( AND(G8<>"",G8<>"Self",H8<>""),"Delegate", IF( D8="Project","Projects", IF( D8="Routine","Routines", IF( D8="Task","Someday", IF( D8="Reference","Reference", "" ) ) ) ) ) ) ) -> Defer | M8: =IF( D8="Project","Project Details", IF( D8="Routine","Routine Details", IF( D8="Reference","Reference Details", "" ) ) ) -> Routine Details | N8: =IF( D8="","", IF( AND(H8<>"",I8="",H8<$A$2),"Overdue", IF( AND(H8<>"",I8="",(7*1+$A$2)>H8),"Due 7d", IF( AND(H8<>"",I8="",(30*1+$A$2)>H8),"Due 30d", "None" ) ) ) ) -> None | O8: =IF( D8="","", IF( I8>($A$2-7*$B$2),"Yes", IF( J8>($A$2-7*$B$2),"Yes", "No" ) ) ) -> No | P8: =IF( D8="","", IF( AND(H8<>"",G8=""),"Error: no Owner for Task with Due Date", "ok" ) ) -> ok | Q8: z
C9: =IF( D9=""," - ZZZ", " - "&F9&E9&F9) -> - Routine task 2Routine 2Routine task 2 | D9: Routine | E9: Routine 2 | F9: Routine task 2 | G9: Self | H9: 46318 | L9: =IF( I9<>"","Delete", IF( AND(G9="Self",H9<>""),"Defer", IF( AND(G9<>"",G9<>"Self",H9<>""),"Delegate", IF( D9="Project","Projects", IF( D9="Routine","Routines", IF( D9="Task","Someday", IF( D9="Reference","Reference", "" ) ) ) ) ) ) ) -> Defer | M9: =IF( D9="Project","Project Details", IF( D9="Routine","Routine Details", IF( D9="Reference","Reference Details", "" ) ) ) -> Routine Details | N9: =IF( D9="","", IF( AND(H9<>"",I9="",H9<$A$2),"Overdue", IF( AND(H9<>"",I9="",(7*1+$A$2)>H9),"Due 7d", IF( AND(H9<>"",I9="",(30*1+$A$2)>H9),"Due 30d", "None" ) ) ) ) -> Overdue | O9: =IF( D9="","", IF( I9>($A$2-7*$B$2),"Yes", IF( J9>($A$2-7*$B$2),"Yes", "No" ) ) ) -> No | P9: =IF( D9="","", IF( AND(H9<>"",G9=""),"Error: no Owner for Task with Due Date", "ok" ) ) -> ok | Q9: z
C10: =IF( D10=""," - ZZZ", " - "&F10&E10&F10) -> - Dedicated task for TataDedicated task for Tata | D10: Task | F10: Dedicated task for Tata | G10: Tata | H10: 46278 | L10: =IF( I10<>"","Delete", IF( AND(G10="Self",H10<>""),"Defer", IF( AND(G10<>"",G10<>"Self",H10<>""),"Delegate", IF( D10="Project","Projects", IF( D10="Routine","Routines", IF( D10="Task","Someday", IF( D10="Reference","Reference", "" ) ) ) ) ) ) ) -> Delegate | M10: =IF( D10="Project","Project Details", IF( D10="Routine","Routine Details", IF( D10="Reference","Reference Details", "" ) ) ) | N10: =IF( D10="","", IF( AND(H10<>"",I10="",H10<$A$2),"Overdue", IF( AND(H10<>"",I10="",(7*1+$A$2)>H10),"Due 7d", IF( AND(H10<>"",I10="",(30*1+$A$2)>H10),"Due 30d", "None" ) ) ) ) -> Overdue | O10: =IF( D10="","", IF( I10>($A$2-7*$B$2),"Yes", IF( J10>($A$2-7*$B$2),"Yes", "No" ) ) ) -> No | P10: =IF( D10="","", IF( AND(H10<>"",G10=""),"Error: no Owner for Task with Due Date", "ok" ) ) -> ok | Q10: z
C11: =IF( D11=""," - ZZZ", " - "&F11&E11&F11) -> - Loss of 200k USD @ Trd DeskIncidentsLoss of 200k USD @ Trd Desk | D11: Reference | E11: Incidents | F11: Loss of 200k USD @ Trd Desk | G11: Self | J11: 46324 | L11: =IF( I11<>"","Delete", IF( AND(G11="Self",H11<>""),"Defer", IF( AND(G11<>"",G11<>"Self",H11<>""),"Delegate", IF( D11="Project","Projects", IF( D11="Routine","Routines", IF( D11="Task","Someday", IF( D11="Reference","Reference", "" ) ) ) ) ) ) ) -> Reference | M11: =IF( D11="Project","Project Details", IF( D11="Routine","Routine Details", IF( D11="Reference","Reference Details", "" ) ) ) -> Reference Details | N11: =IF( D11="","", IF( AND(H11<>"",I11="",H11<$A$2),"Overdue", IF( AND(H11<>"",I11="",(7*1+$A$2)>H11),"Due 7d", IF( AND(H11<>"",I11="",(30*1+$A$2)>H11),"Due 30d", "None" ) ) ) ) -> None | O11: =IF( D11="","", IF( I11>($A$2-7*$B$2),"Yes", IF( J11>($A$2-7*$B$2),"Yes", "No" ) ) ) -> Yes | P11: =IF( D11="","", IF( AND(H11<>"",G11=""),"Error: no Owner for Task with Due Date", "ok" ) ) -> ok | Q11: z
C12: =IF( D12=""," - ZZZ", " - "&F12&E12&F12) -> - Solve division by 0 pbSolve division by 0 pb | D12: Task | F12: Solve division by 0 pb | G12: Self | H12: 46320 | I12: 46322 | L12: =IF( I12<>"","Delete", IF( AND(G12="Self",H12<>""),"Defer", IF( AND(G12<>"",G12<>"Self",H12<>""),"Delegate", IF( D12="Project","Projects", IF( D12="Routine","Routines", IF( D12="Task","Someday", IF( D12="Reference","Reference", "" ) ) ) ) ) ) ) -> Delete | M12: =IF( D12="Project","Project Details", IF( D12="Routine","Routine Details", IF( D12="Reference","Reference Details", "" ) ) ) | N12: =IF( D12="","", IF( AND(H12<>"",I12="",H12<$A$2),"Overdue", IF( AND(H12<>"",I12="",(7*1+$A$2)>H12),"Due 7d", IF( AND(H12<>"",I12="",(30*1+$A$2)>H12),"Due 30d", "None" ) ) ) ) -> None | O12: =IF( D12="","", IF( I12>($A$2-7*$B$2),"Yes", IF( J12>($A$2-7*$B$2),"Yes", "No" ) ) ) -> Yes | P12: =IF( D12="","", IF( AND(H12<>"",G12=""),"Error: no Owner for Task with Due Date", "ok" ) ) -> ok | Q12: z
C13: =IF( D13=""," - ZZZ", " - "&F13&E13&F13) -> - Some nameSome name | D13: Task | F13: Some name | L13: =IF( I13<>"","Delete", IF( AND(G13="Self",H13<>""),"Defer", IF( AND(G13<>"",G13<>"Self",H13<>""),"Delegate", IF( D13="Project","Projects", IF( D13="Routine","Routines", IF( D13="Task","Someday", IF( D13="Reference","Reference", "" ) ) ) ) ) ) ) -> Someday | M13: =IF( D13="Project","Project Details", IF( D13="Routine","Routine Details", IF( D13="Reference","Reference Details", "" ) ) ) | N13: =IF( D13="","", IF( AND(H13<>"",I13="",H13<$A$2),"Overdue", IF( AND(H13<>"",I13="",(7*1+$A$2)>H13),"Due 7d", IF( AND(H13<>"",I13="",(30*1+$A$2)>H13),"Due 30d", "None" ) ) ) ) -> None | O13: =IF( D13="","", IF( I13>($A$2-7*$B$2),"Yes", IF( J13>($A$2-7*$B$2),"Yes", "No" ) ) ) -> No | P13: =IF( D13="","", IF( AND(H13<>"",G13=""),"Error: no Owner for Task with Due Date", "ok" ) ) -> ok | Q13: z
C14: =IF( D14=""," - ZZZ", " - "&F14&E14&F14) -> - ZZZ | L14: =IF( I14<>"","Delete", IF( AND(G14="Self",H14<>""),"Defer", IF( AND(G14<>"",G14<>"Self",H14<>""),"Delegate", IF( D14="Project","Projects", IF( D14="Routine","Routines", IF( D14="Task","Someday", IF( D14="Reference","Reference", "" ) ) ) ) ) ) ) | M14: =IF( D14="Project","Project Details", IF( D14="Routine","Routine Details", IF( D14="Reference","Reference Details", "" ) ) ) | N14: =IF( D14="","", IF( AND(H14<>"",I14="",H14<$A$2),"Overdue", IF( AND(H14<>"",I14="",(7*1+$A$2)>H14),"Due 7d", IF( AND(H14<>"",I14="",(30*1+$A$2)>H14),"Due 30d", "None" ) ) ) ) | O14: =IF( D14="","", IF( I14>($A$2-7*$B$2),"Yes", IF( J14>($A$2-7*$B$2),"Yes", "No" ) ) ) | P14: =IF( D14="","", IF( AND(H14<>"",G14=""),"Error: no Owner for Task with Due Date", "ok" ) ) | Q14: z
C15: =IF( D15=""," - ZZZ", " - "&F15&E15&F15) -> - ZZZ | L15: =IF( I15<>"","Delete", IF( AND(G15="Self",H15<>""),"Defer", IF( AND(G15<>"",G15<>"Self",H15<>""),"Delegate", IF( D15="Project","Projects", IF( D15="Routine","Routines", IF( D15="Task","Someday", IF( D15="Reference","Reference", "" ) ) ) ) ) ) ) | M15: =IF( D15="Project","Project Details", IF( D15="Routine","Routine Details", IF( D15="Reference","Reference Details", "" ) ) ) | N15: =IF( D15="","", IF( AND(H15<>"",I15="",H15<$A$2),"Overdue", IF( AND(H15<>"",I15="",(7*1+$A$2)>H15),"Due 7d", IF( AND(H15<>"",I15="",(30*1+$A$2)>H15),"Due 30d", "None" ) ) ) ) | O15: =IF( D15="","", IF( I15>($A$2-7*$B$2),"Yes", IF( J15>($A$2-7*$B$2),"Yes", "No" ) ) ) | P15: =IF( D15="","", IF( AND(H15<>"",G15=""),"Error: no Owner for Task with Due Date", "ok" ) ) | Q15: z
C16: =IF( D16=""," - ZZZ", " - "&F16&E16&F16) -> - ZZZ | L16: =IF( I16<>"","Delete", IF( AND(G16="Self",H16<>""),"Defer", IF( AND(G16<>"",G16<>"Self",H16<>""),"Delegate", IF( D16="Project","Projects", IF( D16="Routine","Routines", IF( D16="Task","Someday", IF( D16="Reference","Reference", "" ) ) ) ) ) ) ) | M16: =IF( D16="Project","Project Details", IF( D16="Routine","Routine Details", IF( D16="Reference","Reference Details", "" ) ) ) | N16: =IF( D16="","", IF( AND(H16<>"",I16="",H16<$A$2),"Overdue", IF( AND(H16<>"",I16="",(7*1+$A$2)>H16),"Due 7d", IF( AND(H16<>"",I16="",(30*1+$A$2)>H16),"Due 30d", "None" ) ) ) ) | O16: =IF( D16="","", IF( I16>($A$2-7*$B$2),"Yes", IF( J16>($A$2-7*$B$2),"Yes", "No" ) ) ) | P16: =IF( D16="","", IF( AND(H16<>"",G16=""),"Error: no Owner for Task with Due Date", "ok" ) ) | Q16: z
C17: =IF( D17=""," - ZZZ", " - "&F17&E17&F17) -> - ZZZ | L17: =IF( I17<>"","Delete", IF( AND(G17="Self",H17<>""),"Defer", IF( AND(G17<>"",G17<>"Self",H17<>""),"Delegate", IF( D17="Project","Projects", IF( D17="Routine","Routines", IF( D17="Task","Someday", IF( D17="Reference","Reference", "" ) ) ) ) ) ) ) | M17: =IF( D17="Project","Project Details", IF( D17="Routine","Routine Details", IF( D17="Reference","Reference Details", "" ) ) ) | N17: =IF( D17="","", IF( AND(H17<>"",I17="",H17<$A$2),"Overdue", IF( AND(H17<>"",I17="",(7*1+$A$2)>H17),"Due 7d", IF( AND(H17<>"",I17="",(30*1+$A$2)>H17),"Due 30d", "None" ) ) ) ) | O17: =IF( D17="","", IF( I17>($A$2-7*$B$2),"Yes", IF( J17>($A$2-7*$B$2),"Yes", "No" ) ) ) | P17: =IF( D17="","", IF( AND(H17<>"",G17=""),"Error: no Owner for Task with Due Date", "ok" ) ) | Q17: z
C18: =IF( D18=""," - ZZZ", " - "&F18&E18&F18) -> - ZZZ | L18: =IF( I18<>"","Delete", IF( AND(G18="Self",H18<>""),"Defer", IF( AND(G18<>"",G18<>"Self",H18<>""),"Delegate", IF( D18="Project","Projects", IF( D18="Routine","Routines", IF( D18="Task","Someday", IF( D18="Reference","Reference", "" ) ) ) ) ) ) ) | M18: =IF( D18="Project","Project Details", IF( D18="Routine","Routine Details", IF( D18="Reference","Reference Details", "" ) ) ) | N18: =IF( D18="","", IF( AND(H18<>"",I18="",H18<$A$2),"Overdue", IF( AND(H18<>"",I18="",(7*1+$A$2)>H18),"Due 7d", IF( AND(H18<>"",I18="",(30*1+$A$2)>H18),"Due 30d", "None" ) ) ) ) | O18: =IF( D18="","", IF( I18>($A$2-7*$B$2),"Yes", IF( J18>($A$2-7*$B$2),"Yes", "No" ) ) ) | P18: =IF( D18="","", IF( AND(H18<>"",G18=""),"Error: no Owner for Task with Due Date", "ok" ) ) | Q18: z
C19: =IF( D19=""," - ZZZ", " - "&F19&E19&F19) -> - ZZZ | L19: =IF( I19<>"","Delete", IF( AND(G19="Self",H19<>""),"Defer", IF( AND(G19<>"",G19<>"Self",H19<>""),"Delegate", IF( D19="Project","Projects", IF( D19="Routine","Routines", IF( D19="Task","Someday", IF( D19="Reference","Reference", "" ) ) ) ) ) ) ) | M19: =IF( D19="Project","Project Details", IF( D19="Routine","Routine Details", IF( D19="Reference","Reference Details", "" ) ) ) | N19: =IF( D19="","", IF( AND(H19<>"",I19="",H19<$A$2),"Overdue", IF( AND(H19<>"",I19="",(7*1+$A$2)>H19),"Due 7d", IF( AND(H19<>"",I19="",(30*1+$A$2)>H19),"Due 30d", "None" ) ) ) ) | O19: =IF( D19="","", IF( I19>($A$2-7*$B$2),"Yes", IF( J19>($A$2-7*$B$2),"Yes", "No" ) ) ) | P19: =IF( D19="","", IF( AND(H19<>"",G19=""),"Error: no Owner for Task with Due Date", "ok" ) ) | Q19: z
C20: =IF( D20=""," - ZZZ", " - "&F20&E20&F20) -> - ZZZ | L20: =IF( I20<>"","Delete", IF( AND(G20="Self",H20<>""),"Defer", IF( AND(G20<>"",G20<>"Self",H20<>""),"Delegate", IF( D20="Project","Projects", IF( D20="Routine","Routines", IF( D20="Task","Someday", IF( D20="Reference","Reference", "" ) ) ) ) ) ) ) | M20: =IF( D20="Project","Project Details", IF( D20="Routine","Routine Details", IF( D20="Reference","Reference Details", "" ) ) ) | N20: =IF( D20="","", IF( AND(H20<>"",I20="",H20<$A$2),"Overdue", IF( AND(H20<>"",I20="",(7*1+$A$2)>H20),"Due 7d", IF( AND(H20<>"",I20="",(30*1+$A$2)>H20),"Due 30d", "None" ) ) ) ) | O20: =IF( D20="","", IF( I20>($A$2-7*$B$2),"Yes", IF( J20>($A$2-7*$B$2),"Yes", "No" ) ) ) | P20: =IF( D20="","", IF( AND(H20<>"",G20=""),"Error: no Owner for Task with Due Date", "ok" ) ) | Q20: z
C21: =IF( D21=""," - ZZZ", " - "&F21&E21&F21) -> - ZZZ | L21: =IF( I21<>"","Delete", IF( AND(G21="Self",H21<>""),"Defer", IF( AND(G21<>"",G21<>"Self",H21<>""),"Delegate", IF( D21="Project","Projects", IF( D21="Routine","Routines", IF( D21="Task","Someday", IF( D21="Reference","Reference", "" ) ) ) ) ) ) ) | M21: =IF( D21="Project","Project Details", IF( D21="Routine","Routine Details", IF( D21="Reference","Reference Details", "" ) ) ) | N21: =IF( D21="","", IF( AND(H21<>"",I21="",H21<$A$2),"Overdue", IF( AND(H21<>"",I21="",(7*1+$A$2)>H21),"Due 7d", IF( AND(H21<>"",I21="",(30*1+$A$2)>H21),"Due 30d", "None" ) ) ) ) | O21: =IF( D21="","", IF( I21>($A$2-7*$B$2),"Yes", IF( J21>($A$2-7*$B$2),"Yes", "No" ) ) ) | P21: =IF( D21="","", IF( AND(H21<>"",G21=""),"Error: no Owner for Task with Due Date", "ok" ) ) | Q21: z
C22: =IF( D22=""," - ZZZ", " - "&F22&E22&F22) -> - ZZZ | L22: =IF( I22<>"","Delete", IF( AND(G22="Self",H22<>""),"Defer", IF( AND(G22<>"",G22<>"Self",H22<>""),"Delegate", IF( D22="Project","Projects", IF( D22="Routine","Routines", IF( D22="Task","Someday", IF( D22="Reference","Reference", "" ) ) ) ) ) ) ) | M22: =IF( D22="Project","Project Details", IF( D22="Routine","Routine Details", IF( D22="Reference","Reference Details", "" ) ) ) | N22: =IF( D22="","", IF( AND(H22<>"",I22="",H22<$A$2),"Overdue", IF( AND(H22<>"",I22="",(7*1+$A$2)>H22),"Due 7d", IF( AND(H22<>"",I22="",(30*1+$A$2)>H22),"Due 30d", "None" ) ) ) ) | O22: =IF( D22="","", IF( I22>($A$2-7*$B$2),"Yes", IF( J22>($A$2-7*$B$2),"Yes", "No" ) ) ) | P22: =IF( D22="","", IF( AND(H22<>"",G22=""),"Error: no Owner for Task with Due Date", "ok" ) ) | Q22: z
C23: =IF( D23=""," - ZZZ", " - "&F23&E23&F23) -> - ZZZ | L23: =IF( I23<>"","Delete", IF( AND(G23="Self",H23<>""),"Defer", IF( AND(G23<>"",G23<>"Self",H23<>""),"Delegate", IF( D23="Project","Projects", IF( D23="Routine","Routines", IF( D23="Task","Someday", IF( D23="Reference","Reference", "" ) ) ) ) ) ) ) | M23: =IF( D23="Project","Project Details", IF( D23="Routine","Routine Details", IF( D23="Reference","Reference Details", "" ) ) ) | N23: =IF( D23="","", IF( AND(H23<>"",I23="",H23<$A$2),"Overdue", IF( AND(H23<>"",I23="",(7*1+$A$2)>H23),"Due 7d", IF( AND(H23<>"",I23="",(30*1+$A$2)>H23),"Due 30d", "None" ) ) ) ) | O23: =IF( D23="","", IF( I23>($A$2-7*$B$2),"Yes", IF( J23>($A$2-7*$B$2),"Yes", "No" ) ) ) | P23: =IF( D23="","", IF( AND(H23<>"",G23=""),"Error: no Owner for Task with Due Date", "ok" ) ) | Q23: z
C24: =IF( D24=""," - ZZZ", " - "&F24&E24&F24) -> - ZZZ | L24: =IF( I24<>"","Delete", IF( AND(G24="Self",H24<>""),"Defer", IF( AND(G24<>"",G24<>"Self",H24<>""),"Delegate", IF( D24="Project","Projects", IF( D24="Routine","Routines", IF( D24="Task","Someday", IF( D24="Reference","Reference", "" ) ) ) ) ) ) ) | M24: =IF( D24="Project","Project Details", IF( D24="Routine","Routine Details", IF( D24="Reference","Reference Details", "" ) ) ) | N24: =IF( D24="","", IF( AND(H24<>"",I24="",H24<$A$2),"Overdue", IF( AND(H24<>"",I24="",(7*1+$A$2)>H24),"Due 7d", IF( AND(H24<>"",I24="",(30*1+$A$2)>H24),"Due 30d", "None" ) ) ) ) | O24: =IF( D24="","", IF( I24>($A$2-7*$B$2),"Yes", IF( J24>($A$2-7*$B$2),"Yes", "No" ) ) ) | P24: =IF( D24="","", IF( AND(H24<>"",G24=""),"Error: no Owner for Task with Due Date", "ok" ) ) | Q24: z
C25: =IF( D25=""," - ZZZ", " - "&F25&E25&F25) -> - ZZZ | L25: =IF( I25<>"","Delete", IF( AND(G25="Self",H25<>""),"Defer", IF( AND(G25<>"",G25<>"Self",H25<>""),"Delegate", IF( D25="Project","Projects", IF( D25="Routine","Routines", IF( D25="Task","Someday", IF( D25="Reference","Reference", "" ) ) ) ) ) ) ) | M25: =IF( D25="Project","Project Details", IF( D25="Routine","Routine Details", IF( D25="Reference","Reference Details", "" ) ) ) | N25: =IF( D25="","", IF( AND(H25<>"",I25="",H25<$A$2),"Overdue", IF( AND(H25<>"",I25="",(7*1+$A$2)>H25),"Due 7d", IF( AND(H25<>"",I25="",(30*1+$A$2)>H25),"Due 30d", "None" ) ) ) ) | O25: =IF( D25="","", IF( I25>($A$2-7*$B$2),"Yes", IF( J25>($A$2-7*$B$2),"Yes", "No" ) ) ) | P25: =IF( D25="","", IF( AND(H25<>"",G25=""),"Error: no Owner for Task with Due Date", "ok" ) ) | Q25: z
... C61: =IF( D61=""," - ZZZ", " - "&F61&E61&F61) -> - ZZZ | L61: =IF( I61<>"","Delete", IF( AND(G61="Self",H61<>""),"Defer", IF( AND(G61<>"",G61<>"Self",H61<>""),"Delegate", IF( D61="Project","Projects", IF( D61="Routine","Routines", IF( D61="Task","Someday", IF( D61="Reference","Reference", "" ) ) ) ) ) ) ) | M61: =IF( D61="Project","Project Details", IF( D61="Routine","Routine Details", IF( D61="Reference","Reference Details", "" ) ) ) | N61: =IF( D61="","", IF( AND(H61<>"",I61="",H61<$A$2),"Overdue", IF( AND(H61<>"",I61="",(7*1+$A$2)>H61),"Due 7d", IF( AND(H61<>"",I61="",(30*1+$A$2)>H61),"Due 30d", "None" ) ) ) ) | O61: =IF( D61="","", IF( I61>($A$2-7*$B$2),"Yes", IF( J61>($A$2-7*$B$2),"Yes", "No" ) ) ) | P61: =IF( D61="","", IF( AND(H61<>"",G61=""),"Error: no Owner for Task with Due Date", "ok" ) ) | Q61: z

Sheet Log
O1: x
O2: x
O3: x
A4: =A3 -> 0 | B4: =B3 -> 0 | C4: =C3 -> 0 | D4: =D3 -> 0 | E4: =E3 -> 0 | F4: =F3 -> 0 | G4: =G3 -> 0 | J4: =J3 -> 0 | K4: =K3 -> 0 | L4: =L3 -> 0 | M4: =M3 -> 0 | N4: =N3 -> 0 | O4: =O3 -> x
O5: x
O6: x
O7: x
O15: x
O16: x
O17: x
O18: x
O19: x
O20: x
A21: =TODAY() -> 46321 | B21: Calculated. Nr Tasks in Status indicated by name of this Column. The IF() is to account for the fact that typing anything at the start of a cell is not preceded the <ENTER> Character CHAR(10). | C21: Calculated. Nr Tasks in Status indicated by name of this Column. The IF() is to account for the fact that typing anything at the start of a cell is not preceded the <ENTER> Character CHAR(10). | D21: Calculated. Nr Tasks in Status indicated by name of this Column. The IF() is to account for the fact that typing anything at the start of a cell is not preceded the <ENTER> Character CHAR(10). | E21: Calculated. Nr Tasks in Status indicated by name of this Column. The IF() is to account for the fact that typing anything at the start of a cell is not preceded the <ENTER> Character CHAR(10). | F21: Calculated. Nr Tasks in Status indicated by name of this Column. The IF() is to account for the fact that typing anything at the start of a cell is not preceded the <ENTER> Character CHAR(10). | G21: Calaculated. Sum of all Tasks in Tasks. | J21: Mandatory. 6W = What: part 1 of Name. Name is preferably unique within the Tracking Type and should start with a Verb. Verbs are an indication of targeted Result, see [MGT: 99. Tools ## Objective Definition]: - Assist: somebody in execution of their Process - Attend: prepare and attend a meeting - Build: something new from scratch - Complete: something started elsewhere/prior - Create: same as Build - Define: a Target/expected Result, next Build/Create - Deploy: as new something existing elsewhere - Expand: something existing by adding to it - Improve: something existing by automation etc. - Increase: something existing by a numeric value - Learn: something that may become important later on - Maintain: something existing at current level - Meet: someone on regular or ad-hoc basis - Perform: one or more specific Processes - Prepare: a deliverable for completion elsewhere - Process: take in a request and deliver Result - React to: a situation with specific measures - Report to: Staff, Manager, Committee via mail - Resolve: Problems - Review: Result vs Target + assess if change needed - Rewrite: an existing document | K21: Mandatory. Notes drive two columns: Start Date and Last Date. Format for each line: dd-mm-yy: xxx in which dd, mm and yy are day, month and year and xxx is free text. | L21: Optional. Tasks with individual Status. Multiple entries are possible. In combination with Column = Updated this column helps in Reporting. Items follow the Objective Notation as per [MGT: 99.Tools ## Objective Notation] i.e. Status Description (start:end:complete) {who} [ref] NB: Goal end Effort are not relevant for this Column. Used in Formulas. | M21: Calculated. Nr non-completed Tasks. | N21: Calculated. Nr Tasks non-completed Tasks over total nr Tasks as %. | O21: Last Column. Contains value = “X”.
A23: A | B23: Tasks Open | C23: Tasks Started | D23: Tasks Pending | E23: Tasks Urgent | F23: Tasks Done | G23: Tasks Total | H23: Date | I23: Log Type | J23: Name | K23: Notes | L23: Tasks | M23: Tasks Left | N23: Task Progress | O23: Z
A24: =A23 -> A | B24: =B23 -> Tasks Open | C24: =C23 -> Tasks Started | D24: =D23 -> Tasks Pending | E24: =E23 -> Tasks Urgent | F24: =F23 -> Tasks Done | G24: =G23 -> Tasks Total | H24: =H23 -> Date | ... O24: =O23 -> Z
B25: =((LEN($L25)-LEN(SUBSTITUTE($L25,CHAR(10)&". ","")))/3)+IF(LEFT(TRIM($L25),2)=". ",1,0) -> 0 | C25: =((LEN($L25)-LEN(SUBSTITUTE($L25,CHAR(10)&"/ ","")))/3)+IF(LEFT(TRIM($L25),2)="/ ",1,0) -> 0 | D25: =((LEN($L25)-LEN(SUBSTITUTE($L25,CHAR(10)&"~ ","")))/3)+IF(LEFT(TRIM($L25),2)="~ ",1,0) -> 0 | E25: =((LEN($L25)-LEN(SUBSTITUTE($L25,CHAR(10)&"! ","")))/3)+IF(LEFT(TRIM($L25),2)="! ",1,0) -> 0 | F25: =((LEN($L25)-LEN(SUBSTITUTE($L25,CHAR(10)&"x ","")))/3)+IF(LEFT(TRIM($L25),2)="x ",1,0) -> 0 | G25: =SUM(B25:F25) -> 0 | H25: 45918 | I25: Toto | J25: Do mandatory training | M25: =IF(J25="","",SUM(B25:E25)) -> 0 | N25: =IF(J25="","",IF(G25<>0,(C25*0.5+F25)/G25,1)) -> 1 | O25: x
B26: =((LEN($L26)-LEN(SUBSTITUTE($L26,CHAR(10)&". ","")))/3)+IF(LEFT(TRIM($L26),2)=". ",1,0) -> 0 | C26: =((LEN($L26)-LEN(SUBSTITUTE($L26,CHAR(10)&"/ ","")))/3)+IF(LEFT(TRIM($L26),2)="/ ",1,0) -> 0 | D26: =((LEN($L26)-LEN(SUBSTITUTE($L26,CHAR(10)&"~ ","")))/3)+IF(LEFT(TRIM($L26),2)="~ ",1,0) -> 0 | E26: =((LEN($L26)-LEN(SUBSTITUTE($L26,CHAR(10)&"! ","")))/3)+IF(LEFT(TRIM($L26),2)="! ",1,0) -> 0 | F26: =((LEN($L26)-LEN(SUBSTITUTE($L26,CHAR(10)&"x ","")))/3)+IF(LEFT(TRIM($L26),2)="x ",1,0) -> 0 | G26: =SUM(B26:F26) -> 0 | M26: =IF(J26="","",SUM(B26:E26)) | N26: =IF(J26="","",IF(G26<>0,(C26*0.5+F26)/G26,1)) | O26: x
B27: =((LEN($L27)-LEN(SUBSTITUTE($L27,CHAR(10)&". ","")))/3)+IF(LEFT(TRIM($L27),2)=". ",1,0) -> 0 | C27: =((LEN($L27)-LEN(SUBSTITUTE($L27,CHAR(10)&"/ ","")))/3)+IF(LEFT(TRIM($L27),2)="/ ",1,0) -> 0 | D27: =((LEN($L27)-LEN(SUBSTITUTE($L27,CHAR(10)&"~ ","")))/3)+IF(LEFT(TRIM($L27),2)="~ ",1,0) -> 0 | E27: =((LEN($L27)-LEN(SUBSTITUTE($L27,CHAR(10)&"! ","")))/3)+IF(LEFT(TRIM($L27),2)="! ",1,0) -> 0 | F27: =((LEN($L27)-LEN(SUBSTITUTE($L27,CHAR(10)&"x ","")))/3)+IF(LEFT(TRIM($L27),2)="x ",1,0) -> 0 | G27: =SUM(B27:F27) -> 0 | M27: =IF(J27="","",SUM(B27:E27)) | N27: =IF(J27="","",IF(G27<>0,(C27*0.5+F27)/G27,1)) | O27: x
B28: =((LEN($L28)-LEN(SUBSTITUTE($L28,CHAR(10)&". ","")))/3)+IF(LEFT(TRIM($L28),2)=". ",1,0) -> 0 | C28: =((LEN($L28)-LEN(SUBSTITUTE($L28,CHAR(10)&"/ ","")))/3)+IF(LEFT(TRIM($L28),2)="/ ",1,0) -> 0 | D28: =((LEN($L28)-LEN(SUBSTITUTE($L28,CHAR(10)&"~ ","")))/3)+IF(LEFT(TRIM($L28),2)="~ ",1,0) -> 0 | E28: =((LEN($L28)-LEN(SUBSTITUTE($L28,CHAR(10)&"! ","")))/3)+IF(LEFT(TRIM($L28),2)="! ",1,0) -> 0 | F28: =((LEN($L28)-LEN(SUBSTITUTE($L28,CHAR(10)&"x ","")))/3)+IF(LEFT(TRIM($L28),2)="x ",1,0) -> 0 | G28: =SUM(B28:F28) -> 0 | M28: =IF(J28="","",SUM(B28:E28)) | N28: =IF(J28="","",IF(G28<>0,(C28*0.5+F28)/G28,1)) | O28: x
B29: =((LEN($L29)-LEN(SUBSTITUTE($L29,CHAR(10)&". ","")))/3)+IF(LEFT(TRIM($L29),2)=". ",1,0) -> 0 | C29: =((LEN($L29)-LEN(SUBSTITUTE($L29,CHAR(10)&"/ ","")))/3)+IF(LEFT(TRIM($L29),2)="/ ",1,0) -> 0 | D29: =((LEN($L29)-LEN(SUBSTITUTE($L29,CHAR(10)&"~ ","")))/3)+IF(LEFT(TRIM($L29),2)="~ ",1,0) -> 0 | E29: =((LEN($L29)-LEN(SUBSTITUTE($L29,CHAR(10)&"! ","")))/3)+IF(LEFT(TRIM($L29),2)="! ",1,0) -> 0 | F29: =((LEN($L29)-LEN(SUBSTITUTE($L29,CHAR(10)&"x ","")))/3)+IF(LEFT(TRIM($L29),2)="x ",1,0) -> 0 | G29: =SUM(B29:F29) -> 0 | M29: =IF(J29="","",SUM(B29:E29)) | N29: =IF(J29="","",IF(G29<>0,(C29*0.5+F29)/G29,1)) | O29: x
B30: =((LEN($L30)-LEN(SUBSTITUTE($L30,CHAR(10)&". ","")))/3)+IF(LEFT(TRIM($L30),2)=". ",1,0) -> 0 | C30: =((LEN($L30)-LEN(SUBSTITUTE($L30,CHAR(10)&"/ ","")))/3)+IF(LEFT(TRIM($L30),2)="/ ",1,0) -> 0 | D30: =((LEN($L30)-LEN(SUBSTITUTE($L30,CHAR(10)&"~ ","")))/3)+IF(LEFT(TRIM($L30),2)="~ ",1,0) -> 0 | E30: =((LEN($L30)-LEN(SUBSTITUTE($L30,CHAR(10)&"! ","")))/3)+IF(LEFT(TRIM($L30),2)="! ",1,0) -> 0 | F30: =((LEN($L30)-LEN(SUBSTITUTE($L30,CHAR(10)&"x ","")))/3)+IF(LEFT(TRIM($L30),2)="x ",1,0) -> 0 | G30: =SUM(B30:F30) -> 0 | M30: =IF(J30="","",SUM(B30:E30)) | N30: =IF(J30="","",IF(G30<>0,(C30*0.5+F30)/G30,1)) | O30: x
B31: =((LEN($L31)-LEN(SUBSTITUTE($L31,CHAR(10)&". ","")))/3)+IF(LEFT(TRIM($L31),2)=". ",1,0) -> 0 | C31: =((LEN($L31)-LEN(SUBSTITUTE($L31,CHAR(10)&"/ ","")))/3)+IF(LEFT(TRIM($L31),2)="/ ",1,0) -> 0 | D31: =((LEN($L31)-LEN(SUBSTITUTE($L31,CHAR(10)&"~ ","")))/3)+IF(LEFT(TRIM($L31),2)="~ ",1,0) -> 0 | E31: =((LEN($L31)-LEN(SUBSTITUTE($L31,CHAR(10)&"! ","")))/3)+IF(LEFT(TRIM($L31),2)="! ",1,0) -> 0 | F31: =((LEN($L31)-LEN(SUBSTITUTE($L31,CHAR(10)&"x ","")))/3)+IF(LEFT(TRIM($L31),2)="x ",1,0) -> 0 | G31: =SUM(B31:F31) -> 0 | M31: =IF(J31="","",SUM(B31:E31)) | N31: =IF(J31="","",IF(G31<>0,(C31*0.5+F31)/G31,1)) | O31: x
B32: =((LEN($L32)-LEN(SUBSTITUTE($L32,CHAR(10)&". ","")))/3)+IF(LEFT(TRIM($L32),2)=". ",1,0) -> 0 | C32: =((LEN($L32)-LEN(SUBSTITUTE($L32,CHAR(10)&"/ ","")))/3)+IF(LEFT(TRIM($L32),2)="/ ",1,0) -> 0 | D32: =((LEN($L32)-LEN(SUBSTITUTE($L32,CHAR(10)&"~ ","")))/3)+IF(LEFT(TRIM($L32),2)="~ ",1,0) -> 0 | E32: =((LEN($L32)-LEN(SUBSTITUTE($L32,CHAR(10)&"! ","")))/3)+IF(LEFT(TRIM($L32),2)="! ",1,0) -> 0 | F32: =((LEN($L32)-LEN(SUBSTITUTE($L32,CHAR(10)&"x ","")))/3)+IF(LEFT(TRIM($L32),2)="x ",1,0) -> 0 | G32: =SUM(B32:F32) -> 0 | M32: =IF(J32="","",SUM(B32:E32)) | N32: =IF(J32="","",IF(G32<>0,(C32*0.5+F32)/G32,1)) | O32: x
B33: =((LEN($L33)-LEN(SUBSTITUTE($L33,CHAR(10)&". ","")))/3)+IF(LEFT(TRIM($L33),2)=". ",1,0) -> 0 | C33: =((LEN($L33)-LEN(SUBSTITUTE($L33,CHAR(10)&"/ ","")))/3)+IF(LEFT(TRIM($L33),2)="/ ",1,0) -> 0 | D33: =((LEN($L33)-LEN(SUBSTITUTE($L33,CHAR(10)&"~ ","")))/3)+IF(LEFT(TRIM($L33),2)="~ ",1,0) -> 0 | E33: =((LEN($L33)-LEN(SUBSTITUTE($L33,CHAR(10)&"! ","")))/3)+IF(LEFT(TRIM($L33),2)="! ",1,0) -> 0 | F33: =((LEN($L33)-LEN(SUBSTITUTE($L33,CHAR(10)&"x ","")))/3)+IF(LEFT(TRIM($L33),2)="x ",1,0) -> 0 | G33: =SUM(B33:F33) -> 0 | M33: =IF(J33="","",SUM(B33:E33)) | N33: =IF(J33="","",IF(G33<>0,(C33*0.5+F33)/G33,1)) | O33: x
B34: =((LEN($L34)-LEN(SUBSTITUTE($L34,CHAR(10)&". ","")))/3)+IF(LEFT(TRIM($L34),2)=". ",1,0) -> 0 | C34: =((LEN($L34)-LEN(SUBSTITUTE($L34,CHAR(10)&"/ ","")))/3)+IF(LEFT(TRIM($L34),2)="/ ",1,0) -> 0 | D34: =((LEN($L34)-LEN(SUBSTITUTE($L34,CHAR(10)&"~ ","")))/3)+IF(LEFT(TRIM($L34),2)="~ ",1,0) -> 0 | E34: =((LEN($L34)-LEN(SUBSTITUTE($L34,CHAR(10)&"! ","")))/3)+IF(LEFT(TRIM($L34),2)="! ",1,0) -> 0 | F34: =((LEN($L34)-LEN(SUBSTITUTE($L34,CHAR(10)&"x ","")))/3)+IF(LEFT(TRIM($L34),2)="x ",1,0) -> 0 | G34: =SUM(B34:F34) -> 0 | M34: =IF(J34="","",SUM(B34:E34)) | N34: =IF(J34="","",IF(G34<>0,(C34*0.5+F34)/G34,1)) | O34: x
B35: =((LEN($L35)-LEN(SUBSTITUTE($L35,CHAR(10)&". ","")))/3)+IF(LEFT(TRIM($L35),2)=". ",1,0) -> 0 | C35: =((LEN($L35)-LEN(SUBSTITUTE($L35,CHAR(10)&"/ ","")))/3)+IF(LEFT(TRIM($L35),2)="/ ",1,0) -> 0 | D35: =((LEN($L35)-LEN(SUBSTITUTE($L35,CHAR(10)&"~ ","")))/3)+IF(LEFT(TRIM($L35),2)="~ ",1,0) -> 0 | E35: =((LEN($L35)-LEN(SUBSTITUTE($L35,CHAR(10)&"! ","")))/3)+IF(LEFT(TRIM($L35),2)="! ",1,0) -> 0 | F35: =((LEN($L35)-LEN(SUBSTITUTE($L35,CHAR(10)&"x ","")))/3)+IF(LEFT(TRIM($L35),2)="x ",1,0) -> 0 | G35: =SUM(B35:F35) -> 0 | M35: =IF(J35="","",SUM(B35:E35)) | N35: =IF(J35="","",IF(G35<>0,(C35*0.5+F35)/G35,1)) | O35: x
B36: =((LEN($L36)-LEN(SUBSTITUTE($L36,CHAR(10)&". ","")))/3)+IF(LEFT(TRIM($L36),2)=". ",1,0) -> 0 | C36: =((LEN($L36)-LEN(SUBSTITUTE($L36,CHAR(10)&"/ ","")))/3)+IF(LEFT(TRIM($L36),2)="/ ",1,0) -> 0 | D36: =((LEN($L36)-LEN(SUBSTITUTE($L36,CHAR(10)&"~ ","")))/3)+IF(LEFT(TRIM($L36),2)="~ ",1,0) -> 0 | E36: =((LEN($L36)-LEN(SUBSTITUTE($L36,CHAR(10)&"! ","")))/3)+IF(LEFT(TRIM($L36),2)="! ",1,0) -> 0 | F36: =((LEN($L36)-LEN(SUBSTITUTE($L36,CHAR(10)&"x ","")))/3)+IF(LEFT(TRIM($L36),2)="x ",1,0) -> 0 | G36: =SUM(B36:F36) -> 0 | M36: =IF(J36="","",SUM(B36:E36)) | N36: =IF(J36="","",IF(G36<>0,(C36*0.5+F36)/G36,1)) | O36: x
B37: =((LEN($L37)-LEN(SUBSTITUTE($L37,CHAR(10)&". ","")))/3)+IF(LEFT(TRIM($L37),2)=". ",1,0) -> 0 | C37: =((LEN($L37)-LEN(SUBSTITUTE($L37,CHAR(10)&"/ ","")))/3)+IF(LEFT(TRIM($L37),2)="/ ",1,0) -> 0 | D37: =((LEN($L37)-LEN(SUBSTITUTE($L37,CHAR(10)&"~ ","")))/3)+IF(LEFT(TRIM($L37),2)="~ ",1,0) -> 0 | E37: =((LEN($L37)-LEN(SUBSTITUTE($L37,CHAR(10)&"! ","")))/3)+IF(LEFT(TRIM($L37),2)="! ",1,0) -> 0 | F37: =((LEN($L37)-LEN(SUBSTITUTE($L37,CHAR(10)&"x ","")))/3)+IF(LEFT(TRIM($L37),2)="x ",1,0) -> 0 | G37: =SUM(B37:F37) -> 0 | M37: =IF(J37="","",SUM(B37:E37)) | N37: =IF(J37="","",IF(G37<>0,(C37*0.5+F37)/G37,1)) | O37: x
... B81: =((LEN($L81)-LEN(SUBSTITUTE($L81,CHAR(10)&". ","")))/3)+IF(LEFT(TRIM($L81),2)=". ",1,0) -> 0 | C81: =((LEN($L81)-LEN(SUBSTITUTE($L81,CHAR(10)&"/ ","")))/3)+IF(LEFT(TRIM($L81),2)="/ ",1,0) -> 0 | D81: =((LEN($L81)-LEN(SUBSTITUTE($L81,CHAR(10)&"~ ","")))/3)+IF(LEFT(TRIM($L81),2)="~ ",1,0) -> 0 | E81: =((LEN($L81)-LEN(SUBSTITUTE($L81,CHAR(10)&"! ","")))/3)+IF(LEFT(TRIM($L81),2)="! ",1,0) -> 0 | F81: =((LEN($L81)-LEN(SUBSTITUTE($L81,CHAR(10)&"x ","")))/3)+IF(LEFT(TRIM($L81),2)="x ",1,0) -> 0 | G81: =SUM(B81:F81) -> 0 | M81: =IF(J81="","",SUM(B81:E81)) | N81: =IF(J81="","",IF(G81<>0,(C81*0.5+F81)/G81,1)) | O81: x

Sheet 01.09.Planning
C1: This space can hbe used to produce stats on below data | AU1: x
C2: Depending on the venture it can also contain stats on data maintained elsewhere | AU2: x
AU3: x
A4: =A3 -> 0 | B4: =B3 -> 0 | C4: =C3 -> 0 | D4: =D3 -> 0 | E4: =E3 -> 0 | F4: =F3 -> 0 | G4: =G3 -> 0 | H4: =H3 -> 0 | ... AJ4: =AJ3 -> 0 | AL4: =AL3 -> 0 | AM4: =AM3 -> 0 | AN4: =AN3 -> 0 | AO4: =AO3 -> 0 | AP4: =AP3 -> 0 | AQ4: =AQ3 -> 0 | AR4: =AR3 -> 0 | AS4: =AS3 -> 0 | ... AU4: =AU3 -> x
AU5: x
AU6: x
AU7: x
AC8: This space can be used to produce stats on below data | AU8: x
AC9: Depending on the venture it can also contain stats on data maintained elsewhere | AU9: x
AC10: Insert as many rows as necessary | AU10: x
AU11: x
AU12: x
AU13: x
A14: =TODAY() -> 46321 | B14: Calculated. 6W. Who: Performer. If Column = Who is populated the value of Who else myself. | C14: Calculated. 6W Who: Beneficiary. The beneficiary of the Entry. The default is the venture. | D14: Calculated. Date of the Last Note or epoch based on Col = Notes. | E14: Calcualted. Time between Last Date and Start Date. | F14: Calculated. Nr Tasks in Status indicated by name of this Column. The IF() is to account for the fact that typing anything at the start of a cell is not preceded the <ENTER> Character CHAR(10). | G14: Calculated. Nr Tasks in Status indicated by name of this Column. The IF() is to account for the fact that typing anything at the start of a cell is not preceded the <ENTER> Character CHAR(10). | H14: Calculated. Nr Tasks in Status indicated by name of this Column. The IF() is to account for the fact that typing anything at the start of a cell is not preceded the <ENTER> Character CHAR(10). | I14: Calculated. Nr Tasks in Status indicated by name of this Column. The IF() is to account for the fact that typing anything at the start of a cell is not preceded the <ENTER> Character CHAR(10). | J14: Calculated. Nr Tasks in Status indicated by name of this Column. The IF() is to account for the fact that typing anything at the start of a cell is not preceded the <ENTER> Character CHAR(10). | K14: Calaculated. Sum of all Tasks in Tasks. | L14: Calculated. Year of Last Date. | M14: Calculated. Month of Last Date. | N14: Calculated. Week number of Last Date. | O14: Calculated. The sort relevance of the Journal Entry based on the Bujo Type and Sheet = Static. | P14: Calculated. Establishes whether the item is reportable based on Tracking Type. | Q14: Calcualted. Whether the Last Date was within X weeks of the Monday of the week of the date in cell $D$2. | R14: Calculated. Whether the entry has open tasks, i.e. entries in Tasks that are “. “, “/ “, “~ “ or “! “ but not “x “. | S14: Calculated. Indicates whether the Jounral entry was completed recently based on Last Date and Active?. NB: an entry like Roadmap, Project, ToDo is deemed Completed if there is no remaining Tasks and the Last Date is thus the completion data for that entry. | T14: Calculated. Whether the Jounral entry is reportable based on whether the Last Date is newer than the monday X weeks ago, with X determined in Cell $D$2. | U14: Calculated. Show a entry only if there is: - En empty entry OR - An Active entry OR - Start Date = Today This avoid having too many entries that are not worked on anymore. | V14: Calculated. Assures Tracking Type = Management is at the top, then Routines, then Projects that are Roadmap items, then Projects and then the rest of the entries. | W14: Calculated. The weekday of Column = Start Date. | X14: Calculated. 6W. When: Start Date. Same value as Column = First Note Date. | Y14: Optional. Can force the reporting of a Journal Entry if the defaulting rules would (not) report an entry. | Z14: Optional. Tag the entry for specific filtering. The value can be freely chosen. It is possible to have multiple comma-separated values. This column is an incredibly powerful feature of the entire sheet. | AA14: Mandatory. In theory several options possible, but choose only “Routine”. | AB14: Mandatory. 6W = What: part 1 of Name. Name is preferably unique within the Tracking Type and should start with a Verb. Verbs are an indication of targeted Result, see [MGT: 99. Tools ## Objective Definition]: - Assist: somebody in execution of their Process - Attend: prepare and attend a meeting - Build: something new from scratch - Complete: something started elsewhere/prior - Create: same as Build - Define: a Target/expected Result, next Build/Create - Deploy: as new something existing elsewhere - Expand: something existing by adding to it - Improve: something existing by automation etc. - Increase: something existing by a numeric value - Learn: something that may become important later on - Maintain: something existing at current level - Meet: someone on regular or ad-hoc basis - Perform: one or more specific Processes - Prepare: a deliverable for completion elsewhere - Process: take in a request and deliver Result - React to: a situation with specific measures - Report to: Staff, Manager, Committee via mail - Resolve: Problems - Review: Result vs Target + assess if change needed - Rewrite: an existing document | AC14: Mandatory. 6W = What: Name part 2, Overview. High Level overview of Name. Recommended use: slightly shorter descrip - For Tracking Type in (Management, Routine) all relevant details including references to Paths, URLs - For Tracking Type in (Roadmap, Project, ToDo) give a short description of the Objective. Details can go into Col = Reference. | AD14: Mandatory. The frequency type of the Routine, based on a drop-down list maintained in Sheet=Static. | AE14: Mandatory. The number of times the Routine is done throughout a year. This is partially linked to Period (label): Day -> 260 (without holidays), 220 (with holidays) Week -> 52 (without holidays), 48 (with full week holidays) Month -> 12 Quarterly -> 4 Semi-annually -> 2 Annually -> 1 Ad-hoc -> this is determined by the user depending on expetations based on past or current information | AF14: Mandatory. THe amount of hours worked on each time the Routine is performed. | AG14: Calculated. Total nr of 8-hour days the ROutine takes. | AH14: Mandatory. The Performer of the Rotuine. The person performing the entry i.e. delivering a Routine, Project, Roadmap. etc. | AI14: Mandatory. The Beneficiery. The Activity for which this is performed. The Default = the entire Venture VNT. | AJ14: Mandatory. 6W = Why. The Goal to which the item belongs. Goals are maintained in Sheet = Static. | AK14: Optional: This column has a drop-down which is based on the value in the column to the left i.e. Sub-Goal depends on Goal. | AL14: Optional. 6W = How: Details of how the Routine is achieved. | AM14: Mandatory. Notes drive two columns: Start Date and Last Date. Format for each line: dd-mm-yy: xxx in which dd, mm and yy are day, month and year and xxx is free text. | AN14: Optional. Tasks with individual Status. Multiple entries are possible. In combination with Column = Updated this column helps in Reporting. Items follow the Objective Notation as per [MGT: 99.Tools ## Objective Notation] i.e. Status Description (start:end:complete) {who} [ref] NB: Goal end Effort are not relevant for this Column. Used in Formulas. | AO14: Calculated. Nr non-completed Tasks. | AP14: Calculated. Nr Tasks non-completed Tasks over total nr Tasks as %. | AQ14: Calculated. First Note of Column = Notes. | AR14: Calculated. Last Note -f Column = Notes. | AS14: Calculated. Date of First NoTe from Column = First Note. | AT14: Calculated. Date of Last Note from Column = Last Note. | AU14: Last Column. Contains value = “X”.
D15: 1
A16: A | B16: Performer | C16: Beneficiary | D16: Last Date | E16: Duration | F16: Tasks Open | G16: Tasks Started | H16: Tasks Pending | I16: Tasks Urgent | J16: Tasks Done | K16: Tasks Total | L16: Last Date Year | M16: Last Date Month | N16: Last Date Week | O16: Tracking Type Sort | P16: Report Eligible? | Q16: Last wk? | R16: Active ? | S16: Done ? | T16: Rep ? | U16: Show ? | V16: Sort | W16: Day | X16: Calc Start Date | Y16: Force Rep? | Z16: Tag | AA16: Planning Type | AB16: Name | AC16: Overview | AD16: Period (label) | AE16: Period (count) | AF16: Effort / count (hr) | AG16: Effort / yr (days) | AH16: Whom by | AI16: Whom for | AJ16: Goal | AK16: Sub-Goal | AL16: Reference | AM16: Notes | AN16: Tasks | AO16: Tasks Left | AP16: Task Progress | AQ16: First Note | AR16: Last Note | AS16: First Note Date | AT16: Last Note Date | AU16: Z
A17: =A16 -> A | B17: =B16 -> Performer | C17: =C16 -> Beneficiary | D17: =D16 -> Last Date | E17: =E16 -> Duration | F17: =F16 -> Tasks Open | G17: =G16 -> Tasks Started | H17: =H16 -> Tasks Pending | ... N17: =N16 -> Last Date Week | Q17: =Q16 -> Last wk? | R17: =R16 -> Active ? | S17: =S16 -> Done ? | T17: =T16 -> Rep ? | U17: =U16 -> Show ? | V17: =V16 -> Sort | W17: =W16 -> Day | X17: =X16 -> Calc Start Date | Y17: =Y16 -> Force Rep? | AA17: =AA16 -> Planning Type | AB17: =AB16 -> Name | AC17: =AC16 -> Overview | AD17: =AD16 -> Period (label) | AE17: =AE16 -> Period (count) | AF17: =AF16 -> Effort / count (hr) | AG17: =AG16 -> Effort / yr (days) | AH17: =AH16 -> Whom by | ... AU17: =AU16 -> Z
B18: =IF(AH18="","tbc",AH18) -> STE | C18: =IF(AI18="","VNT",AI18) -> VNT | D18: =MAX(X18,IF(AT18="none",X18,AT18)) -> 44564 | E18: =IFERROR(DAYS360(X18,D18),0) -> 0 | F18: =((LEN($AN18)-LEN(SUBSTITUTE($AN18,CHAR(10)&". ","")))/3)+IF(LEFT(TRIM($AN18),2)=". ",1,0) -> 0 | G18: =((LEN($AN18)-LEN(SUBSTITUTE($AN18,CHAR(10)&"/ ","")))/3)+IF(LEFT(TRIM($AN18),2)="/ ",1,0) -> 0 | H18: =((LEN($AN18)-LEN(SUBSTITUTE($AN18,CHAR(10)&"~ ","")))/3)+IF(LEFT(TRIM($AN18),2)="~ ",1,0) -> 0 | I18: =((LEN($AN18)-LEN(SUBSTITUTE($AN18,CHAR(10)&"! ","")))/3)+IF(LEFT(TRIM($AN18),2)="! ",1,0) -> 0 | J18: =((LEN($AN18)-LEN(SUBSTITUTE($AN18,CHAR(10)&"x ","")))/3)+IF(LEFT(TRIM($AN18),2)="x ",1,0) -> 0 | K18: =SUM(F18:J18) -> 0 | L18: =YEAR(D18) -> 2022 | M18: =VLOOKUP(MONTH(D18),Static!$AJ$3:$AK$16,2,0) -> Jan | N18: =WEEKNUM(D18,1) -> 2 | O18: =IFERROR(INDEX(Static!$I$5:$L$15,MATCH(AA18,Static!$I$5:$I$15,0),3),"Z") -> B | P18: =IFERROR(INDEX(Static!$I$5:$L$15,MATCH(AA18,Static!$I$5:$I$15,0),4),"Y") -> Y | Q18: =IF(D18>(($A$14-WEEKDAY($A$14,2))-7*$D$15),"Y","N") -> N | R18: =IF(AB18<>"","Y","N") -> Y | S18: =IF(AND(Q18="Y",R18="N"),"Y","N") -> N | T18: =IF(OR(Y18="Y",Y18="N"),Y18,IF(AND(P18="Y", OR(Q18="Y",S18="Y")),"Y","N")) -> N | U18: ="Y" -> Y | V18: =" - "&O18&AJ18&AK18&AB18 -> - BmgtleadingDo mandatory training | W18: =IFERROR(VLOOKUP(WEEKDAY(X18),Static!$AL$3:$AM$11,2,0),"") -> Mon | X18: =IF(AD18<>"",AS18,0) -> 44564 | AA18: Routine | AB18: Do mandatory training | AC18: Trainig made mandatory by the company. | AD18: Ad-hoc | AE18: 15 | AF18: 0.5 | AG18: =IF(AB18="","",AE18*AF18/8) -> 0.9375 | AH18: STE | AI18: VNT | AJ18: mgt | AK18: leading | AL18: Details: # GENERAL ## Effort ## Assets ## Context | AM18: 03-01-22: init | AO18: =SUM(F18:I18) -> 0 | AP18: =IF(AB18="",1,IF(K18<>0,(G18*0.5+J18)/K18,1)) -> 1 | AQ18: =IF(AM18="","",IF(ISERROR(FIND(CHAR(10),AM18,1)),AM18,LEFT(AM18,FIND(CHAR(10),AM18,1)))) -> 03-01-22: init | AR18: =IF(AM18="","",IFERROR(RIGHT(AM18,LEN(AM18)-FIND("@@@",SUBSTITUTE(AM18,CHAR(10),"@@@",LEN(AM18)-LEN(SUBSTITUTE(AM18,CHAR(10),""))),1)),AM18)) -> 03-01-22: init | AS18: =IFERROR(DATE(("20"&MID(AQ18,7,2))*1,MID(AQ18,4,2)*1,MID(AQ18,1,2)*1),"") -> 44564 | AT18: =IFERROR(DATE(("20"&MID(AR18,7,2))*1,MID(AR18,4,2)*1,MID(AR18,1,2)*1),"") -> 44564 | AU18: x
B19: =IF(AH19="","tbc",AH19) -> STE | C19: =IF(AI19="","VNT",AI19) -> VNT | D19: =MAX(X19,IF(AT19="none",X19,AT19)) -> 44564 | E19: =IFERROR(DAYS360(X19,D19),0) -> 0 | F19: =((LEN($AN19)-LEN(SUBSTITUTE($AN19,CHAR(10)&". ","")))/3)+IF(LEFT(TRIM($AN19),2)=". ",1,0) -> 1 | G19: =((LEN($AN19)-LEN(SUBSTITUTE($AN19,CHAR(10)&"/ ","")))/3)+IF(LEFT(TRIM($AN19),2)="/ ",1,0) -> 1 | H19: =((LEN($AN19)-LEN(SUBSTITUTE($AN19,CHAR(10)&"~ ","")))/3)+IF(LEFT(TRIM($AN19),2)="~ ",1,0) -> 1 | I19: =((LEN($AN19)-LEN(SUBSTITUTE($AN19,CHAR(10)&"! ","")))/3)+IF(LEFT(TRIM($AN19),2)="! ",1,0) -> 1 | J19: =((LEN($AN19)-LEN(SUBSTITUTE($AN19,CHAR(10)&"x ","")))/3)+IF(LEFT(TRIM($AN19),2)="x ",1,0) -> 1 | K19: =SUM(F19:J19) -> 5 | L19: =YEAR(D19) -> 2022 | M19: =VLOOKUP(MONTH(D19),Static!$AJ$3:$AK$16,2,0) -> Jan | N19: =WEEKNUM(D19,1) -> 2 | O19: =IFERROR(INDEX(Static!$I$5:$L$15,MATCH(AA19,Static!$I$5:$I$15,0),3),"Z") -> B | P19: =IFERROR(INDEX(Static!$I$5:$L$15,MATCH(AA19,Static!$I$5:$I$15,0),4),"Y") -> Y | Q19: =IF(D19>(($A$14-WEEKDAY($A$14,2))-7*$D$15),"Y","N") -> N | R19: =IF(AB19<>"","Y","N") -> Y | S19: =IF(AND(Q19="Y",R19="N"),"Y","N") -> N | T19: =IF(OR(Y19="Y",Y19="N"),Y19,IF(AND(P19="Y", OR(Q19="Y",S19="Y")),"Y","N")) -> N | U19: ="Y" -> Y | V19: =" - "&O19&AJ19&AK19&AB19 -> - BmgtleadingAttend meetings | W19: =IFERROR(VLOOKUP(WEEKDAY(X19),Static!$AL$3:$AM$11,2,0),"") -> Mon | X19: =IF(AD19<>"",AS19,0) -> 44564 | AA19: Routine | AB19: Attend meetings | AC19: There are various meetings that need to be attended not related to the other entries. | AD19: Weekly | AE19: 52 | AF19: 2 | AG19: =IF(AB19="","",AE19*AF19/8) -> 13 | AH19: STE | AI19: VNT | AJ19: mgt | AK19: leading | AL19: Details: # GENERAL ## Effort ## Assets ## Context | AM19: 03-01-22: init | AN19: . Open task / Started task x Closed task ~ Pending Task ! Urgent task | AO19: =SUM(F19:I19) -> 4 | AP19: =IF(AB19="",1,IF(K19<>0,(G19*0.5+J19)/K19,1)) -> 0.3 | AQ19: =IF(AM19="","",IF(ISERROR(FIND(CHAR(10),AM19,1)),AM19,LEFT(AM19,FIND(CHAR(10),AM19,1)))) -> 03-01-22: init | AR19: =IF(AM19="","",IFERROR(RIGHT(AM19,LEN(AM19)-FIND("@@@",SUBSTITUTE(AM19,CHAR(10),"@@@",LEN(AM19)-LEN(SUBSTITUTE(AM19,CHAR(10),""))),1)),AM19)) -> 03-01-22: init | AS19: =IFERROR(DATE(("20"&MID(AQ19,7,2))*1,MID(AQ19,4,2)*1,MID(AQ19,1,2)*1),"") -> 44564 | AT19: =IFERROR(DATE(("20"&MID(AR19,7,2))*1,MID(AR19,4,2)*1,MID(AR19,1,2)*1),"") -> 44564 | AU19: x
B20: =IF(AH20="","tbc",AH20) -> STE | C20: =IF(AI20="","VNT",AI20) -> VNT | D20: =MAX(X20,IF(AT20="none",X20,AT20)) -> 44564 | E20: =IFERROR(DAYS360(X20,D20),0) -> 0 | F20: =((LEN($AN20)-LEN(SUBSTITUTE($AN20,CHAR(10)&". ","")))/3)+IF(LEFT(TRIM($AN20),2)=". ",1,0) -> 0 | G20: =((LEN($AN20)-LEN(SUBSTITUTE($AN20,CHAR(10)&"/ ","")))/3)+IF(LEFT(TRIM($AN20),2)="/ ",1,0) -> 0 | H20: =((LEN($AN20)-LEN(SUBSTITUTE($AN20,CHAR(10)&"~ ","")))/3)+IF(LEFT(TRIM($AN20),2)="~ ",1,0) -> 0 | I20: =((LEN($AN20)-LEN(SUBSTITUTE($AN20,CHAR(10)&"! ","")))/3)+IF(LEFT(TRIM($AN20),2)="! ",1,0) -> 0 | J20: =((LEN($AN20)-LEN(SUBSTITUTE($AN20,CHAR(10)&"x ","")))/3)+IF(LEFT(TRIM($AN20),2)="x ",1,0) -> 0 | K20: =SUM(F20:J20) -> 0 | L20: =YEAR(D20) -> 2022 | M20: =VLOOKUP(MONTH(D20),Static!$AJ$3:$AK$16,2,0) -> Jan | N20: =WEEKNUM(D20,1) -> 2 | O20: =IFERROR(INDEX(Static!$I$5:$L$15,MATCH(AA20,Static!$I$5:$I$15,0),3),"Z") -> B | P20: =IFERROR(INDEX(Static!$I$5:$L$15,MATCH(AA20,Static!$I$5:$I$15,0),4),"Y") -> Y | Q20: =IF(D20>(($A$14-WEEKDAY($A$14,2))-7*$D$15),"Y","N") -> N | R20: =IF(AB20<>"","Y","N") -> Y | S20: =IF(AND(Q20="Y",R20="N"),"Y","N") -> N | T20: =IF(OR(Y20="Y",Y20="N"),Y20,IF(AND(P20="Y", OR(Q20="Y",S20="Y")),"Y","N")) -> N | U20: ="Y" -> Y | V20: =" - "&O20&AJ20&AK20&AB20 -> - BmgtleadingRead emails | W20: =IFERROR(VLOOKUP(WEEKDAY(X20),Static!$AL$3:$AM$11,2,0),"") -> Mon | X20: =IF(AD20<>"",AS20,0) -> 44564 | AA20: Routine | AB20: Read emails | AC20: This concerns emails not related to any of the other routines | AD20: Daily | AE20: 220 | AF20: 0.5 | AG20: =IF(AB20="","",AE20*AF20/8) -> 13.75 | AH20: STE | AI20: VNT | AJ20: mgt | AK20: leading | AL20: Details: # GENERAL ## Effort ## Assets ## Context | AM20: 03-01-22: init | AO20: =SUM(F20:I20) -> 0 | AP20: =IF(AB20="",1,IF(K20<>0,(G20*0.5+J20)/K20,1)) -> 1 | AQ20: =IF(AM20="","",IF(ISERROR(FIND(CHAR(10),AM20,1)),AM20,LEFT(AM20,FIND(CHAR(10),AM20,1)))) -> 03-01-22: init | AR20: =IF(AM20="","",IFERROR(RIGHT(AM20,LEN(AM20)-FIND("@@@",SUBSTITUTE(AM20,CHAR(10),"@@@",LEN(AM20)-LEN(SUBSTITUTE(AM20,CHAR(10),""))),1)),AM20)) -> 03-01-22: init | AS20: =IFERROR(DATE(("20"&MID(AQ20,7,2))*1,MID(AQ20,4,2)*1,MID(AQ20,1,2)*1),"") -> 44564 | AT20: =IFERROR(DATE(("20"&MID(AR20,7,2))*1,MID(AR20,4,2)*1,MID(AR20,1,2)*1),"") -> 44564 | AU20: x
B21: =IF(AH21="","tbc",AH21) -> STE | C21: =IF(AI21="","VNT",AI21) -> VNT | D21: =MAX(X21,IF(AT21="none",X21,AT21)) -> 44564 | E21: =IFERROR(DAYS360(X21,D21),0) -> 0 | F21: =((LEN($AN21)-LEN(SUBSTITUTE($AN21,CHAR(10)&". ","")))/3)+IF(LEFT(TRIM($AN21),2)=". ",1,0) -> 0 | G21: =((LEN($AN21)-LEN(SUBSTITUTE($AN21,CHAR(10)&"/ ","")))/3)+IF(LEFT(TRIM($AN21),2)="/ ",1,0) -> 0 | H21: =((LEN($AN21)-LEN(SUBSTITUTE($AN21,CHAR(10)&"~ ","")))/3)+IF(LEFT(TRIM($AN21),2)="~ ",1,0) -> 0 | I21: =((LEN($AN21)-LEN(SUBSTITUTE($AN21,CHAR(10)&"! ","")))/3)+IF(LEFT(TRIM($AN21),2)="! ",1,0) -> 0 | J21: =((LEN($AN21)-LEN(SUBSTITUTE($AN21,CHAR(10)&"x ","")))/3)+IF(LEFT(TRIM($AN21),2)="x ",1,0) -> 0 | K21: =SUM(F21:J21) -> 0 | L21: =YEAR(D21) -> 2022 | M21: =VLOOKUP(MONTH(D21),Static!$AJ$3:$AK$16,2,0) -> Jan | N21: =WEEKNUM(D21,1) -> 2 | O21: =IFERROR(INDEX(Static!$I$5:$L$15,MATCH(AA21,Static!$I$5:$I$15,0),3),"Z") -> B | P21: =IFERROR(INDEX(Static!$I$5:$L$15,MATCH(AA21,Static!$I$5:$I$15,0),4),"Y") -> Y | Q21: =IF(D21>(($A$14-WEEKDAY($A$14,2))-7*$D$15),"Y","N") -> N | R21: =IF(AB21<>"","Y","N") -> Y | S21: =IF(AND(Q21="Y",R21="N"),"Y","N") -> N | T21: =IF(OR(Y21="Y",Y21="N"),Y21,IF(AND(P21="Y", OR(Q21="Y",S21="Y")),"Y","N")) -> N | U21: ="Y" -> Y | V21: =" - "&O21&AJ21&AK21&AB21 -> - BmgtleadingSort emails | W21: =IFERROR(VLOOKUP(WEEKDAY(X21),Static!$AL$3:$AM$11,2,0),"") -> Mon | X21: =IF(AD21<>"",AS21,0) -> 44564 | AA21: Routine | AB21: Sort emails | AC21: This concerns days when utterly bored | AD21: Daily | AE21: 220 | AF21: 0.25 | AG21: =IF(AB21="","",AE21*AF21/8) -> 6.875 | AH21: STE | AI21: VNT | AJ21: mgt | AK21: leading | AL21: Details: # GENERAL ## Effort ## | AM21: 03-01-22: init | AO21: =SUM(F21:I21) -> 0 | AP21: =IF(AB21="",1,IF(K21<>0,(G21*0.5+J21)/K21,1)) -> 1 | AQ21: =IF(AM21="","",IF(ISERROR(FIND(CHAR(10),AM21,1)),AM21,LEFT(AM21,FIND(CHAR(10),AM21,1)))) -> 03-01-22: init | AR21: =IF(AM21="","",IFERROR(RIGHT(AM21,LEN(AM21)-FIND("@@@",SUBSTITUTE(AM21,CHAR(10),"@@@",LEN(AM21)-LEN(SUBSTITUTE(AM21,CHAR(10),""))),1)),AM21)) -> 03-01-22: init | AS21: =IFERROR(DATE(("20"&MID(AQ21,7,2))*1,MID(AQ21,4,2)*1,MID(AQ21,1,2)*1),"") -> 44564 | AT21: =IFERROR(DATE(("20"&MID(AR21,7,2))*1,MID(AR21,4,2)*1,MID(AR21,1,2)*1),"") -> 44564 | AU21: x
B22: =IF(AH22="","tbc",AH22) -> tbc | C22: =IF(AI22="","VNT",AI22) -> VNT | D22: =MAX(X22,IF(AT22="none",X22,AT22)) -> 0 | E22: =IFERROR(DAYS360(X22,D22),0) -> 0 | F22: =((LEN($AN22)-LEN(SUBSTITUTE($AN22,CHAR(10)&". ","")))/3)+IF(LEFT(TRIM($AN22),2)=". ",1,0) -> 0 | G22: =((LEN($AN22)-LEN(SUBSTITUTE($AN22,CHAR(10)&"/ ","")))/3)+IF(LEFT(TRIM($AN22),2)="/ ",1,0) -> 0 | H22: =((LEN($AN22)-LEN(SUBSTITUTE($AN22,CHAR(10)&"~ ","")))/3)+IF(LEFT(TRIM($AN22),2)="~ ",1,0) -> 0 | I22: =((LEN($AN22)-LEN(SUBSTITUTE($AN22,CHAR(10)&"! ","")))/3)+IF(LEFT(TRIM($AN22),2)="! ",1,0) -> 0 | J22: =((LEN($AN22)-LEN(SUBSTITUTE($AN22,CHAR(10)&"x ","")))/3)+IF(LEFT(TRIM($AN22),2)="x ",1,0) -> 0 | K22: =SUM(F22:J22) -> 0 | L22: =YEAR(D22) -> 1899 | M22: =VLOOKUP(MONTH(D22),Static!$AJ$3:$AK$16,2,0) -> Dec | N22: =WEEKNUM(D22,1) -> 52 | O22: =IFERROR(INDEX(Static!$I$5:$L$15,MATCH(AA22,Static!$I$5:$I$15,0),3),"Z") -> Z | P22: =IFERROR(INDEX(Static!$I$5:$L$15,MATCH(AA22,Static!$I$5:$I$15,0),4),"Y") -> Y | Q22: =IF(D22>(($A$14-WEEKDAY($A$14,2))-7*$D$15),"Y","N") -> N | R22: =IF(AB22<>"","Y","N") -> N | S22: =IF(AND(Q22="Y",R22="N"),"Y","N") -> N | T22: =IF(OR(Y22="Y",Y22="N"),Y22,IF(AND(P22="Y", OR(Q22="Y",S22="Y")),"Y","N")) -> N | U22: ="Y" -> Y | V22: =" - "&O22&AJ22&AK22&AB22 -> - Zprdresearch & development | W22: =IFERROR(VLOOKUP(WEEKDAY(X22),Static!$AL$3:$AM$11,2,0),"") -> Sat | X22: =IF(AD22<>"",AS22,0) -> 0 | AG22: =IF(AB22="","",AE22*AF22/8) | AJ22: prd | AK22: research & development | AO22: =SUM(F22:I22) -> 0 | AP22: =IF(AB22="",1,IF(K22<>0,(G22*0.5+J22)/K22,1)) -> 1 | AQ22: =IF(AM22="","",IF(ISERROR(FIND(CHAR(10),AM22,1)),AM22,LEFT(AM22,FIND(CHAR(10),AM22,1)))) | AR22: =IF(AM22="","",IFERROR(RIGHT(AM22,LEN(AM22)-FIND("@@@",SUBSTITUTE(AM22,CHAR(10),"@@@",LEN(AM22)-LEN(SUBSTITUTE(AM22,CHAR(10),""))),1)),AM22)) | AS22: =IFERROR(DATE(("20"&MID(AQ22,7,2))*1,MID(AQ22,4,2)*1,MID(AQ22,1,2)*1),"") | AT22: =IFERROR(DATE(("20"&MID(AR22,7,2))*1,MID(AR22,4,2)*1,MID(AR22,1,2)*1),"") | AU22: x
B23: =IF(AH23="","tbc",AH23) -> tbc | C23: =IF(AI23="","VNT",AI23) -> VNT | D23: =MAX(X23,IF(AT23="none",X23,AT23)) -> 0 | E23: =IFERROR(DAYS360(X23,D23),0) -> 0 | F23: =((LEN($AN23)-LEN(SUBSTITUTE($AN23,CHAR(10)&". ","")))/3)+IF(LEFT(TRIM($AN23),2)=". ",1,0) -> 0 | G23: =((LEN($AN23)-LEN(SUBSTITUTE($AN23,CHAR(10)&"/ ","")))/3)+IF(LEFT(TRIM($AN23),2)="/ ",1,0) -> 0 | H23: =((LEN($AN23)-LEN(SUBSTITUTE($AN23,CHAR(10)&"~ ","")))/3)+IF(LEFT(TRIM($AN23),2)="~ ",1,0) -> 0 | I23: =((LEN($AN23)-LEN(SUBSTITUTE($AN23,CHAR(10)&"! ","")))/3)+IF(LEFT(TRIM($AN23),2)="! ",1,0) -> 0 | J23: =((LEN($AN23)-LEN(SUBSTITUTE($AN23,CHAR(10)&"x ","")))/3)+IF(LEFT(TRIM($AN23),2)="x ",1,0) -> 0 | K23: =SUM(F23:J23) -> 0 | L23: =YEAR(D23) -> 1899 | M23: =VLOOKUP(MONTH(D23),Static!$AJ$3:$AK$16,2,0) -> Dec | N23: =WEEKNUM(D23,1) -> 52 | O23: =IFERROR(INDEX(Static!$I$5:$L$15,MATCH(AA23,Static!$I$5:$I$15,0),3),"Z") -> Z | P23: =IFERROR(INDEX(Static!$I$5:$L$15,MATCH(AA23,Static!$I$5:$I$15,0),4),"Y") -> Y | Q23: =IF(D23>(($A$14-WEEKDAY($A$14,2))-7*$D$15),"Y","N") -> N | R23: =IF(AB23<>"","Y","N") -> N | S23: =IF(AND(Q23="Y",R23="N"),"Y","N") -> N | T23: =IF(OR(Y23="Y",Y23="N"),Y23,IF(AND(P23="Y", OR(Q23="Y",S23="Y")),"Y","N")) -> N | U23: ="Y" -> Y | V23: =" - "&O23&AJ23&AK23&AB23 -> - Z | W23: =IFERROR(VLOOKUP(WEEKDAY(X23),Static!$AL$3:$AM$11,2,0),"") -> Sat | X23: =IF(AD23<>"",AS23,0) -> 0 | AG23: =IF(AB23="","",AE23*AF23/8) | AO23: =SUM(F23:I23) -> 0 | AP23: =IF(AB23="",1,IF(K23<>0,(G23*0.5+J23)/K23,1)) -> 1 | AQ23: =IF(AM23="","",IF(ISERROR(FIND(CHAR(10),AM23,1)),AM23,LEFT(AM23,FIND(CHAR(10),AM23,1)))) | AR23: =IF(AM23="","",IFERROR(RIGHT(AM23,LEN(AM23)-FIND("@@@",SUBSTITUTE(AM23,CHAR(10),"@@@",LEN(AM23)-LEN(SUBSTITUTE(AM23,CHAR(10),""))),1)),AM23)) | AS23: =IFERROR(DATE(("20"&MID(AQ23,7,2))*1,MID(AQ23,4,2)*1,MID(AQ23,1,2)*1),"") | AT23: =IFERROR(DATE(("20"&MID(AR23,7,2))*1,MID(AR23,4,2)*1,MID(AR23,1,2)*1),"") | AU23: x
B24: =IF(AH24="","tbc",AH24) -> tbc | C24: =IF(AI24="","VNT",AI24) -> VNT | D24: =MAX(X24,IF(AT24="none",X24,AT24)) -> 0 | E24: =IFERROR(DAYS360(X24,D24),0) -> 0 | F24: =((LEN($AN24)-LEN(SUBSTITUTE($AN24,CHAR(10)&". ","")))/3)+IF(LEFT(TRIM($AN24),2)=". ",1,0) -> 0 | G24: =((LEN($AN24)-LEN(SUBSTITUTE($AN24,CHAR(10)&"/ ","")))/3)+IF(LEFT(TRIM($AN24),2)="/ ",1,0) -> 0 | H24: =((LEN($AN24)-LEN(SUBSTITUTE($AN24,CHAR(10)&"~ ","")))/3)+IF(LEFT(TRIM($AN24),2)="~ ",1,0) -> 0 | I24: =((LEN($AN24)-LEN(SUBSTITUTE($AN24,CHAR(10)&"! ","")))/3)+IF(LEFT(TRIM($AN24),2)="! ",1,0) -> 0 | J24: =((LEN($AN24)-LEN(SUBSTITUTE($AN24,CHAR(10)&"x ","")))/3)+IF(LEFT(TRIM($AN24),2)="x ",1,0) -> 0 | K24: =SUM(F24:J24) -> 0 | L24: =YEAR(D24) -> 1899 | M24: =VLOOKUP(MONTH(D24),Static!$AJ$3:$AK$16,2,0) -> Dec | N24: =WEEKNUM(D24,1) -> 52 | O24: =IFERROR(INDEX(Static!$I$5:$L$15,MATCH(AA24,Static!$I$5:$I$15,0),3),"Z") -> Z | P24: =IFERROR(INDEX(Static!$I$5:$L$15,MATCH(AA24,Static!$I$5:$I$15,0),4),"Y") -> Y | Q24: =IF(D24>(($A$14-WEEKDAY($A$14,2))-7*$D$15),"Y","N") -> N | R24: =IF(AB24<>"","Y","N") -> N | S24: =IF(AND(Q24="Y",R24="N"),"Y","N") -> N | T24: =IF(OR(Y24="Y",Y24="N"),Y24,IF(AND(P24="Y", OR(Q24="Y",S24="Y")),"Y","N")) -> N | U24: ="Y" -> Y | V24: =" - "&O24&AJ24&AK24&AB24 -> - Z | W24: =IFERROR(VLOOKUP(WEEKDAY(X24),Static!$AL$3:$AM$11,2,0),"") -> Sat | X24: =IF(AD24<>"",AS24,0) -> 0 | AG24: =IF(AB24="","",AE24*AF24/8) | AO24: =SUM(F24:I24) -> 0 | AP24: =IF(AB24="",1,IF(K24<>0,(G24*0.5+J24)/K24,1)) -> 1 | AQ24: =IF(AM24="","",IF(ISERROR(FIND(CHAR(10),AM24,1)),AM24,LEFT(AM24,FIND(CHAR(10),AM24,1)))) | AR24: =IF(AM24="","",IFERROR(RIGHT(AM24,LEN(AM24)-FIND("@@@",SUBSTITUTE(AM24,CHAR(10),"@@@",LEN(AM24)-LEN(SUBSTITUTE(AM24,CHAR(10),""))),1)),AM24)) | AS24: =IFERROR(DATE(("20"&MID(AQ24,7,2))*1,MID(AQ24,4,2)*1,MID(AQ24,1,2)*1),"") | AT24: =IFERROR(DATE(("20"&MID(AR24,7,2))*1,MID(AR24,4,2)*1,MID(AR24,1,2)*1),"") | AU24: x
B25: =IF(AH25="","tbc",AH25) -> tbc | C25: =IF(AI25="","VNT",AI25) -> VNT | D25: =MAX(X25,IF(AT25="none",X25,AT25)) -> 0 | E25: =IFERROR(DAYS360(X25,D25),0) -> 0 | F25: =((LEN($AN25)-LEN(SUBSTITUTE($AN25,CHAR(10)&". ","")))/3)+IF(LEFT(TRIM($AN25),2)=". ",1,0) -> 0 | G25: =((LEN($AN25)-LEN(SUBSTITUTE($AN25,CHAR(10)&"/ ","")))/3)+IF(LEFT(TRIM($AN25),2)="/ ",1,0) -> 0 | H25: =((LEN($AN25)-LEN(SUBSTITUTE($AN25,CHAR(10)&"~ ","")))/3)+IF(LEFT(TRIM($AN25),2)="~ ",1,0) -> 0 | I25: =((LEN($AN25)-LEN(SUBSTITUTE($AN25,CHAR(10)&"! ","")))/3)+IF(LEFT(TRIM($AN25),2)="! ",1,0) -> 0 | J25: =((LEN($AN25)-LEN(SUBSTITUTE($AN25,CHAR(10)&"x ","")))/3)+IF(LEFT(TRIM($AN25),2)="x ",1,0) -> 0 | K25: =SUM(F25:J25) -> 0 | L25: =YEAR(D25) -> 1899 | M25: =VLOOKUP(MONTH(D25),Static!$AJ$3:$AK$16,2,0) -> Dec | N25: =WEEKNUM(D25,1) -> 52 | O25: =IFERROR(INDEX(Static!$I$5:$L$15,MATCH(AA25,Static!$I$5:$I$15,0),3),"Z") -> Z | P25: =IFERROR(INDEX(Static!$I$5:$L$15,MATCH(AA25,Static!$I$5:$I$15,0),4),"Y") -> Y | Q25: =IF(D25>(($A$14-WEEKDAY($A$14,2))-7*$D$15),"Y","N") -> N | R25: =IF(AB25<>"","Y","N") -> N | S25: =IF(AND(Q25="Y",R25="N"),"Y","N") -> N | T25: =IF(OR(Y25="Y",Y25="N"),Y25,IF(AND(P25="Y", OR(Q25="Y",S25="Y")),"Y","N")) -> N | U25: ="Y" -> Y | V25: =" - "&O25&AJ25&AK25&AB25 -> - Z | W25: =IFERROR(VLOOKUP(WEEKDAY(X25),Static!$AL$3:$AM$11,2,0),"") -> Sat | X25: =IF(AD25<>"",AS25,0) -> 0 | AG25: =IF(AB25="","",AE25*AF25/8) | AO25: =SUM(F25:I25) -> 0 | AP25: =IF(AB25="",1,IF(K25<>0,(G25*0.5+J25)/K25,1)) -> 1 | AQ25: =IF(AM25="","",IF(ISERROR(FIND(CHAR(10),AM25,1)),AM25,LEFT(AM25,FIND(CHAR(10),AM25,1)))) | AR25: =IF(AM25="","",IFERROR(RIGHT(AM25,LEN(AM25)-FIND("@@@",SUBSTITUTE(AM25,CHAR(10),"@@@",LEN(AM25)-LEN(SUBSTITUTE(AM25,CHAR(10),""))),1)),AM25)) | AS25: =IFERROR(DATE(("20"&MID(AQ25,7,2))*1,MID(AQ25,4,2)*1,MID(AQ25,1,2)*1),"") | AT25: =IFERROR(DATE(("20"&MID(AR25,7,2))*1,MID(AR25,4,2)*1,MID(AR25,1,2)*1),"") | AU25: x
B26: =IF(AH26="","tbc",AH26) -> tbc | C26: =IF(AI26="","VNT",AI26) -> VNT | D26: =MAX(X26,IF(AT26="none",X26,AT26)) -> 0 | E26: =IFERROR(DAYS360(X26,D26),0) -> 0 | F26: =((LEN($AN26)-LEN(SUBSTITUTE($AN26,CHAR(10)&". ","")))/3)+IF(LEFT(TRIM($AN26),2)=". ",1,0) -> 0 | G26: =((LEN($AN26)-LEN(SUBSTITUTE($AN26,CHAR(10)&"/ ","")))/3)+IF(LEFT(TRIM($AN26),2)="/ ",1,0) -> 0 | H26: =((LEN($AN26)-LEN(SUBSTITUTE($AN26,CHAR(10)&"~ ","")))/3)+IF(LEFT(TRIM($AN26),2)="~ ",1,0) -> 0 | I26: =((LEN($AN26)-LEN(SUBSTITUTE($AN26,CHAR(10)&"! ","")))/3)+IF(LEFT(TRIM($AN26),2)="! ",1,0) -> 0 | J26: =((LEN($AN26)-LEN(SUBSTITUTE($AN26,CHAR(10)&"x ","")))/3)+IF(LEFT(TRIM($AN26),2)="x ",1,0) -> 0 | K26: =SUM(F26:J26) -> 0 | L26: =YEAR(D26) -> 1899 | M26: =VLOOKUP(MONTH(D26),Static!$AJ$3:$AK$16,2,0) -> Dec | N26: =WEEKNUM(D26,1) -> 52 | O26: =IFERROR(INDEX(Static!$I$5:$L$15,MATCH(AA26,Static!$I$5:$I$15,0),3),"Z") -> Z | P26: =IFERROR(INDEX(Static!$I$5:$L$15,MATCH(AA26,Static!$I$5:$I$15,0),4),"Y") -> Y | Q26: =IF(D26>(($A$14-WEEKDAY($A$14,2))-7*$D$15),"Y","N") -> N | R26: =IF(AB26<>"","Y","N") -> N | S26: =IF(AND(Q26="Y",R26="N"),"Y","N") -> N | T26: =IF(OR(Y26="Y",Y26="N"),Y26,IF(AND(P26="Y", OR(Q26="Y",S26="Y")),"Y","N")) -> N | U26: ="Y" -> Y | V26: =" - "&O26&AJ26&AK26&AB26 -> - Z | W26: =IFERROR(VLOOKUP(WEEKDAY(X26),Static!$AL$3:$AM$11,2,0),"") -> Sat | X26: =IF(AD26<>"",AS26,0) -> 0 | AG26: =IF(AB26="","",AE26*AF26/8) | AO26: =SUM(F26:I26) -> 0 | AP26: =IF(AB26="",1,IF(K26<>0,(G26*0.5+J26)/K26,1)) -> 1 | AQ26: =IF(AM26="","",IF(ISERROR(FIND(CHAR(10),AM26,1)),AM26,LEFT(AM26,FIND(CHAR(10),AM26,1)))) | AR26: =IF(AM26="","",IFERROR(RIGHT(AM26,LEN(AM26)-FIND("@@@",SUBSTITUTE(AM26,CHAR(10),"@@@",LEN(AM26)-LEN(SUBSTITUTE(AM26,CHAR(10),""))),1)),AM26)) | AS26: =IFERROR(DATE(("20"&MID(AQ26,7,2))*1,MID(AQ26,4,2)*1,MID(AQ26,1,2)*1),"") | AT26: =IFERROR(DATE(("20"&MID(AR26,7,2))*1,MID(AR26,4,2)*1,MID(AR26,1,2)*1),"") | AU26: x
B27: =IF(AH27="","tbc",AH27) -> tbc | C27: =IF(AI27="","VNT",AI27) -> VNT | D27: =MAX(X27,IF(AT27="none",X27,AT27)) -> 0 | E27: =IFERROR(DAYS360(X27,D27),0) -> 0 | F27: =((LEN($AN27)-LEN(SUBSTITUTE($AN27,CHAR(10)&". ","")))/3)+IF(LEFT(TRIM($AN27),2)=". ",1,0) -> 0 | G27: =((LEN($AN27)-LEN(SUBSTITUTE($AN27,CHAR(10)&"/ ","")))/3)+IF(LEFT(TRIM($AN27),2)="/ ",1,0) -> 0 | H27: =((LEN($AN27)-LEN(SUBSTITUTE($AN27,CHAR(10)&"~ ","")))/3)+IF(LEFT(TRIM($AN27),2)="~ ",1,0) -> 0 | I27: =((LEN($AN27)-LEN(SUBSTITUTE($AN27,CHAR(10)&"! ","")))/3)+IF(LEFT(TRIM($AN27),2)="! ",1,0) -> 0 | J27: =((LEN($AN27)-LEN(SUBSTITUTE($AN27,CHAR(10)&"x ","")))/3)+IF(LEFT(TRIM($AN27),2)="x ",1,0) -> 0 | K27: =SUM(F27:J27) -> 0 | L27: =YEAR(D27) -> 1899 | M27: =VLOOKUP(MONTH(D27),Static!$AJ$3:$AK$16,2,0) -> Dec | N27: =WEEKNUM(D27,1) -> 52 | O27: =IFERROR(INDEX(Static!$I$5:$L$15,MATCH(AA27,Static!$I$5:$I$15,0),3),"Z") -> Z | P27: =IFERROR(INDEX(Static!$I$5:$L$15,MATCH(AA27,Static!$I$5:$I$15,0),4),"Y") -> Y | Q27: =IF(D27>(($A$14-WEEKDAY($A$14,2))-7*$D$15),"Y","N") -> N | R27: =IF(AB27<>"","Y","N") -> N | S27: =IF(AND(Q27="Y",R27="N"),"Y","N") -> N | T27: =IF(OR(Y27="Y",Y27="N"),Y27,IF(AND(P27="Y", OR(Q27="Y",S27="Y")),"Y","N")) -> N | U27: ="Y" -> Y | V27: =" - "&O27&AJ27&AK27&AB27 -> - Z | W27: =IFERROR(VLOOKUP(WEEKDAY(X27),Static!$AL$3:$AM$11,2,0),"") -> Sat | X27: =IF(AD27<>"",AS27,0) -> 0 | AG27: =IF(AB27="","",AE27*AF27/8) | AO27: =SUM(F27:I27) -> 0 | AP27: =IF(AB27="",1,IF(K27<>0,(G27*0.5+J27)/K27,1)) -> 1 | AQ27: =IF(AM27="","",IF(ISERROR(FIND(CHAR(10),AM27,1)),AM27,LEFT(AM27,FIND(CHAR(10),AM27,1)))) | AR27: =IF(AM27="","",IFERROR(RIGHT(AM27,LEN(AM27)-FIND("@@@",SUBSTITUTE(AM27,CHAR(10),"@@@",LEN(AM27)-LEN(SUBSTITUTE(AM27,CHAR(10),""))),1)),AM27)) | AS27: =IFERROR(DATE(("20"&MID(AQ27,7,2))*1,MID(AQ27,4,2)*1,MID(AQ27,1,2)*1),"") | AT27: =IFERROR(DATE(("20"&MID(AR27,7,2))*1,MID(AR27,4,2)*1,MID(AR27,1,2)*1),"") | AU27: x
B28: =IF(AH28="","tbc",AH28) -> tbc | C28: =IF(AI28="","VNT",AI28) -> VNT | D28: =MAX(X28,IF(AT28="none",X28,AT28)) -> 0 | E28: =IFERROR(DAYS360(X28,D28),0) -> 0 | F28: =((LEN($AN28)-LEN(SUBSTITUTE($AN28,CHAR(10)&". ","")))/3)+IF(LEFT(TRIM($AN28),2)=". ",1,0) -> 0 | G28: =((LEN($AN28)-LEN(SUBSTITUTE($AN28,CHAR(10)&"/ ","")))/3)+IF(LEFT(TRIM($AN28),2)="/ ",1,0) -> 0 | H28: =((LEN($AN28)-LEN(SUBSTITUTE($AN28,CHAR(10)&"~ ","")))/3)+IF(LEFT(TRIM($AN28),2)="~ ",1,0) -> 0 | I28: =((LEN($AN28)-LEN(SUBSTITUTE($AN28,CHAR(10)&"! ","")))/3)+IF(LEFT(TRIM($AN28),2)="! ",1,0) -> 0 | J28: =((LEN($AN28)-LEN(SUBSTITUTE($AN28,CHAR(10)&"x ","")))/3)+IF(LEFT(TRIM($AN28),2)="x ",1,0) -> 0 | K28: =SUM(F28:J28) -> 0 | L28: =YEAR(D28) -> 1899 | M28: =VLOOKUP(MONTH(D28),Static!$AJ$3:$AK$16,2,0) -> Dec | N28: =WEEKNUM(D28,1) -> 52 | O28: =IFERROR(INDEX(Static!$I$5:$L$15,MATCH(AA28,Static!$I$5:$I$15,0),3),"Z") -> Z | P28: =IFERROR(INDEX(Static!$I$5:$L$15,MATCH(AA28,Static!$I$5:$I$15,0),4),"Y") -> Y | Q28: =IF(D28>(($A$14-WEEKDAY($A$14,2))-7*$D$15),"Y","N") -> N | R28: =IF(AB28<>"","Y","N") -> N | S28: =IF(AND(Q28="Y",R28="N"),"Y","N") -> N | T28: =IF(OR(Y28="Y",Y28="N"),Y28,IF(AND(P28="Y", OR(Q28="Y",S28="Y")),"Y","N")) -> N | U28: ="Y" -> Y | V28: =" - "&O28&AJ28&AK28&AB28 -> - Z | W28: =IFERROR(VLOOKUP(WEEKDAY(X28),Static!$AL$3:$AM$11,2,0),"") -> Sat | X28: =IF(AD28<>"",AS28,0) -> 0 | AG28: =IF(AB28="","",AE28*AF28/8) | AO28: =SUM(F28:I28) -> 0 | AP28: =IF(AB28="",1,IF(K28<>0,(G28*0.5+J28)/K28,1)) -> 1 | AQ28: =IF(AM28="","",IF(ISERROR(FIND(CHAR(10),AM28,1)),AM28,LEFT(AM28,FIND(CHAR(10),AM28,1)))) | AR28: =IF(AM28="","",IFERROR(RIGHT(AM28,LEN(AM28)-FIND("@@@",SUBSTITUTE(AM28,CHAR(10),"@@@",LEN(AM28)-LEN(SUBSTITUTE(AM28,CHAR(10),""))),1)),AM28)) | AS28: =IFERROR(DATE(("20"&MID(AQ28,7,2))*1,MID(AQ28,4,2)*1,MID(AQ28,1,2)*1),"") | AT28: =IFERROR(DATE(("20"&MID(AR28,7,2))*1,MID(AR28,4,2)*1,MID(AR28,1,2)*1),"") | AU28: x
B29: =IF(AH29="","tbc",AH29) -> tbc | C29: =IF(AI29="","VNT",AI29) -> VNT | D29: =MAX(X29,IF(AT29="none",X29,AT29)) -> 0 | E29: =IFERROR(DAYS360(X29,D29),0) -> 0 | F29: =((LEN($AN29)-LEN(SUBSTITUTE($AN29,CHAR(10)&". ","")))/3)+IF(LEFT(TRIM($AN29),2)=". ",1,0) -> 0 | G29: =((LEN($AN29)-LEN(SUBSTITUTE($AN29,CHAR(10)&"/ ","")))/3)+IF(LEFT(TRIM($AN29),2)="/ ",1,0) -> 0 | H29: =((LEN($AN29)-LEN(SUBSTITUTE($AN29,CHAR(10)&"~ ","")))/3)+IF(LEFT(TRIM($AN29),2)="~ ",1,0) -> 0 | I29: =((LEN($AN29)-LEN(SUBSTITUTE($AN29,CHAR(10)&"! ","")))/3)+IF(LEFT(TRIM($AN29),2)="! ",1,0) -> 0 | J29: =((LEN($AN29)-LEN(SUBSTITUTE($AN29,CHAR(10)&"x ","")))/3)+IF(LEFT(TRIM($AN29),2)="x ",1,0) -> 0 | K29: =SUM(F29:J29) -> 0 | L29: =YEAR(D29) -> 1899 | M29: =VLOOKUP(MONTH(D29),Static!$AJ$3:$AK$16,2,0) -> Dec | N29: =WEEKNUM(D29,1) -> 52 | O29: =IFERROR(INDEX(Static!$I$5:$L$15,MATCH(AA29,Static!$I$5:$I$15,0),3),"Z") -> Z | P29: =IFERROR(INDEX(Static!$I$5:$L$15,MATCH(AA29,Static!$I$5:$I$15,0),4),"Y") -> Y | Q29: =IF(D29>(($A$14-WEEKDAY($A$14,2))-7*$D$15),"Y","N") -> N | R29: =IF(AB29<>"","Y","N") -> N | S29: =IF(AND(Q29="Y",R29="N"),"Y","N") -> N | T29: =IF(OR(Y29="Y",Y29="N"),Y29,IF(AND(P29="Y", OR(Q29="Y",S29="Y")),"Y","N")) -> N | U29: ="Y" -> Y | V29: =" - "&O29&AJ29&AK29&AB29 -> - Z | W29: =IFERROR(VLOOKUP(WEEKDAY(X29),Static!$AL$3:$AM$11,2,0),"") -> Sat | X29: =IF(AD29<>"",AS29,0) -> 0 | AG29: =IF(AB29="","",AE29*AF29/8) | AO29: =SUM(F29:I29) -> 0 | AP29: =IF(AB29="",1,IF(K29<>0,(G29*0.5+J29)/K29,1)) -> 1 | AQ29: =IF(AM29="","",IF(ISERROR(FIND(CHAR(10),AM29,1)),AM29,LEFT(AM29,FIND(CHAR(10),AM29,1)))) | AR29: =IF(AM29="","",IFERROR(RIGHT(AM29,LEN(AM29)-FIND("@@@",SUBSTITUTE(AM29,CHAR(10),"@@@",LEN(AM29)-LEN(SUBSTITUTE(AM29,CHAR(10),""))),1)),AM29)) | AS29: =IFERROR(DATE(("20"&MID(AQ29,7,2))*1,MID(AQ29,4,2)*1,MID(AQ29,1,2)*1),"") | AT29: =IFERROR(DATE(("20"&MID(AR29,7,2))*1,MID(AR29,4,2)*1,MID(AR29,1,2)*1),"") | AU29: x
B30: =IF(AH30="","tbc",AH30) -> tbc | C30: =IF(AI30="","VNT",AI30) -> VNT | D30: =MAX(X30,IF(AT30="none",X30,AT30)) -> 0 | E30: =IFERROR(DAYS360(X30,D30),0) -> 0 | F30: =((LEN($AN30)-LEN(SUBSTITUTE($AN30,CHAR(10)&". ","")))/3)+IF(LEFT(TRIM($AN30),2)=". ",1,0) -> 0 | G30: =((LEN($AN30)-LEN(SUBSTITUTE($AN30,CHAR(10)&"/ ","")))/3)+IF(LEFT(TRIM($AN30),2)="/ ",1,0) -> 0 | H30: =((LEN($AN30)-LEN(SUBSTITUTE($AN30,CHAR(10)&"~ ","")))/3)+IF(LEFT(TRIM($AN30),2)="~ ",1,0) -> 0 | I30: =((LEN($AN30)-LEN(SUBSTITUTE($AN30,CHAR(10)&"! ","")))/3)+IF(LEFT(TRIM($AN30),2)="! ",1,0) -> 0 | J30: =((LEN($AN30)-LEN(SUBSTITUTE($AN30,CHAR(10)&"x ","")))/3)+IF(LEFT(TRIM($AN30),2)="x ",1,0) -> 0 | K30: =SUM(F30:J30) -> 0 | L30: =YEAR(D30) -> 1899 | M30: =VLOOKUP(MONTH(D30),Static!$AJ$3:$AK$16,2,0) -> Dec | N30: =WEEKNUM(D30,1) -> 52 | O30: =IFERROR(INDEX(Static!$I$5:$L$15,MATCH(AA30,Static!$I$5:$I$15,0),3),"Z") -> Z | P30: =IFERROR(INDEX(Static!$I$5:$L$15,MATCH(AA30,Static!$I$5:$I$15,0),4),"Y") -> Y | Q30: =IF(D30>(($A$14-WEEKDAY($A$14,2))-7*$D$15),"Y","N") -> N | R30: =IF(AB30<>"","Y","N") -> N | S30: =IF(AND(Q30="Y",R30="N"),"Y","N") -> N | T30: =IF(OR(Y30="Y",Y30="N"),Y30,IF(AND(P30="Y", OR(Q30="Y",S30="Y")),"Y","N")) -> N | U30: ="Y" -> Y | V30: =" - "&O30&AJ30&AK30&AB30 -> - Z | W30: =IFERROR(VLOOKUP(WEEKDAY(X30),Static!$AL$3:$AM$11,2,0),"") -> Sat | X30: =IF(AD30<>"",AS30,0) -> 0 | AG30: =IF(AB30="","",AE30*AF30/8) | AO30: =SUM(F30:I30) -> 0 | AP30: =IF(AB30="",1,IF(K30<>0,(G30*0.5+J30)/K30,1)) -> 1 | AQ30: =IF(AM30="","",IF(ISERROR(FIND(CHAR(10),AM30,1)),AM30,LEFT(AM30,FIND(CHAR(10),AM30,1)))) | AR30: =IF(AM30="","",IFERROR(RIGHT(AM30,LEN(AM30)-FIND("@@@",SUBSTITUTE(AM30,CHAR(10),"@@@",LEN(AM30)-LEN(SUBSTITUTE(AM30,CHAR(10),""))),1)),AM30)) | AS30: =IFERROR(DATE(("20"&MID(AQ30,7,2))*1,MID(AQ30,4,2)*1,MID(AQ30,1,2)*1),"") | AT30: =IFERROR(DATE(("20"&MID(AR30,7,2))*1,MID(AR30,4,2)*1,MID(AR30,1,2)*1),"") | AU30: x
B31: =IF(AH31="","tbc",AH31) -> tbc | C31: =IF(AI31="","VNT",AI31) -> VNT | D31: =MAX(X31,IF(AT31="none",X31,AT31)) -> 0 | E31: =IFERROR(DAYS360(X31,D31),0) -> 0 | F31: =((LEN($AN31)-LEN(SUBSTITUTE($AN31,CHAR(10)&". ","")))/3)+IF(LEFT(TRIM($AN31),2)=". ",1,0) -> 0 | G31: =((LEN($AN31)-LEN(SUBSTITUTE($AN31,CHAR(10)&"/ ","")))/3)+IF(LEFT(TRIM($AN31),2)="/ ",1,0) -> 0 | H31: =((LEN($AN31)-LEN(SUBSTITUTE($AN31,CHAR(10)&"~ ","")))/3)+IF(LEFT(TRIM($AN31),2)="~ ",1,0) -> 0 | I31: =((LEN($AN31)-LEN(SUBSTITUTE($AN31,CHAR(10)&"! ","")))/3)+IF(LEFT(TRIM($AN31),2)="! ",1,0) -> 0 | J31: =((LEN($AN31)-LEN(SUBSTITUTE($AN31,CHAR(10)&"x ","")))/3)+IF(LEFT(TRIM($AN31),2)="x ",1,0) -> 0 | K31: =SUM(F31:J31) -> 0 | L31: =YEAR(D31) -> 1899 | M31: =VLOOKUP(MONTH(D31),Static!$AJ$3:$AK$16,2,0) -> Dec | N31: =WEEKNUM(D31,1) -> 52 | O31: =IFERROR(INDEX(Static!$I$5:$L$15,MATCH(AA31,Static!$I$5:$I$15,0),3),"Z") -> Z | P31: =IFERROR(INDEX(Static!$I$5:$L$15,MATCH(AA31,Static!$I$5:$I$15,0),4),"Y") -> Y | Q31: =IF(D31>(($A$14-WEEKDAY($A$14,2))-7*$D$15),"Y","N") -> N | R31: =IF(AB31<>"","Y","N") -> N | S31: =IF(AND(Q31="Y",R31="N"),"Y","N") -> N | T31: =IF(OR(Y31="Y",Y31="N"),Y31,IF(AND(P31="Y", OR(Q31="Y",S31="Y")),"Y","N")) -> N | U31: ="Y" -> Y | V31: =" - "&O31&AJ31&AK31&AB31 -> - Z | W31: =IFERROR(VLOOKUP(WEEKDAY(X31),Static!$AL$3:$AM$11,2,0),"") -> Sat | X31: =IF(AD31<>"",AS31,0) -> 0 | AG31: =IF(AB31="","",AE31*AF31/8) | AO31: =SUM(F31:I31) -> 0 | AP31: =IF(AB31="",1,IF(K31<>0,(G31*0.5+J31)/K31,1)) -> 1 | AQ31: =IF(AM31="","",IF(ISERROR(FIND(CHAR(10),AM31,1)),AM31,LEFT(AM31,FIND(CHAR(10),AM31,1)))) | AR31: =IF(AM31="","",IFERROR(RIGHT(AM31,LEN(AM31)-FIND("@@@",SUBSTITUTE(AM31,CHAR(10),"@@@",LEN(AM31)-LEN(SUBSTITUTE(AM31,CHAR(10),""))),1)),AM31)) | AS31: =IFERROR(DATE(("20"&MID(AQ31,7,2))*1,MID(AQ31,4,2)*1,MID(AQ31,1,2)*1),"") | AT31: =IFERROR(DATE(("20"&MID(AR31,7,2))*1,MID(AR31,4,2)*1,MID(AR31,1,2)*1),"") | AU31: x
B32: =IF(AH32="","tbc",AH32) -> tbc | C32: =IF(AI32="","VNT",AI32) -> VNT | D32: =MAX(X32,IF(AT32="none",X32,AT32)) -> 0 | E32: =IFERROR(DAYS360(X32,D32),0) -> 0 | F32: =((LEN($AN32)-LEN(SUBSTITUTE($AN32,CHAR(10)&". ","")))/3)+IF(LEFT(TRIM($AN32),2)=". ",1,0) -> 0 | G32: =((LEN($AN32)-LEN(SUBSTITUTE($AN32,CHAR(10)&"/ ","")))/3)+IF(LEFT(TRIM($AN32),2)="/ ",1,0) -> 0 | H32: =((LEN($AN32)-LEN(SUBSTITUTE($AN32,CHAR(10)&"~ ","")))/3)+IF(LEFT(TRIM($AN32),2)="~ ",1,0) -> 0 | I32: =((LEN($AN32)-LEN(SUBSTITUTE($AN32,CHAR(10)&"! ","")))/3)+IF(LEFT(TRIM($AN32),2)="! ",1,0) -> 0 | J32: =((LEN($AN32)-LEN(SUBSTITUTE($AN32,CHAR(10)&"x ","")))/3)+IF(LEFT(TRIM($AN32),2)="x ",1,0) -> 0 | K32: =SUM(F32:J32) -> 0 | L32: =YEAR(D32) -> 1899 | M32: =VLOOKUP(MONTH(D32),Static!$AJ$3:$AK$16,2,0) -> Dec | N32: =WEEKNUM(D32,1) -> 52 | O32: =IFERROR(INDEX(Static!$I$5:$L$15,MATCH(AA32,Static!$I$5:$I$15,0),3),"Z") -> Z | P32: =IFERROR(INDEX(Static!$I$5:$L$15,MATCH(AA32,Static!$I$5:$I$15,0),4),"Y") -> Y | Q32: =IF(D32>(($A$14-WEEKDAY($A$14,2))-7*$D$15),"Y","N") -> N | R32: =IF(AB32<>"","Y","N") -> N | S32: =IF(AND(Q32="Y",R32="N"),"Y","N") -> N | T32: =IF(OR(Y32="Y",Y32="N"),Y32,IF(AND(P32="Y", OR(Q32="Y",S32="Y")),"Y","N")) -> N | U32: ="Y" -> Y | V32: =" - "&O32&AJ32&AK32&AB32 -> - Z | W32: =IFERROR(VLOOKUP(WEEKDAY(X32),Static!$AL$3:$AM$11,2,0),"") -> Sat | X32: =IF(AD32<>"",AS32,0) -> 0 | AG32: =IF(AB32="","",AE32*AF32/8) | AO32: =SUM(F32:I32) -> 0 | AP32: =IF(AB32="",1,IF(K32<>0,(G32*0.5+J32)/K32,1)) -> 1 | AQ32: =IF(AM32="","",IF(ISERROR(FIND(CHAR(10),AM32,1)),AM32,LEFT(AM32,FIND(CHAR(10),AM32,1)))) | AR32: =IF(AM32="","",IFERROR(RIGHT(AM32,LEN(AM32)-FIND("@@@",SUBSTITUTE(AM32,CHAR(10),"@@@",LEN(AM32)-LEN(SUBSTITUTE(AM32,CHAR(10),""))),1)),AM32)) | AS32: =IFERROR(DATE(("20"&MID(AQ32,7,2))*1,MID(AQ32,4,2)*1,MID(AQ32,1,2)*1),"") | AT32: =IFERROR(DATE(("20"&MID(AR32,7,2))*1,MID(AR32,4,2)*1,MID(AR32,1,2)*1),"") | AU32: x
B33: =IF(AH33="","tbc",AH33) -> tbc | C33: =IF(AI33="","VNT",AI33) -> VNT | D33: =MAX(X33,IF(AT33="none",X33,AT33)) -> 0 | E33: =IFERROR(DAYS360(X33,D33),0) -> 0 | F33: =((LEN($AN33)-LEN(SUBSTITUTE($AN33,CHAR(10)&". ","")))/3)+IF(LEFT(TRIM($AN33),2)=". ",1,0) -> 0 | G33: =((LEN($AN33)-LEN(SUBSTITUTE($AN33,CHAR(10)&"/ ","")))/3)+IF(LEFT(TRIM($AN33),2)="/ ",1,0) -> 0 | H33: =((LEN($AN33)-LEN(SUBSTITUTE($AN33,CHAR(10)&"~ ","")))/3)+IF(LEFT(TRIM($AN33),2)="~ ",1,0) -> 0 | I33: =((LEN($AN33)-LEN(SUBSTITUTE($AN33,CHAR(10)&"! ","")))/3)+IF(LEFT(TRIM($AN33),2)="! ",1,0) -> 0 | J33: =((LEN($AN33)-LEN(SUBSTITUTE($AN33,CHAR(10)&"x ","")))/3)+IF(LEFT(TRIM($AN33),2)="x ",1,0) -> 0 | K33: =SUM(F33:J33) -> 0 | L33: =YEAR(D33) -> 1899 | M33: =VLOOKUP(MONTH(D33),Static!$AJ$3:$AK$16,2,0) -> Dec | N33: =WEEKNUM(D33,1) -> 52 | O33: =IFERROR(INDEX(Static!$I$5:$L$15,MATCH(AA33,Static!$I$5:$I$15,0),3),"Z") -> Z | P33: =IFERROR(INDEX(Static!$I$5:$L$15,MATCH(AA33,Static!$I$5:$I$15,0),4),"Y") -> Y | Q33: =IF(D33>(($A$14-WEEKDAY($A$14,2))-7*$D$15),"Y","N") -> N | R33: =IF(AB33<>"","Y","N") -> N | S33: =IF(AND(Q33="Y",R33="N"),"Y","N") -> N | T33: =IF(OR(Y33="Y",Y33="N"),Y33,IF(AND(P33="Y", OR(Q33="Y",S33="Y")),"Y","N")) -> N | U33: ="Y" -> Y | V33: =" - "&O33&AJ33&AK33&AB33 -> - Z | W33: =IFERROR(VLOOKUP(WEEKDAY(X33),Static!$AL$3:$AM$11,2,0),"") -> Sat | X33: =IF(AD33<>"",AS33,0) -> 0 | AG33: =IF(AB33="","",AE33*AF33/8) | AO33: =SUM(F33:I33) -> 0 | AP33: =IF(AB33="",1,IF(K33<>0,(G33*0.5+J33)/K33,1)) -> 1 | AQ33: =IF(AM33="","",IF(ISERROR(FIND(CHAR(10),AM33,1)),AM33,LEFT(AM33,FIND(CHAR(10),AM33,1)))) | AR33: =IF(AM33="","",IFERROR(RIGHT(AM33,LEN(AM33)-FIND("@@@",SUBSTITUTE(AM33,CHAR(10),"@@@",LEN(AM33)-LEN(SUBSTITUTE(AM33,CHAR(10),""))),1)),AM33)) | AS33: =IFERROR(DATE(("20"&MID(AQ33,7,2))*1,MID(AQ33,4,2)*1,MID(AQ33,1,2)*1),"") | AT33: =IFERROR(DATE(("20"&MID(AR33,7,2))*1,MID(AR33,4,2)*1,MID(AR33,1,2)*1),"") | AU33: x
B34: =IF(AH34="","tbc",AH34) -> tbc | C34: =IF(AI34="","VNT",AI34) -> VNT | D34: =MAX(X34,IF(AT34="none",X34,AT34)) -> 0 | E34: =IFERROR(DAYS360(X34,D34),0) -> 0 | F34: =((LEN($AN34)-LEN(SUBSTITUTE($AN34,CHAR(10)&". ","")))/3)+IF(LEFT(TRIM($AN34),2)=". ",1,0) -> 0 | G34: =((LEN($AN34)-LEN(SUBSTITUTE($AN34,CHAR(10)&"/ ","")))/3)+IF(LEFT(TRIM($AN34),2)="/ ",1,0) -> 0 | H34: =((LEN($AN34)-LEN(SUBSTITUTE($AN34,CHAR(10)&"~ ","")))/3)+IF(LEFT(TRIM($AN34),2)="~ ",1,0) -> 0 | I34: =((LEN($AN34)-LEN(SUBSTITUTE($AN34,CHAR(10)&"! ","")))/3)+IF(LEFT(TRIM($AN34),2)="! ",1,0) -> 0 | J34: =((LEN($AN34)-LEN(SUBSTITUTE($AN34,CHAR(10)&"x ","")))/3)+IF(LEFT(TRIM($AN34),2)="x ",1,0) -> 0 | K34: =SUM(F34:J34) -> 0 | L34: =YEAR(D34) -> 1899 | M34: =VLOOKUP(MONTH(D34),Static!$AJ$3:$AK$16,2,0) -> Dec | N34: =WEEKNUM(D34,1) -> 52 | O34: =IFERROR(INDEX(Static!$I$5:$L$15,MATCH(AA34,Static!$I$5:$I$15,0),3),"Z") -> Z | P34: =IFERROR(INDEX(Static!$I$5:$L$15,MATCH(AA34,Static!$I$5:$I$15,0),4),"Y") -> Y | Q34: =IF(D34>(($A$14-WEEKDAY($A$14,2))-7*$D$15),"Y","N") -> N | R34: =IF(AB34<>"","Y","N") -> N | S34: =IF(AND(Q34="Y",R34="N"),"Y","N") -> N | T34: =IF(OR(Y34="Y",Y34="N"),Y34,IF(AND(P34="Y", OR(Q34="Y",S34="Y")),"Y","N")) -> N | U34: ="Y" -> Y | V34: =" - "&O34&AJ34&AK34&AB34 -> - Z | W34: =IFERROR(VLOOKUP(WEEKDAY(X34),Static!$AL$3:$AM$11,2,0),"") -> Sat | X34: =IF(AD34<>"",AS34,0) -> 0 | AG34: =IF(AB34="","",AE34*AF34/8) | AO34: =SUM(F34:I34) -> 0 | AP34: =IF(AB34="",1,IF(K34<>0,(G34*0.5+J34)/K34,1)) -> 1 | AQ34: =IF(AM34="","",IF(ISERROR(FIND(CHAR(10),AM34,1)),AM34,LEFT(AM34,FIND(CHAR(10),AM34,1)))) | AR34: =IF(AM34="","",IFERROR(RIGHT(AM34,LEN(AM34)-FIND("@@@",SUBSTITUTE(AM34,CHAR(10),"@@@",LEN(AM34)-LEN(SUBSTITUTE(AM34,CHAR(10),""))),1)),AM34)) | AS34: =IFERROR(DATE(("20"&MID(AQ34,7,2))*1,MID(AQ34,4,2)*1,MID(AQ34,1,2)*1),"") | AT34: =IFERROR(DATE(("20"&MID(AR34,7,2))*1,MID(AR34,4,2)*1,MID(AR34,1,2)*1),"") | AU34: x
... B74: =IF(AH74="","tbc",AH74) -> tbc | C74: =IF(AI74="","VNT",AI74) -> VNT | D74: =MAX(X74,IF(AT74="none",X74,AT74)) -> 0 | E74: =IFERROR(DAYS360(X74,D74),0) -> 0 | F74: =((LEN($AN74)-LEN(SUBSTITUTE($AN74,CHAR(10)&". ","")))/3)+IF(LEFT(TRIM($AN74),2)=". ",1,0) -> 0 | G74: =((LEN($AN74)-LEN(SUBSTITUTE($AN74,CHAR(10)&"/ ","")))/3)+IF(LEFT(TRIM($AN74),2)="/ ",1,0) -> 0 | H74: =((LEN($AN74)-LEN(SUBSTITUTE($AN74,CHAR(10)&"~ ","")))/3)+IF(LEFT(TRIM($AN74),2)="~ ",1,0) -> 0 | I74: =((LEN($AN74)-LEN(SUBSTITUTE($AN74,CHAR(10)&"! ","")))/3)+IF(LEFT(TRIM($AN74),2)="! ",1,0) -> 0 | J74: =((LEN($AN74)-LEN(SUBSTITUTE($AN74,CHAR(10)&"x ","")))/3)+IF(LEFT(TRIM($AN74),2)="x ",1,0) -> 0 | K74: =SUM(F74:J74) -> 0 | L74: =YEAR(D74) -> 1899 | M74: =VLOOKUP(MONTH(D74),Static!$AJ$3:$AK$16,2,0) -> Dec | N74: =WEEKNUM(D74,1) -> 52 | O74: =IFERROR(INDEX(Static!$I$5:$L$15,MATCH(AA74,Static!$I$5:$I$15,0),3),"Z") -> Z | P74: =IFERROR(INDEX(Static!$I$5:$L$15,MATCH(AA74,Static!$I$5:$I$15,0),4),"Y") -> Y | Q74: =IF(D74>(($A$14-WEEKDAY($A$14,2))-7*$D$15),"Y","N") -> N | R74: =IF(AB74<>"","Y","N") -> N | S74: =IF(AND(Q74="Y",R74="N"),"Y","N") -> N | T74: =IF(OR(Y74="Y",Y74="N"),Y74,IF(AND(P74="Y", OR(Q74="Y",S74="Y")),"Y","N")) -> N | U74: ="Y" -> Y | V74: =" - "&O74&AJ74&AK74&AB74 -> - Z | W74: =IFERROR(VLOOKUP(WEEKDAY(X74),Static!$AL$3:$AM$11,2,0),"") -> Sat | X74: =IF(AD74<>"",AS74,0) -> 0 | AG74: =IF(AB74="","",AE74*AF74/8) | AO74: =SUM(F74:I74) -> 0 | AP74: =IF(AB74="",1,IF(K74<>0,(G74*0.5+J74)/K74,1)) -> 1 | AQ74: =IF(AM74="","",IF(ISERROR(FIND(CHAR(10),AM74,1)),AM74,LEFT(AM74,FIND(CHAR(10),AM74,1)))) | AR74: =IF(AM74="","",IFERROR(RIGHT(AM74,LEN(AM74)-FIND("@@@",SUBSTITUTE(AM74,CHAR(10),"@@@",LEN(AM74)-LEN(SUBSTITUTE(AM74,CHAR(10),""))),1)),AM74)) | AS74: =IFERROR(DATE(("20"&MID(AQ74,7,2))*1,MID(AQ74,4,2)*1,MID(AQ74,1,2)*1),"") | AT74: =IFERROR(DATE(("20"&MID(AR74,7,2))*1,MID(AR74,4,2)*1,MID(AR74,1,2)*1),"") | AU74: x

Sheet 01.10.Projects
C1: This space can hbe used to produce stats on below data | DZ1: x
C2: Depending on the venture it can also contain stats on data maintained elsewhere | DZ2: x
DZ3: x
A4: =A3 -> 0 | B4: =B3 -> 0 | C4: =C3 -> 0 | D4: =D3 -> 0 | E4: =E3 -> 0 | F4: =F3 -> 0 | G4: =G3 -> 0 | H4: =H3 -> 0 | ... K4: =K3 -> 0 | M4: =M3 -> 0 | N4: =N3 -> 0 | U4: =U3 -> 0 | V4: =V3 -> 0 | W4: =W3 -> 0 | X4: =X3 -> 0 | Y4: =Y3 -> 0 | Z4: =Z3 -> 0 | AA4: =AA3 -> 0 | AB4: =AB3 -> 0 | ... AD4: =AD3 -> 0 | AF4: =AF3 -> 0 | AG4: =AG3 -> 0 | AH4: =AH3 -> 0 | AI4: =AI3 -> 0 | AJ4: =AJ3 -> 0 | AK4: =AK3 -> 0 | AL4: =AL3 -> 0 | AM4: =AM3 -> 0 | ... BD4: =BD3 -> 0 | BG4: =BG3 -> 0 | BH4: =BH3 -> 0 | BI4: =BI3 -> 0 | BJ4: =BJ3 -> 0 | BK4: =BK3 -> 0 | BL4: =BL3 -> 0 | BM4: =BM3 -> 0 | BN4: =BN3 -> 0 | ... DZ4: =DZ3 -> x
DZ5: x
DZ6: x
DZ7: x
AK8: This space can be used to produce stats on below data | DZ8: x
AK9: Depending on the venture it can also contain stats on data maintained elsewhere | DZ9: x
AK10: Insert as many rows as necessary | DZ10: x
DZ11: x
DZ12: x
DZ13: x
DZ14: x
DZ15: x
DZ16: x
A17: =TODAY() -> 46321 | B17: Formula. Planning Type. Same value as the Column = Planning Type. This can be used as an extra filtering column in Pivot Tables in case Planning Type is already used as a display column. | C17: Formula. Level of the Planning Type | D17: Formula. Priority of the Goal (Run before Change) | E17: Formula. Key for the item. | F17: Formula. Priotity for the item | G17: Formula. Key of the Parent | H17: Formula. Priority of the Parent of the item | I17: Formula. Key of the Grand Parent of the item | J17: Formula. Priority of the Grand Parent of the item | K17: Formula. Key of the Great Grand parent of the item | M17: Formula. Simplified Status used for more binary reporting: an item is either completed, or else it is ongoing. | N17: Formula. Cell A1 = a formula. Column B is calculated. | O17: Calculated. Nr Tasks in Status indicated by name of this Column. The IF() is to account for the fact that typing anything at the start of a cell is not preceded the <ENTER> Character CHAR(10). | P17: Calculated. Nr Tasks in Status indicated by name of this Column. The IF() is to account for the fact that typing anything at the start of a cell is not preceded the <ENTER> Character CHAR(10). | Q17: Calculated. Nr Tasks in Status indicated by name of this Column. The IF() is to account for the fact that typing anything at the start of a cell is not preceded the <ENTER> Character CHAR(10). | R17: Calculated. Nr Tasks in Status indicated by name of this Column. The IF() is to account for the fact that typing anything at the start of a cell is not preceded the <ENTER> Character CHAR(10). | S17: Calculated. Nr Tasks in Status indicated by name of this Column. The IF() is to account for the fact that typing anything at the start of a cell is not preceded the <ENTER> Character CHAR(10). | T17: Calaculated. Sum of all Tasks in Tasks. | V17: Formula. The sum of Target Effort for all Drills/Actions within a Sub/Stream as well as the Sub/Stream itself. | W17: Formula. The sum of Target Effort for all Subs/Streams within a Routine/Project as well as the Routine/Project itself. | X17: Formula. The sum of Target Effort for all Goals within the Venture as well as the Venture itself. | Z17: Formula. The sum of Actual Effort for all Drills/Actions within a Sub/Stream as well as the Sub/Stream itself. | AA17: Formula. The sum of Actual Effort for all Subs/Streams within a Routine/Project as well as the Routine/Project itself. | AB17: Formula. The sum of Actual Effort for all Goals within the Venture as well as the Venture itself. | AC17: Unique Key that can be used in conjunction with Sheet = Delegation. | AD17: Formula. To sort the planning based on the Planning Type and priority based on date or periodicity. Sorting is first Venture, then Run Goals (alphabetically) then Change Goals (alphabettically). Within Run Goals Soring is done based on the Periodicity (daily before weekly, before monthly etc), same for Subs and Drills. Within Change Goals soring is done based on Start date. Same for Streams and then Drills. | AF17: Calculated. This shows “Yes” for all items that have an entry in Column = Notes not older than the Monday of the current week. This helps in weekly reporting. | AG17: Optional: can be used to manually force the display of reportable items. | AI17: Mandatory. The Planning type drives most of the functionality used in the formulae on this sheet. It is possible to create hiearchies as follows: - VNT - Run Goal - Routine - Sub – Drill - VNT - Change Goal - Project - Stream – Action - VNT - Routine - Sub – Drill - VNT - Project - Stream – Action | AJ17: Mandatory. Provide a Short description. For Subs/Streams indent with 4x space and for Drills/Actions indent with 8x space. Make sure it starts with a Verb which are an indication of targeted Result, see [## SMART]: - Assist: somebody in execution of their Process - Build: something new from scratch - Complete: something started elsewhere/prior - Create: same as Build - Define: Target/expected Result, next Build/Create - Deploy: as new something existing elsewhere - Expand: something existing by adding to it - Improve: something existing by automation etc. - Increase: something existing by a numeric value - Learn: how something operates - Maintain: something existing at current level - Meet: someone on regular or ad-hoc basis - Perform: one or more specific Processes - Prepare: a deliverable for completion elsewhere - Process: take in a request and deliver Result - React to: a situation with specific measures - Resolve: Problems - Review: Result vs Target + assess if change needed - Rewrite: an existing document Used in Formulas. | AK17: More detailed information w/r to the Description. Mulitple Entries possible (use Ctrl+Enter in LibreOffice, Alt+Enter in Excel). | AL17: If Venture or Goal, the start of the reporting period (mostly start of Year). If Project the Targeted start date (replace with actual start date). If Routine the first time the Routine was performed. This helps in tracking increase in workload. Used in Formulas. | AM17: If Venture or Goal the end of the reporting period (mostly the end of the year). If Project targeted end date – do not replace with actual end date unless project officialy revised. If Routine the last time the Routine was performed i.e. decommissioned. This helps in tracking decrease in workload. Used in Formulas. | AN17: If Venture, Goal or Routine (and below) leave empty. If Project the date the Project is put on Hold – status = Pending, else leave empty. Used in Formulas. | AO17: If Venture, Goal or Routine (and below) leave empty. If Project Actual Completion data of project, else empty. Used in Formulas. | AP17: Optional. IMandays per year. Used in Formulas. | AQ17: Optional. Actual mandays per year. Used in Formulas. | AR17: Mandatory. The Alias of Staff (see Sheet = Staff) or Group (see Sheet = Organising) accountable for the item. Only one Entry possible. | AS17: Mandatory. If the item is a Routine/Project (or below) the Activity in which the item is performed. If the item is Venture/Goal it is “STE”. | AT17: If Planning Type = Venture then VNT. If Planning Type = Run Goal/Chg Goal then Key of Venture. If Planning Type = Routine then Key of Run Goal it belongs to(mgt, ovh, ovs,...). If Planning Type = Project then Key of Change Goal it belongs to(gro, opt, pro, std,...). If Planning Type = Sub then Key of Routine it belongs to. If Planning Type = Drill then Key of Sub it belongs to. If Planning Type = Stream then Key of Project it belongs to. If Planning Type = Action then Key of Sub it belongs to. NB: Copy the Key from the Parent Item of the item being updated, i.e. as per above, and Paste Value in the cell in this column. In other words the following type of Hierachies exist, where each item is linked to a Parent Item by Column = Link which has the value of Column = Key of the Parent: Venture Run Goal Routine Sub Drill Chg Goal Project Stream Action Used in Formulas. | AU17: The Goal Associated to the Project. For Streams and Actions it should be the same as the project. | AV17: Optional: This column has a drop-down which is based on the value in the column to the left i.e. Sub-Goal depends on Goal. Sub-Goals for Streams and Actions should be the same as the Project they belong to. | AW17: Optional. The expected impact of the Projects (or below) on Revenue expressed in Financial Reporting currency. One entry only. | AX17: Optional. The expected impact of the Projects on Running Cost expressed in Financial Reporting currency. One entry only. | AY17: Optional. The expected impact of the Projects (or below) on Risk expressed in Financial Reporting currency. One entry only. | AZ17: The expected Cost of the Project. | BA17: The Actual Cost of the Project | BB17: Optional. Reference to more information. Can include multiple entries and refer to: Files, URL, etc. Absence of a Reference means there is no other location where information is maintained. For Goals there is always a Directory created for the Goal in question. All other items (Projects, Routines, etc.) need to be explicitly populated. | BC17: Optional. Provide further notes, updates etc.w/r to the item. Mulitple entries are possible. Items should start with “dd-mm-yy: “ (note the space behind ‘:’). Used in Formulas. | BD17: Optional. Tasks with individual Status. Multiple entries are possible. In combination with Column = Updated this column helps in Reporting. Items follow the Objective Notation as per [MGT: 99.Tools ## Objective Notation] i.e. Status Description (start:end:complete) {who} [ref] NB: Goal end Effort are not relevant for this Column. Used in Formulas. | BE17: Calculated. Nr non-completed Tasks. | BF17: Calculated. Nr Tasks non-completed Tasks over total nr Tasks as %. | BG17: Formula. The Total Target Effort of the Item as well as any children and grandchildren etc. of that item. | BH17: Formula. The total Actual Effort of the Item as well as any children and grandchildren etc. of that item. | BI17: Calculated. Progress expressed as a % of Total Effort assuming Effort is a proxy for Completion. | BJ17: Formula for first date of the Venture based on earliest entry in Column = Start Date. | BK17: Formula for next date based on previous date + value in Cell xxx1 at the end of all dates. | BL17: Formula for next date based on previous date + value in Cell xxx1 at the end of all dates. | BM17: Formula for next date based on previous date + value in Cell xxx1 at the end of all dates. | BN17: Formula for next date based on previous date + value in Cell xxx1 at the end of all dates. | BO17: Formula for next date based on previous date + value in Cell xxx1 at the end of all dates. | BP17: Formula for next date based on previous date + value in Cell xxx1 at the end of all dates. | BQ17: Formula for next date based on previous date + value in Cell xxx1 at the end of all dates. | BR17: Formula for next date based on previous date + value in Cell xxx1 at the end of all dates. | BS17: Formula for next date based on previous date + value in Cell xxx1 at the end of all dates. | BT17: Formula for next date based on previous date + value in Cell xxx1 at the end of all dates. | BU17: Formula for next date based on previous date + value in Cell xxx1 at the end of all dates. | BV17: Formula for next date based on previous date + value in Cell xxx1 at the end of all dates. | BW17: Formula for next date based on previous date + value in Cell xxx1 at the end of all dates. | BX17: Formula for next date based on previous date + value in Cell xxx1 at the end of all dates. | BY17: Formula for next date based on previous date + value in Cell xxx1 at the end of all dates. | BZ17: Formula for next date based on previous date + value in Cell xxx1 at the end of all dates. | CA17: Formula for next date based on previous date + value in Cell xxx1 at the end of all dates. | CB17: Formula for next date based on previous date + value in Cell xxx1 at the end of all dates. | CC17: Formula for next date based on previous date + value in Cell xxx1 at the end of all dates. | CD17: Formula for next date based on previous date + value in Cell xxx1 at the end of all dates. | CE17: Formula for next date based on previous date + value in Cell xxx1 at the end of all dates. | CF17: Formula for next date based on previous date + value in Cell xxx1 at the end of all dates. | CG17: Formula for next date based on previous date + value in Cell xxx1 at the end of all dates. | CH17: Formula for next date based on previous date + value in Cell xxx1 at the end of all dates. | CI17: Formula for next date based on previous date + value in Cell xxx1 at the end of all dates. | CJ17: Formula for next date based on previous date + value in Cell xxx1 at the end of all dates. | CK17: Formula for next date based on previous date + value in Cell xxx1 at the end of all dates. | CL17: Formula for next date based on previous date + value in Cell xxx1 at the end of all dates. | CM17: Formula for next date based on previous date + value in Cell xxx1 at the end of all dates. | CN17: Formula for next date based on previous date + value in Cell xxx1 at the end of all dates. | CO17: Formula for next date based on previous date + value in Cell xxx1 at the end of all dates. | CP17: Formula for next date based on previous date + value in Cell xxx1 at the end of all dates. | CQ17: Formula for next date based on previous date + value in Cell xxx1 at the end of all dates. | CR17: Formula for next date based on previous date + value in Cell xxx1 at the end of all dates. | CS17: Formula for next date based on previous date + value in Cell xxx1 at the end of all dates. | CT17: Formula for next date based on previous date + value in Cell xxx1 at the end of all dates. | CU17: Formula for next date based on previous date + value in Cell xxx1 at the end of all dates. | CV17: Formula for next date based on previous date + value in Cell xxx1 at the end of all dates. | CW17: Formula for next date based on previous date + value in Cell xxx1 at the end of all dates. | CX17: Formula for next date based on previous date + value in Cell xxx1 at the end of all dates. | CY17: Formula for next date based on previous date + value in Cell xxx1 at the end of all dates. | CZ17: Formula for next date based on previous date + value in Cell xxx1 at the end of all dates. | DA17: Formula for next date based on previous date + value in Cell xxx1 at the end of all dates. | DB17: Formula for next date based on previous date + value in Cell xxx1 at the end of all dates. | DC17: Formula for next date based on previous date + value in Cell xxx1 at the end of all dates. | DD17: Formula for next date based on previous date + value in Cell xxx1 at the end of all dates. | DE17: Formula for next date based on previous date + value in Cell xxx1 at the end of all dates. | DF17: Formula for next date based on previous date + value in Cell xxx1 at the end of all dates. | DG17: Formula for next date based on previous date + value in Cell xxx1 at the end of all dates. | DH17: Formula for next date based on previous date + value in Cell xxx1 at the end of all dates. | DI17: =(DI19-BJ19)/52 -> 14.019231 | DJ17: Formula to Calculate the first Note in Column = Notes | DK17: Formula to calculate last Note in Column = Notes | DL17: Formula to calculate last Task in Column = Tasks. | DM17: Formula to calculate Day of the First Note from Column = First Note. | DN17: Formula to calculated Day of the Last Note from Column = Last Note. | DO17: Formula to calculate the date of entry of item in this sheet based on First Note Date. | DP17: Formula to calculate the effective Update Date based on Last Note Date. | DQ17: Formula for Nr of days lapsed since Created Date. | DR17: Formula to calculate Nr days lapsed since Updated Date. | DS17: Formula to calculate nr Weeks since last updated Date. | DT17: Formula to calculate the Nr Days Overdue (only for projects) based on End Date. | DU17: Formula to calculate the nr Days before Project goes Overdue. If negative it is already Overdue. | DV17: Formula. Calculates Run / Change | DW17: Formula. Indicates the color to use in the Dynamic Calendar based on the Level | DX17: Formula. Date to be be used in the Dynamic Gantt Chart | DY17: Formula. Date to be be used in the Dynamic Gantt Chart | DZ17: End of dataset. Insert Columns before this column. | EB17: Formula to calculate nr Weeks since last updated Date.
AF18: 1 | BP18: Q | BQ18: 1 | CC18: Q | CD18: 2 | CP18: Q | CQ18: 3 | DC18: Q | DD18: 4
A19: A | B19: Item Type | C19: Lvl | D19: Goal Pty | E19: Self | F19: Self Pty | G19: Self+1 | H19: Self+1 Pty | I19: Self+2 | J19: Self+2 Pty | K19: Self+3 | L19: Self+3 Pty | M19: Report Status | N19: Status | O19: Tasks Open | P19: Tasks Started | Q19: Tasks Pending | R19: Tasks Urgent | S19: Tasks Done | T19: Tasks Total | U19: Target Drill / Action Effort | V19: Target Sub / Stream Effort | W19: Target Routine / Project Effort | X19: Target Venture Effort | Y19: Actual Drill / Action Effort | Z19: Actual Sub / Stream Effort | AA19: Actual Routine / Project Effort | AB19: Actual Venture Effort | AC19: Key | AD19: Sort | AE19: Active? | AF19: Rep ? | AG19: Force Rep? | AH19: Tag | AI19: Planning Type | AJ19: Name | AK19: Overview | AL19: Start Date | AM19: End Date | AN19: Hold Date | AO19: Complete Date | AP19: Target Effort | AQ19: Actual Effort | AR19: Whom By | AS19: Whom For | AT19: Link | AU19: Goal | AV19: Sub-Goal | AW19: Target Revenue Increase | AX19: Target Cost Savings | AY19: Target Risk Avoidance | AZ19: Target Project Cost | BA19: Actual Project Cost | BB19: Reference | BC19: Notes | BD19: Tasks | BE19: Tasks Left | BF19: Task Progress | BG19: Total Target Effort | BH19: Total Actual Effort | BI19: Effort % | BJ19: =MIN(AL20:AL56) -> 45658 | BK19: =BJ19+$DI$17 -> 45672.019 | BL19: =BK19+$DI$17 -> 45686.038 | BM19: =BL19+$DI$17 -> 45700.058 | BN19: =BM19+$DI$17 -> 45714.077 | BO19: =BN19+$DI$17 -> 45728.096 | BP19: =BO19+$DI$17 -> 45742.115 | BQ19: =BP19+$DI$17 -> 45756.135 | BR19: =BQ19+$DI$17 -> 45770.154 | ... DH19: =DG19+$DI$17 -> 46358.962 | DI19: =MAX(AM:AM,DATE(YEAR($A$17),12,31)) -> 46387 | DJ19: First Note | DK19: Last Note | DL19: Last Task | DM19: First Note Date | DN19: Last Note Date | DO19: Created Date | DP19: Updated Date | DQ19: Days since Creation | DR19: Days since Update Date | DS19: WK since Updated | DT19: Days Overdue | DU19: Days to End Date | DV19: Run / Chg | DW19: Color | DX19: Dynamic Gannt Chart Start | DY19: Dynamic Cantt Chart End | DZ19: Z
A20: =A19 -> A | B20: =B19 -> Item Type | C20: =C19 -> Lvl | D20: =AD19 -> Sort | E20: =E19 -> Self | F20: =F19 -> Self Pty | G20: =G19 -> Self+1 | H20: =H19 -> Self+1 Pty | I20: =I19 -> Self+2 | J20: =J19 -> Self+2 Pty | K20: =K19 -> Self+3 | L20: =L19 -> Self+3 Pty | ... X20: =X19 -> Target Venture Effort | Z20: =Z19 -> Actual Sub / Stream Effort | AA20: =AA19 -> Actual Routine / Project Effort | AB20: =AB19 -> Actual Venture Effort | AC20: =AC19 -> Key | AD20: =AD19 -> Sort | AE20: =AE19 -> Active? | AF20: =AF19 -> Rep ? | AG20: =AG19 -> Force Rep? | ... AS20: =AS19 -> Whom For | AT20: =AS19 -> Whom For | AU20: =AU19 -> Goal | AV20: =AV19 -> Sub-Goal | AW20: =AW19 -> Target Revenue Increase | AX20: =AX19 -> Target Cost Savings | AY20: =AY19 -> Target Risk Avoidance | AZ20: =AZ19 -> Target Project Cost | BA20: =BA19 -> Actual Project Cost | BB20: =BB19 -> Reference | BC20: =BC19 -> Notes | BD20: =AR19 -> Whom By | BE20: =BE19 -> Tasks Left | BF20: =BF19 -> Task Progress | BG20: =BG19 -> Total Target Effort | BH20: =BH19 -> Total Actual Effort | BI20: =BI19 -> Effort % | BJ20: =BJ19 -> 45658 | BK20: =BK19 -> 45672.019 | BL20: =BL19 -> 45686.038 | ... DZ20: =DZ19 -> Z
B21: =AI21 -> Venture | C21: =IFERROR(INDEX(Static!$D$5:$F$13,MATCH(AI21,Static!$D$5:$D$13,0),3),90000000) -> 10000000 | D21: =MID(C21,2,1) -> 0 | E21: =AC21 -> VNT | F21: =IF(B21="Venture",0,IF(OR(B21="Project",B21="Stream",B21="Action"),AL21,0)) -> 0 | G21: =AT21 -> VNT | H21: =IF(B21="Venture",0,IFERROR(INDEX($E$20:$F$55,MATCH(G21,$E$20:$E$55,0),2),0)) -> 0 | I21: =IF(B21="Venture",0,IFERROR(INDEX($E$20:$G$55,MATCH(G21,$E$20:$E$55,0),3),"")) -> 0 | J21: =IF(B21="Venture",0,IFERROR(INDEX($E$20:$H$55,MATCH(G21,$E$20:$E$55,0),4),0)) -> 0 | K21: =IF(B21="Venture",0,IFERROR(INDEX($E$20:$G$55,MATCH(I21,$E$20:$E$55,0),3),"")) -> 0 | L21: =IF(C21="Venture",0,IFERROR(INDEX($E$20:$G$55,MATCH(J21,$E$20:$E$55,0),4),0)) -> 0 | M21: =IF(N21="Completed","Completed","Ongoing") -> Ongoing | N21: =IF(OR(AI21="Venture",AI21="Routine",AI21="Run Goal", AI21="Chg Goal", AI21=""),AI21,IF(AO21<>"","Completed",IF(AN21<>"","Pending",IF(AND(AM21<>"",$A$17>AM21),"Overdue",IF($A$17>AL21,"Started","Open"))))) -> Venture | O21: =((LEN($BD21)-LEN(SUBSTITUTE($BD21,CHAR(10)&". ","")))/3)+IF(LEFT(TRIM($BD21),2)=". ",1,0) -> 2 | P21: =((LEN($BD21)-LEN(SUBSTITUTE($BD21,CHAR(10)&"/ ","")))/3)+IF(LEFT(TRIM($BD21),2)="/ ",1,0) -> 1 | Q21: =((LEN($BD21)-LEN(SUBSTITUTE($BD21,CHAR(10)&"~ ","")))/3)+IF(LEFT(TRIM($BD21),2)="~ ",1,0) -> 1 | R21: =((LEN($BD21)-LEN(SUBSTITUTE($BD21,CHAR(10)&"! ","")))/3)+IF(LEFT(TRIM($BD21),2)="! ",1,0) -> 1 | S21: =((LEN($BD21)-LEN(SUBSTITUTE($BD21,CHAR(10)&"x ","")))/3)+IF(LEFT(TRIM($BD21),2)="x ",1,0) -> 1 | T21: =SUM(O21:S21) -> 6 | U21: =IF(OR($B21="Drill",$B21="Action"),$AP21,0) -> 0 | V21: =IF(OR($B21="Sub",$B21="Stream"),$AP21+SUMIFS($AP$20:$AP$55,$G$20:$G$55,$E21),0) -> 0 | W21: =IF(OR($B21="Routine",$B21="Project"),$AP21+SUMIFS($V$20:$V$55,$G$20:$G$55,$E21),0) -> 0 | X21: =IF($B21="Venture",$AP21+SUMIFS($W$20:$W$55,$G$20:$G$55,$E21),0) -> 0 | Y21: =IF(OR($B21="Drill",$B21="Action"),$AQ21,0) -> 0 | Z21: =IF(OR($B21="Sub",$B21="Stream"),$AQ21+SUMIFS($AQ$20:$AQ$55,$G$20:$G$55,$E21),0) -> 0 | AA21: =IF(OR($B21="Routine",$B21="Project"),$AQ21+SUMIFS($Z$20:$Z$55,$G$20:$G$55,$E21),0) -> 0 | AB21: =IF($B21="Venture",$AQ21+SUMIFS($AA$20:$AA$55,$G$20:$G$55,$E21),0) -> 0 | AC21: =IF(AI21="Venture",AJ21,AI21&AJ21) -> VNT | AD21: =" - "&IF(E21="","ZZZ",D21&AF21&IF(OR(B21="Run Goal",B21="Chg Goal", B21="Venture"),F21&E21,IF(OR(B21="Routine",B21="Project"),H21&G21&F21&E21, IF(OR(B21="Sub",B21="Stream"),J21&I21&H21&G21&F21&E21,IF(OR(B21="Drill",B21="Action"),L21&K21&J21&I21&H21&G21&F21&E21, "") ) ))) -> - 0N0VNT | AE21: =IF(AND(AN21="",AO21=""),"Y","N") -> Y | AF21: =IF(OR(AG21="Y",AG21="Y"),AG21,IF(DN21="none","N",IF(DN21>($A$17-WEEKDAY($A$17,2)-(7*$AF$18)),"Y","N"))) -> N | AI21: Venture | AJ21: VNT | AK21: Represents the entire Venture. An overview is presented in below Sub =1.01 Maintain Context. | AL21: 45658 | AM21: 46022 | AR21: SE | AS21: STE | AT21: VNT | BC21: 01-01-22: init | BD21: . ss / ss x ll ~ hh ! uu . Task | BE21: =SUM(O21:R21) -> 5 | BF21: =IF(AJ21="",1,IF(T21<>0,(P21*0.5+S21)/T21,1)) -> 0.25 | BG21: =IF(AI21="","",IF(AI21="Venture",X21,IF(OR(AI21="Chg Goal",AI21="RUn Goal"),W21,IF(OR(AI21="ROutine",AI21="Project"),W21,IF(OR(AI21="Sub",AI21="Stream"),V21,IF(OR(AI21="Drill",AI21="Action"),U21,0)))))) -> 0 | BH21: =IF(AI21="","",IF(AI21="Venture",AB21,IF(OR(AI21="Chg Goal",AI21="RUn Goal"),AA21,IF(OR(AI21="ROutine",AI21="Project"),AA21,IF(OR(AI21="Sub",AI21="Stream"),Z21,IF(OR(AI21="Drill",AI21="Action"),Y21,0)))))) -> 0 | BI21: =IF(AJ21="","",IF(OR(BG21=0, BG21=""),0,BH21/BG21)) -> 0 | BJ21: =IF( OR( AND($C21=10000000, BJ$19>=$A$17, BJ$19 <($A$17+$DI$17) ), AND($C21<>10000000, BJ$19>=$DX21, BJ$19<=($DY21+$DI$17) )) ,$DW21, "") | BK21: =IF( OR( AND($C21=10000000, $A$17<=BK$19, ($A$17+$DI$17)>BK$19 ), AND($C21<>10000000, BK$19>=$DX21, BK$19<=($DY21+$DI$17) )) ,$DW21, "") | BL21: =IF( OR( AND($C21=10000000, $A$17<=BL$19, ($A$17+$DI$17)>BL$19 ), AND($C21<>10000000, BL$19>=$DX21, BL$19<=($DY21+$DI$17) )) ,$DW21, "") | BM21: =IF( OR( AND($C21=10000000, $A$17<=BM$19, ($A$17+$DI$17)>BM$19 ), AND($C21<>10000000, BM$19>=$DX21, BM$19<=($DY21+$DI$17) )) ,$DW21, "") | BN21: =IF( OR( AND($C21=10000000, $A$17<=BN$19, ($A$17+$DI$17)>BN$19 ), AND($C21<>10000000, BN$19>=$DX21, BN$19<=($DY21+$DI$17) )) ,$DW21, "") | BO21: =IF( OR( AND($C21=10000000, $A$17<=BO$19, ($A$17+$DI$17)>BO$19 ), AND($C21<>10000000, BO$19>=$DX21, BO$19<=($DY21+$DI$17) )) ,$DW21, "") | BP21: =IF( OR( AND($C21=10000000, $A$17<=BP$19, ($A$17+$DI$17)>BP$19 ), AND($C21<>10000000, BP$19>=$DX21, BP$19<=($DY21+$DI$17) )) ,$DW21, "") | BQ21: =IF( OR( AND($C21=10000000, $A$17<=BQ$19, ($A$17+$DI$17)>BQ$19 ), AND($C21<>10000000, BQ$19>=$DX21, BQ$19<=($DY21+$DI$17) )) ,$DW21, "") | BR21: =IF( OR( AND($C21=10000000, $A$17<=BR$19, ($A$17+$DI$17)>BR$19 ), AND($C21<>10000000, BR$19>=$DX21, BR$19<=($DY21+$DI$17) )) ,$DW21, "") | ... DI21: =IF( OR( AND($C21=10000000, $A$17<=DI$19, ($A$17+$DI$17)>DI$19 ), AND($C21<>10000000, DI$19>=$DX21, DI$19<=($DY21+$DI$17) )) ,$DW21, "") | DJ21: =IF(BC21="","",IF(ISERROR(FIND(CHAR(10),BC21,1)),BC21,LEFT(BC21,FIND(CHAR(10),BC21,1)))) -> 01-01-22: init | DK21: =IF(BC21="","",IFERROR(RIGHT(BC21,LEN(BC21)-FIND("@@@",SUBSTITUTE(BC21,CHAR(10),"@@@",LEN(BC21)-LEN(SUBSTITUTE(BC21,CHAR(10),""))),1)),BC21)) -> 01-01-22: init | DL21: =IF(BD21="","",IFERROR(RIGHT(BD21,LEN(BD21)-FIND("@@@",SUBSTITUTE(BD21,CHAR(10),"@@@",LEN(BD21)-LEN(SUBSTITUTE(BD21,CHAR(10),""))),1)),BD21)) -> . Task | DM21: =IFERROR(DATE(("20"&MID(DJ21,7,2))*1,MID(DJ21,4,2)*1,MID(DJ21,1,2)*1),"none") -> 44562 | DN21: =IFERROR(DATE(("20"&MID(DK21,7,2))*1,MID(DK21,4,2)*1,MID(DK21,1,2)*1),"none") -> 44562 | DO21: =IF(DM21<>"none",DM21,DATE(1900,1,1)) -> 44562 | DP21: =IF(DN21<>"none",DN21,DO21) -> 44562 | DQ21: =_xlfn.DAYS($A$17,DO21) -> 1759 | DR21: =_xlfn.DAYS($A$17, DP21) -> 1759 | DS21: =IF(DP21<>"",INT(DR21/7),0) -> 251 | DT21: =IF(N21="Overdue",_xlfn.DAYS($A$17,AM21),0) -> 0 | DU21: =IF(AI21="Project",_xlfn.DAYS(AM21,$A$17),0) -> 0 | DV21: =IFERROR(INDEX(Static!$D$5:$E$13,MATCH(AI21,Static!$D$5:$D$13,0),2),"") -> Run | DW21: =IF(C21=10000000,"Red",IF(OR(C21=11000000,C21=12000000),"Black",IF(C21=11100000,"Dark",IF(AND(C21=12100000,N21="Completed"),"Green",IF(AND(C21=12100000,N21="Overdue"),"Red",IF(C21=12100000,"Dark",IF(AND(C21=12110000,N21="Overdue"),"LightRed",IF(AND(C21=12110000,N21="Completed"),"LightGreen",IF(OR(C21=11110000,C21=12110000),"Light",IF(AND(C21=12111000,N21="Overdue"),"SoftRed",IF(AND(C21=12111000,N21="Completed"),"SoftGreen",IF(OR(C21=11111000,C21=12111000),"Grey","")))))))))))) -> Red | DX21: =IF(AL21<>"",AL21,$BJ$19) -> 45658 | DY21: =IF(AM21<>"",AM21,$DI$19) -> 46022 | DZ21: x
B22: =AI22 -> Chg Goal | C22: =IFERROR(INDEX(Static!$D$5:$F$13,MATCH(AI22,Static!$D$5:$D$13,0),3),90000000) -> 12000000 | D22: =MID(C22,2,1) -> 2 | E22: =AC22 -> Chg GoalDMM | F22: =IF(B22="Venture",0,IF(OR(B22="Project",B22="Stream",B22="Action"),AL22,0)) -> 0 | G22: =AT22 -> VNT | H22: =IF(B22="Venture",0,IFERROR(INDEX($E$20:$F$55,MATCH(G22,$E$20:$E$55,0),2),0)) -> 0 | I22: =IF(B22="Venture",0,IFERROR(INDEX($E$20:$G$55,MATCH(G22,$E$20:$E$55,0),3),"")) -> VNT | J22: =IF(B22="Venture",0,IFERROR(INDEX($E$20:$H$55,MATCH(G22,$E$20:$E$55,0),4),0)) -> 0 | K22: =IF(B22="Venture",0,IFERROR(INDEX($E$20:$G$55,MATCH(I22,$E$20:$E$55,0),3),"")) -> VNT | L22: =IF(C22="Venture",0,IFERROR(INDEX($E$20:$G$55,MATCH(J22,$E$20:$E$55,0),4),0)) -> 0 | M22: =IF(N22="Completed","Completed","Ongoing") -> Ongoing | N22: =IF(OR(AI22="Venture",AI22="Routine",AI22="Run Goal", AI22="Chg Goal", AI22=""),AI22,IF(AO22<>"","Completed",IF(AN22<>"","Pending",IF(AND(AM22<>"",$A$17>AM22),"Overdue",IF($A$17>AL22,"Started","Open"))))) -> Chg Goal | O22: =((LEN($BD22)-LEN(SUBSTITUTE($BD22,CHAR(10)&". ","")))/3)+IF(LEFT(TRIM($BD22),2)=". ",1,0) -> 0 | P22: =((LEN($BD22)-LEN(SUBSTITUTE($BD22,CHAR(10)&"/ ","")))/3)+IF(LEFT(TRIM($BD22),2)="/ ",1,0) -> 0 | Q22: =((LEN($BD22)-LEN(SUBSTITUTE($BD22,CHAR(10)&"~ ","")))/3)+IF(LEFT(TRIM($BD22),2)="~ ",1,0) -> 0 | R22: =((LEN($BD22)-LEN(SUBSTITUTE($BD22,CHAR(10)&"! ","")))/3)+IF(LEFT(TRIM($BD22),2)="! ",1,0) -> 0 | S22: =((LEN($BD22)-LEN(SUBSTITUTE($BD22,CHAR(10)&"x ","")))/3)+IF(LEFT(TRIM($BD22),2)="x ",1,0) -> 0 | T22: =SUM(O22:S22) -> 0 | U22: =IF(OR($B22="Drill",$B22="Action"),$AP22,0) -> 0 | V22: =IF(OR($B22="Sub",$B22="Stream"),$AP22+SUMIFS($AP$20:$AP$55,$G$20:$G$55,$E22),0) -> 0 | W22: =IF(OR($B22="Routine",$B22="Project"),$AP22+SUMIFS($V$20:$V$55,$G$20:$G$55,$E22),0) -> 0 | X22: =IF($B22="Venture",$AP22+SUMIFS($W$20:$W$55,$G$20:$G$55,$E22),0) -> 0 | Y22: =IF(OR($B22="Drill",$B22="Action"),$AQ22,0) -> 0 | Z22: =IF(OR($B22="Sub",$B22="Stream"),$AQ22+SUMIFS($AQ$20:$AQ$55,$G$20:$G$55,$E22),0) -> 0 | AA22: =IF(OR($B22="Routine",$B22="Project"),$AQ22+SUMIFS($Z$20:$Z$55,$G$20:$G$55,$E22),0) -> 0 | AB22: =IF($B22="Venture",$AQ22+SUMIFS($AA$20:$AA$55,$G$20:$G$55,$E22),0) -> 0 | AC22: =IF(AI22="Venture",AJ22,AI22&AJ22) -> Chg GoalDMM | AD22: =" - "&IF(E22="","ZZZ",D22&AF22&IF(OR(B22="Run Goal",B22="Chg Goal", B22="Venture"),F22&E22,IF(OR(B22="Routine",B22="Project"),H22&G22&F22&E22, IF(OR(B22="Sub",B22="Stream"),J22&I22&H22&G22&F22&E22,IF(OR(B22="Drill",B22="Action"),L22&K22&J22&I22&H22&G22&F22&E22, "") ) ))) -> - 2N0Chg GoalDMM | AE22: =IF(AND(AN22="",AO22=""),"Y","N") -> Y | AF22: =IF(OR(AG22="Y",AG22="Y"),AG22,IF(DN22="none","N",IF(DN22>($A$17-WEEKDAY($A$17,2)-(7*$AF$18)),"Y","N"))) -> N | AI22: Chg Goal | AJ22: DMM | AL22: 45658 | AM22: 46022 | AT22: VNT | BE22: =SUM(O22:R22) -> 0 | BF22: =IF(AJ22="",1,IF(T22<>0,(P22*0.5+S22)/T22,1)) -> 1 | BG22: =IF(AI22="","",IF(AI22="Venture",X22,IF(OR(AI22="Chg Goal",AI22="RUn Goal"),W22,IF(OR(AI22="ROutine",AI22="Project"),W22,IF(OR(AI22="Sub",AI22="Stream"),V22,IF(OR(AI22="Drill",AI22="Action"),U22,0)))))) -> 0 | BH22: =IF(AI22="","",IF(AI22="Venture",AB22,IF(OR(AI22="Chg Goal",AI22="RUn Goal"),AA22,IF(OR(AI22="ROutine",AI22="Project"),AA22,IF(OR(AI22="Sub",AI22="Stream"),Z22,IF(OR(AI22="Drill",AI22="Action"),Y22,0)))))) -> 0 | BI22: =IF(AJ22="","",IF(OR(BG22=0, BG22=""),0,BH22/BG22)) -> 0 | BJ22: =IF( OR( AND($C22=10000000, BJ$19>=$A$17, BJ$19 <($A$17+$DI$17) ), AND($C22<>10000000, BJ$19>=$DX22, BJ$19<=($DY22+$DI$17) )) ,$DW22, "") -> Black | BK22: =IF( OR( AND($C22=10000000, $A$17<=BK$19, ($A$17+$DI$17)>BK$19 ), AND($C22<>10000000, BK$19>=$DX22, BK$19<=($DY22+$DI$17) )) ,$DW22, "") -> Black | BL22: =IF( OR( AND($C22=10000000, $A$17<=BL$19, ($A$17+$DI$17)>BL$19 ), AND($C22<>10000000, BL$19>=$DX22, BL$19<=($DY22+$DI$17) )) ,$DW22, "") -> Black | BM22: =IF( OR( AND($C22=10000000, $A$17<=BM$19, ($A$17+$DI$17)>BM$19 ), AND($C22<>10000000, BM$19>=$DX22, BM$19<=($DY22+$DI$17) )) ,$DW22, "") -> Black | BN22: =IF( OR( AND($C22=10000000, $A$17<=BN$19, ($A$17+$DI$17)>BN$19 ), AND($C22<>10000000, BN$19>=$DX22, BN$19<=($DY22+$DI$17) )) ,$DW22, "") -> Black | BO22: =IF( OR( AND($C22=10000000, $A$17<=BO$19, ($A$17+$DI$17)>BO$19 ), AND($C22<>10000000, BO$19>=$DX22, BO$19<=($DY22+$DI$17) )) ,$DW22, "") -> Black | BP22: =IF( OR( AND($C22=10000000, $A$17<=BP$19, ($A$17+$DI$17)>BP$19 ), AND($C22<>10000000, BP$19>=$DX22, BP$19<=($DY22+$DI$17) )) ,$DW22, "") -> Black | BQ22: =IF( OR( AND($C22=10000000, $A$17<=BQ$19, ($A$17+$DI$17)>BQ$19 ), AND($C22<>10000000, BQ$19>=$DX22, BQ$19<=($DY22+$DI$17) )) ,$DW22, "") -> Black | BR22: =IF( OR( AND($C22=10000000, $A$17<=BR$19, ($A$17+$DI$17)>BR$19 ), AND($C22<>10000000, BR$19>=$DX22, BR$19<=($DY22+$DI$17) )) ,$DW22, "") -> Black | ... DI22: =IF( OR( AND($C22=10000000, $A$17<=DI$19, ($A$17+$DI$17)>DI$19 ), AND($C22<>10000000, DI$19>=$DX22, DI$19<=($DY22+$DI$17) )) ,$DW22, "") | DJ22: =IF(BC22="","",IF(ISERROR(FIND(CHAR(10),BC22,1)),BC22,LEFT(BC22,FIND(CHAR(10),BC22,1)))) | DK22: =IF(BC22="","",IFERROR(RIGHT(BC22,LEN(BC22)-FIND("@@@",SUBSTITUTE(BC22,CHAR(10),"@@@",LEN(BC22)-LEN(SUBSTITUTE(BC22,CHAR(10),""))),1)),BC22)) | DL22: =IF(BD22="","",IFERROR(RIGHT(BD22,LEN(BD22)-FIND("@@@",SUBSTITUTE(BD22,CHAR(10),"@@@",LEN(BD22)-LEN(SUBSTITUTE(BD22,CHAR(10),""))),1)),BD22)) | DM22: =IFERROR(DATE(("20"&MID(DJ22,7,2))*1,MID(DJ22,4,2)*1,MID(DJ22,1,2)*1),"none") -> none | DN22: =IFERROR(DATE(("20"&MID(DK22,7,2))*1,MID(DK22,4,2)*1,MID(DK22,1,2)*1),"none") -> none | DO22: =IF(DM22<>"none",DM22,DATE(1900,1,1)) -> 2 | DP22: =IF(DN22<>"none",DN22,DO22) -> 2 | DQ22: =_xlfn.DAYS($A$17,DO22) -> 46319 | DR22: =_xlfn.DAYS($A$17, DP22) -> 46319 | DS22: =IF(DP22<>"",INT(DR22/7),0) -> 6617 | DT22: =IF(N22="Overdue",_xlfn.DAYS($A$17,AM22),0) -> 0 | DU22: =IF(AI22="Project",_xlfn.DAYS(AM22,$A$17),0) -> 0 | DV22: =IFERROR(INDEX(Static!$D$5:$E$13,MATCH(AI22,Static!$D$5:$D$13,0),2),"") -> Chg | DW22: =IF(C22=10000000,"Red",IF(OR(C22=11000000,C22=12000000),"Black",IF(C22=11100000,"Dark",IF(AND(C22=12100000,N22="Completed"),"Green",IF(AND(C22=12100000,N22="Overdue"),"Red",IF(C22=12100000,"Dark",IF(AND(C22=12110000,N22="Overdue"),"LightRed",IF(AND(C22=12110000,N22="Completed"),"LightGreen",IF(OR(C22=11110000,C22=12110000),"Light",IF(AND(C22=12111000,N22="Overdue"),"SoftRed",IF(AND(C22=12111000,N22="Completed"),"SoftGreen",IF(OR(C22=11111000,C22=12111000),"Grey","")))))))))))) -> Black | DX22: =IF(AL22<>"",AL22,$BJ$19) -> 45658 | DY22: =IF(AM22<>"",AM22,$DI$19) -> 46022 | DZ22: x
B23: =AI23 -> Project | C23: =IFERROR(INDEX(Static!$D$5:$F$13,MATCH(AI23,Static!$D$5:$D$13,0),3),90000000) -> 12100000 | D23: =MID(C23,2,1) -> 2 | E23: =AC23 -> ProjectSome Study Project for sub-cat 2 | F23: =IF(B23="Venture",0,IF(OR(B23="Project",B23="Stream",B23="Action"),AL23,0)) -> 45658 | G23: =AT23 -> Chg GoalDMM | H23: =IF(B23="Venture",0,IFERROR(INDEX($E$20:$F$55,MATCH(G23,$E$20:$E$55,0),2),0)) -> 0 | I23: =IF(B23="Venture",0,IFERROR(INDEX($E$20:$G$55,MATCH(G23,$E$20:$E$55,0),3),"")) -> VNT | J23: =IF(B23="Venture",0,IFERROR(INDEX($E$20:$H$55,MATCH(G23,$E$20:$E$55,0),4),0)) -> 0 | K23: =IF(B23="Venture",0,IFERROR(INDEX($E$20:$G$55,MATCH(I23,$E$20:$E$55,0),3),"")) -> VNT | L23: =IF(C23="Venture",0,IFERROR(INDEX($E$20:$G$55,MATCH(J23,$E$20:$E$55,0),4),0)) -> 0 | M23: =IF(N23="Completed","Completed","Ongoing") -> Ongoing | N23: =IF(OR(AI23="Venture",AI23="Routine",AI23="Run Goal", AI23="Chg Goal", AI23=""),AI23,IF(AO23<>"","Completed",IF(AN23<>"","Pending",IF(AND(AM23<>"",$A$17>AM23),"Overdue",IF($A$17>AL23,"Started","Open"))))) -> Overdue | O23: =((LEN($BD23)-LEN(SUBSTITUTE($BD23,CHAR(10)&". ","")))/3)+IF(LEFT(TRIM($BD23),2)=". ",1,0) -> 0 | P23: =((LEN($BD23)-LEN(SUBSTITUTE($BD23,CHAR(10)&"/ ","")))/3)+IF(LEFT(TRIM($BD23),2)="/ ",1,0) -> 0 | Q23: =((LEN($BD23)-LEN(SUBSTITUTE($BD23,CHAR(10)&"~ ","")))/3)+IF(LEFT(TRIM($BD23),2)="~ ",1,0) -> 0 | R23: =((LEN($BD23)-LEN(SUBSTITUTE($BD23,CHAR(10)&"! ","")))/3)+IF(LEFT(TRIM($BD23),2)="! ",1,0) -> 0 | S23: =((LEN($BD23)-LEN(SUBSTITUTE($BD23,CHAR(10)&"x ","")))/3)+IF(LEFT(TRIM($BD23),2)="x ",1,0) -> 0 | T23: =SUM(O23:S23) -> 0 | U23: =IF(OR($B23="Drill",$B23="Action"),$AP23,0) -> 0 | V23: =IF(OR($B23="Sub",$B23="Stream"),$AP23+SUMIFS($AP$20:$AP$55,$G$20:$G$55,$E23),0) -> 0 | W23: =IF(OR($B23="Routine",$B23="Project"),$AP23+SUMIFS($V$20:$V$55,$G$20:$G$55,$E23),0) -> 0 | X23: =IF($B23="Venture",$AP23+SUMIFS($W$20:$W$55,$G$20:$G$55,$E23),0) -> 0 | Y23: =IF(OR($B23="Drill",$B23="Action"),$AQ23,0) -> 0 | Z23: =IF(OR($B23="Sub",$B23="Stream"),$AQ23+SUMIFS($AQ$20:$AQ$55,$G$20:$G$55,$E23),0) -> 0 | AA23: =IF(OR($B23="Routine",$B23="Project"),$AQ23+SUMIFS($Z$20:$Z$55,$G$20:$G$55,$E23),0) -> 0 | AB23: =IF($B23="Venture",$AQ23+SUMIFS($AA$20:$AA$55,$G$20:$G$55,$E23),0) -> 0 | AC23: =IF(AI23="Venture",AJ23,AI23&AJ23) -> ProjectSome Study Project for sub-cat 2 | AD23: =" - "&IF(E23="","ZZZ",D23&AF23&IF(OR(B23="Run Goal",B23="Chg Goal", B23="Venture"),F23&E23,IF(OR(B23="Routine",B23="Project"),H23&G23&F23&E23, IF(OR(B23="Sub",B23="Stream"),J23&I23&H23&G23&F23&E23,IF(OR(B23="Drill",B23="Action"),L23&K23&J23&I23&H23&G23&F23&E23, "") ) ))) -> - 2N0Chg GoalDMM45658ProjectSome Study Project for sub-cat 2 | AE23: =IF(AND(AN23="",AO23=""),"Y","N") -> Y | AF23: =IF(OR(AG23="Y",AG23="Y"),AG23,IF(DN23="none","N",IF(DN23>($A$17-WEEKDAY($A$17,2)-(7*$AF$18)),"Y","N"))) -> N | AI23: Project | AJ23: Some Study Project for sub-cat 2 | AK23: Some Project Overview | AL23: 45658 | AM23: 46022 | AR23: SE | AS23: STE | AT23: Chg GoalDMM | AU23: sec | AV23: sec 1 | BC23: 01-01-22: init | BE23: =SUM(O23:R23) -> 0 | BF23: =IF(AJ23="",1,IF(T23<>0,(P23*0.5+S23)/T23,1)) -> 1 | BG23: =IF(AI23="","",IF(AI23="Venture",X23,IF(OR(AI23="Chg Goal",AI23="RUn Goal"),W23,IF(OR(AI23="ROutine",AI23="Project"),W23,IF(OR(AI23="Sub",AI23="Stream"),V23,IF(OR(AI23="Drill",AI23="Action"),U23,0)))))) -> 0 | BH23: =IF(AI23="","",IF(AI23="Venture",AB23,IF(OR(AI23="Chg Goal",AI23="RUn Goal"),AA23,IF(OR(AI23="ROutine",AI23="Project"),AA23,IF(OR(AI23="Sub",AI23="Stream"),Z23,IF(OR(AI23="Drill",AI23="Action"),Y23,0)))))) -> 0 | BI23: =IF(AJ23="","",IF(OR(BG23=0, BG23=""),0,BH23/BG23)) -> 0 | BJ23: =IF( OR( AND($C23=10000000, BJ$19>=$A$17, BJ$19 <($A$17+$DI$17) ), AND($C23<>10000000, BJ$19>=$DX23, BJ$19<=($DY23+$DI$17) )) ,$DW23, "") -> Red | BK23: =IF( OR( AND($C23=10000000, $A$17<=BK$19, ($A$17+$DI$17)>BK$19 ), AND($C23<>10000000, BK$19>=$DX23, BK$19<=($DY23+$DI$17) )) ,$DW23, "") -> Red | BL23: =IF( OR( AND($C23=10000000, $A$17<=BL$19, ($A$17+$DI$17)>BL$19 ), AND($C23<>10000000, BL$19>=$DX23, BL$19<=($DY23+$DI$17) )) ,$DW23, "") -> Red | BM23: =IF( OR( AND($C23=10000000, $A$17<=BM$19, ($A$17+$DI$17)>BM$19 ), AND($C23<>10000000, BM$19>=$DX23, BM$19<=($DY23+$DI$17) )) ,$DW23, "") -> Red | BN23: =IF( OR( AND($C23=10000000, $A$17<=BN$19, ($A$17+$DI$17)>BN$19 ), AND($C23<>10000000, BN$19>=$DX23, BN$19<=($DY23+$DI$17) )) ,$DW23, "") -> Red | BO23: =IF( OR( AND($C23=10000000, $A$17<=BO$19, ($A$17+$DI$17)>BO$19 ), AND($C23<>10000000, BO$19>=$DX23, BO$19<=($DY23+$DI$17) )) ,$DW23, "") -> Red | BP23: =IF( OR( AND($C23=10000000, $A$17<=BP$19, ($A$17+$DI$17)>BP$19 ), AND($C23<>10000000, BP$19>=$DX23, BP$19<=($DY23+$DI$17) )) ,$DW23, "") -> Red | BQ23: =IF( OR( AND($C23=10000000, $A$17<=BQ$19, ($A$17+$DI$17)>BQ$19 ), AND($C23<>10000000, BQ$19>=$DX23, BQ$19<=($DY23+$DI$17) )) ,$DW23, "") -> Red | BR23: =IF( OR( AND($C23=10000000, $A$17<=BR$19, ($A$17+$DI$17)>BR$19 ), AND($C23<>10000000, BR$19>=$DX23, BR$19<=($DY23+$DI$17) )) ,$DW23, "") -> Red | ... DI23: =IF( OR( AND($C23=10000000, $A$17<=DI$19, ($A$17+$DI$17)>DI$19 ), AND($C23<>10000000, DI$19>=$DX23, DI$19<=($DY23+$DI$17) )) ,$DW23, "") | DJ23: =IF(BC23="","",IF(ISERROR(FIND(CHAR(10),BC23,1)),BC23,LEFT(BC23,FIND(CHAR(10),BC23,1)))) -> 01-01-22: init | DK23: =IF(BC23="","",IFERROR(RIGHT(BC23,LEN(BC23)-FIND("@@@",SUBSTITUTE(BC23,CHAR(10),"@@@",LEN(BC23)-LEN(SUBSTITUTE(BC23,CHAR(10),""))),1)),BC23)) -> 01-01-22: init | DL23: =IF(BD23="","",IFERROR(RIGHT(BD23,LEN(BD23)-FIND("@@@",SUBSTITUTE(BD23,CHAR(10),"@@@",LEN(BD23)-LEN(SUBSTITUTE(BD23,CHAR(10),""))),1)),BD23)) | DM23: =IFERROR(DATE(("20"&MID(DJ23,7,2))*1,MID(DJ23,4,2)*1,MID(DJ23,1,2)*1),"none") -> 44562 | DN23: =IFERROR(DATE(("20"&MID(DK23,7,2))*1,MID(DK23,4,2)*1,MID(DK23,1,2)*1),"none") -> 44562 | DO23: =IF(DM23<>"none",DM23,DATE(1900,1,1)) -> 44562 | DP23: =IF(DN23<>"none",DN23,DO23) -> 44562 | DQ23: =_xlfn.DAYS($A$17,DO23) -> 1759 | DR23: =_xlfn.DAYS($A$17, DP23) -> 1759 | DS23: =IF(DP23<>"",INT(DR23/7),0) -> 251 | DT23: =IF(N23="Overdue",_xlfn.DAYS($A$17,AM23),0) -> 299 | DU23: =IF(AI23="Project",_xlfn.DAYS(AM23,$A$17),0) -> -299 | DV23: =IFERROR(INDEX(Static!$D$5:$E$13,MATCH(AI23,Static!$D$5:$D$13,0),2),"") -> Chg | DW23: =IF(C23=10000000,"Red",IF(OR(C23=11000000,C23=12000000),"Black",IF(C23=11100000,"Dark",IF(AND(C23=12100000,N23="Completed"),"Green",IF(AND(C23=12100000,N23="Overdue"),"Red",IF(C23=12100000,"Dark",IF(AND(C23=12110000,N23="Overdue"),"LightRed",IF(AND(C23=12110000,N23="Completed"),"LightGreen",IF(OR(C23=11110000,C23=12110000),"Light",IF(AND(C23=12111000,N23="Overdue"),"SoftRed",IF(AND(C23=12111000,N23="Completed"),"SoftGreen",IF(OR(C23=11111000,C23=12111000),"Grey","")))))))))))) -> Red | DX23: =IF(AL23<>"",AL23,$BJ$19) -> 45658 | DY23: =IF(AM23<>"",AM23,$DI$19) -> 46022 | DZ23: x
B24: =AI24 -> Stream | C24: =IFERROR(INDEX(Static!$D$5:$F$13,MATCH(AI24,Static!$D$5:$D$13,0),3),90000000) -> 12110000 | D24: =MID(C24,2,1) -> 2 | E24: =AC24 -> Stream Some Stream of the project | F24: =IF(B24="Venture",0,IF(OR(B24="Project",B24="Stream",B24="Action"),AL24,0)) -> 45658 | G24: =AT24 -> ProjectSome Study Project for sub-cat 2 | H24: =IF(B24="Venture",0,IFERROR(INDEX($E$20:$F$55,MATCH(G24,$E$20:$E$55,0),2),0)) -> 45658 | I24: =IF(B24="Venture",0,IFERROR(INDEX($E$20:$G$55,MATCH(G24,$E$20:$E$55,0),3),"")) -> Chg GoalDMM | J24: =IF(B24="Venture",0,IFERROR(INDEX($E$20:$H$55,MATCH(G24,$E$20:$E$55,0),4),0)) -> 0 | K24: =IF(B24="Venture",0,IFERROR(INDEX($E$20:$G$55,MATCH(I24,$E$20:$E$55,0),3),"")) -> VNT | L24: =IF(C24="Venture",0,IFERROR(INDEX($E$20:$G$55,MATCH(J24,$E$20:$E$55,0),4),0)) -> 0 | M24: =IF(N24="Completed","Completed","Ongoing") -> Ongoing | N24: =IF(OR(AI24="Venture",AI24="Routine",AI24="Run Goal", AI24="Chg Goal", AI24=""),AI24,IF(AO24<>"","Completed",IF(AN24<>"","Pending",IF(AND(AM24<>"",$A$17>AM24),"Overdue",IF($A$17>AL24,"Started","Open"))))) -> Overdue | O24: =((LEN($BD24)-LEN(SUBSTITUTE($BD24,CHAR(10)&". ","")))/3)+IF(LEFT(TRIM($BD24),2)=". ",1,0) -> 0 | P24: =((LEN($BD24)-LEN(SUBSTITUTE($BD24,CHAR(10)&"/ ","")))/3)+IF(LEFT(TRIM($BD24),2)="/ ",1,0) -> 0 | Q24: =((LEN($BD24)-LEN(SUBSTITUTE($BD24,CHAR(10)&"~ ","")))/3)+IF(LEFT(TRIM($BD24),2)="~ ",1,0) -> 0 | R24: =((LEN($BD24)-LEN(SUBSTITUTE($BD24,CHAR(10)&"! ","")))/3)+IF(LEFT(TRIM($BD24),2)="! ",1,0) -> 0 | S24: =((LEN($BD24)-LEN(SUBSTITUTE($BD24,CHAR(10)&"x ","")))/3)+IF(LEFT(TRIM($BD24),2)="x ",1,0) -> 0 | T24: =SUM(O24:S24) -> 0 | U24: =IF(OR($B24="Drill",$B24="Action"),$AP24,0) -> 0 | V24: =IF(OR($B24="Sub",$B24="Stream"),$AP24+SUMIFS($AP$20:$AP$55,$G$20:$G$55,$E24),0) -> 0 | W24: =IF(OR($B24="Routine",$B24="Project"),$AP24+SUMIFS($V$20:$V$55,$G$20:$G$55,$E24),0) -> 0 | X24: =IF($B24="Venture",$AP24+SUMIFS($W$20:$W$55,$G$20:$G$55,$E24),0) -> 0 | Y24: =IF(OR($B24="Drill",$B24="Action"),$AQ24,0) -> 0 | Z24: =IF(OR($B24="Sub",$B24="Stream"),$AQ24+SUMIFS($AQ$20:$AQ$55,$G$20:$G$55,$E24),0) -> 0 | AA24: =IF(OR($B24="Routine",$B24="Project"),$AQ24+SUMIFS($Z$20:$Z$55,$G$20:$G$55,$E24),0) -> 0 | AB24: =IF($B24="Venture",$AQ24+SUMIFS($AA$20:$AA$55,$G$20:$G$55,$E24),0) -> 0 | AC24: =IF(AI24="Venture",AJ24,AI24&AJ24) -> Stream Some Stream of the project | AD24: =" - "&IF(E24="","ZZZ",D24&AF24&IF(OR(B24="Run Goal",B24="Chg Goal", B24="Venture"),F24&E24,IF(OR(B24="Routine",B24="Project"),H24&G24&F24&E24, IF(OR(B24="Sub",B24="Stream"),J24&I24&H24&G24&F24&E24,IF(OR(B24="Drill",B24="Action"),L24&K24&J24&I24&H24&G24&F24&E24, "") ) ))) -> - 2N0Chg GoalDMM45658ProjectSome Study Project for sub-cat 245658Stream Some Stream of the project | AE24: =IF(AND(AN24="",AO24=""),"Y","N") -> Y | AF24: =IF(OR(AG24="Y",AG24="Y"),AG24,IF(DN24="none","N",IF(DN24>($A$17-WEEKDAY($A$17,2)-(7*$AF$18)),"Y","N"))) -> N | AI24: Stream | AJ24: Some Stream of the project | AK24: Some Stream Overview | AL24: 45658 | AM24: 46022 | AR24: SE | AS24: STE | AT24: ProjectSome Study Project for sub-cat 2 | AU24: sec | AV24: sec 1 | BC24: 01-01-22: init | BE24: =SUM(O24:R24) -> 0 | BF24: =IF(AJ24="",1,IF(T24<>0,(P24*0.5+S24)/T24,1)) -> 1 | BG24: =IF(AI24="","",IF(AI24="Venture",X24,IF(OR(AI24="Chg Goal",AI24="RUn Goal"),W24,IF(OR(AI24="ROutine",AI24="Project"),W24,IF(OR(AI24="Sub",AI24="Stream"),V24,IF(OR(AI24="Drill",AI24="Action"),U24,0)))))) -> 0 | BH24: =IF(AI24="","",IF(AI24="Venture",AB24,IF(OR(AI24="Chg Goal",AI24="RUn Goal"),AA24,IF(OR(AI24="ROutine",AI24="Project"),AA24,IF(OR(AI24="Sub",AI24="Stream"),Z24,IF(OR(AI24="Drill",AI24="Action"),Y24,0)))))) -> 0 | BI24: =IF(AJ24="","",IF(OR(BG24=0, BG24=""),0,BH24/BG24)) -> 0 | BJ24: =IF( OR( AND($C24=10000000, BJ$19>=$A$17, BJ$19 <($A$17+$DI$17) ), AND($C24<>10000000, BJ$19>=$DX24, BJ$19<=($DY24+$DI$17) )) ,$DW24, "") -> LightRed | BK24: =IF( OR( AND($C24=10000000, $A$17<=BK$19, ($A$17+$DI$17)>BK$19 ), AND($C24<>10000000, BK$19>=$DX24, BK$19<=($DY24+$DI$17) )) ,$DW24, "") -> LightRed | BL24: =IF( OR( AND($C24=10000000, $A$17<=BL$19, ($A$17+$DI$17)>BL$19 ), AND($C24<>10000000, BL$19>=$DX24, BL$19<=($DY24+$DI$17) )) ,$DW24, "") -> LightRed | BM24: =IF( OR( AND($C24=10000000, $A$17<=BM$19, ($A$17+$DI$17)>BM$19 ), AND($C24<>10000000, BM$19>=$DX24, BM$19<=($DY24+$DI$17) )) ,$DW24, "") -> LightRed | BN24: =IF( OR( AND($C24=10000000, $A$17<=BN$19, ($A$17+$DI$17)>BN$19 ), AND($C24<>10000000, BN$19>=$DX24, BN$19<=($DY24+$DI$17) )) ,$DW24, "") -> LightRed | BO24: =IF( OR( AND($C24=10000000, $A$17<=BO$19, ($A$17+$DI$17)>BO$19 ), AND($C24<>10000000, BO$19>=$DX24, BO$19<=($DY24+$DI$17) )) ,$DW24, "") -> LightRed | BP24: =IF( OR( AND($C24=10000000, $A$17<=BP$19, ($A$17+$DI$17)>BP$19 ), AND($C24<>10000000, BP$19>=$DX24, BP$19<=($DY24+$DI$17) )) ,$DW24, "") -> LightRed | BQ24: =IF( OR( AND($C24=10000000, $A$17<=BQ$19, ($A$17+$DI$17)>BQ$19 ), AND($C24<>10000000, BQ$19>=$DX24, BQ$19<=($DY24+$DI$17) )) ,$DW24, "") -> LightRed | BR24: =IF( OR( AND($C24=10000000, $A$17<=BR$19, ($A$17+$DI$17)>BR$19 ), AND($C24<>10000000, BR$19>=$DX24, BR$19<=($DY24+$DI$17) )) ,$DW24, "") -> LightRed | ... DI24: =IF( OR( AND($C24=10000000, $A$17<=DI$19, ($A$17+$DI$17)>DI$19 ), AND($C24<>10000000, DI$19>=$DX24, DI$19<=($DY24+$DI$17) )) ,$DW24, "") | DJ24: =IF(BC24="","",IF(ISERROR(FIND(CHAR(10),BC24,1)),BC24,LEFT(BC24,FIND(CHAR(10),BC24,1)))) -> 01-01-22: init | DK24: =IF(BC24="","",IFERROR(RIGHT(BC24,LEN(BC24)-FIND("@@@",SUBSTITUTE(BC24,CHAR(10),"@@@",LEN(BC24)-LEN(SUBSTITUTE(BC24,CHAR(10),""))),1)),BC24)) -> 01-01-22: init | DL24: =IF(BD24="","",IFERROR(RIGHT(BD24,LEN(BD24)-FIND("@@@",SUBSTITUTE(BD24,CHAR(10),"@@@",LEN(BD24)-LEN(SUBSTITUTE(BD24,CHAR(10),""))),1)),BD24)) | DM24: =IFERROR(DATE(("20"&MID(DJ24,7,2))*1,MID(DJ24,4,2)*1,MID(DJ24,1,2)*1),"none") -> 44562 | DN24: =IFERROR(DATE(("20"&MID(DK24,7,2))*1,MID(DK24,4,2)*1,MID(DK24,1,2)*1),"none") -> 44562 | DO24: =IF(DM24<>"none",DM24,DATE(1900,1,1)) -> 44562 | DP24: =IF(DN24<>"none",DN24,DO24) -> 44562 | DQ24: =_xlfn.DAYS($A$17,DO24) -> 1759 | DR24: =_xlfn.DAYS($A$17, DP24) -> 1759 | DS24: =IF(DP24<>"",INT(DR24/7),0) -> 251 | DT24: =IF(N24="Overdue",_xlfn.DAYS($A$17,AM24),0) -> 299 | DU24: =IF(AI24="Project",_xlfn.DAYS(AM24,$A$17),0) -> 0 | DV24: =IFERROR(INDEX(Static!$D$5:$E$13,MATCH(AI24,Static!$D$5:$D$13,0),2),"") -> Chg | DW24: =IF(C24=10000000,"Red",IF(OR(C24=11000000,C24=12000000),"Black",IF(C24=11100000,"Dark",IF(AND(C24=12100000,N24="Completed"),"Green",IF(AND(C24=12100000,N24="Overdue"),"Red",IF(C24=12100000,"Dark",IF(AND(C24=12110000,N24="Overdue"),"LightRed",IF(AND(C24=12110000,N24="Completed"),"LightGreen",IF(OR(C24=11110000,C24=12110000),"Light",IF(AND(C24=12111000,N24="Overdue"),"SoftRed",IF(AND(C24=12111000,N24="Completed"),"SoftGreen",IF(OR(C24=11111000,C24=12111000),"Grey","")))))))))))) -> LightRed | DX24: =IF(AL24<>"",AL24,$BJ$19) -> 45658 | DY24: =IF(AM24<>"",AM24,$DI$19) -> 46022 | DZ24: x
